Workbook

Sheet MASTER Verification
A1: Project ID | B1: Project Name | C1: Primary Department | D1: Secondary Department | E1: 1st ADR | F1: 2nd ADR | G1: 3rd ADR | H1: 4th ADR | I1: 5th ADR | J1: 6th ADR
A2: SRP8-001 | B2: Doors | C2: Chassis & Bodywork
A3: SRP8-002 | B3: Door Handles | C3: Chassis & Bodywork
A4: SRP8-003 | B4: Windscreen | C4: Chassis & Bodywork | E4: ADR-93 | F4: ADR-08
A5: SRP8-004 | B5: Boot | C5: Chassis & Bodywork | E5: ADR-43
A6: SRP8-005 | B6: Bonnet | C6: Chassis & Bodywork
A7: SRP8-006 | B7: Exterior Design | C7: Chassis & Bodywork
A8: SRP8-007 | B8: Front Wheel Covers
A9: SRP8-008 | B9: Rear Wheel Covers
A10: SRP8-009 | B10: Chassis
A11: SRP8-010 | B11: Ventilation | C11: Chassis & Bodywork | D11: Energy Systems
A12: SRP8-011 | B12: Tailights | C12: Embedded Systems | D12: Chassis & Bodywork
A13: SRP8-012 | B13: Headlights | C13: Embedded Systems | D13: Chassis & Bodywork | E13: ADR-46 | F13: ADR-92 | G13: ADR-76
A14: SRP8-013 | B14: Indicators | C14: Embedded Systems | D14: Chassis & Bodywork | E14: ADR-13
A15: SRP8-014 | B15: Regen Braking | C15: Embedded Systems
A16: SRP8-015 | B16: Cruise Control | C16: Embedded Systems
A17: SRP8-016 | B17: Battery | C17: Energy Systems | D17: Chassis & Bodywork
A18: SRP8-017 | B18: Auxillary Power Distribution | C18: Energy Systems | D18: Energy Systems
A19: SRP8-018 | B19: Energy Control | C19: Energy Systems
A20: SRP8-019 | B20: MPPTs | C20: Energy Systems
A21: SRP8-020 | B21: Solar Array | C21: Energy Systems | D21: Chassis & Bodywork
A22: SRP8-021 | B22: Charging | C22: Energy Systems | D22: Chassis & Bodywork
A23: SRP8-022 | B23: Steering Wheel | C23: Interior | D23: Embedded Systems | E23: ADR-42 | F23: ADR-10 | G23: ADR-93
A24: SRP8-023 | B24: Interior Lights | C24: Interior | D24: Embedded Systems
A25: SRP8-024 | B25: Rear Vision System | C25: Interior | D25: Chassis & Bodywork
A26: SRP8-025 | B26: Side Vision System | C26: Interior | D26: Chassis & Bodywork
A27: SRP8-026 | B27: Pedals | C27: Interior
A28: SRP8-027 | B28: Ceiling | C28: Interior | D28: Chassis & Bodywork
A29: SRP8-028 | B29: Central Display | C29: Interior | D29: Chassis & Bodywork
A30: SRP8-029 | B30: Driver Display | C30: Interior | D30: Embedded Systems
A31: SRP8-030 | B31: Heads-Up Display
A32: SRP8-031 | B32: 0
A33: SRP8-032 | B33: Front Seats | C33: Interior
A34: SRP8-033 | B34: Rear Seatbelts
A35: SRP8-034 | B35: Front Seatbelts | C35: Interior | E35: ADR-69 | F35: ADR-42
A36: SRP8-035 | B36: Rear Seat Mount
A37: SRP8-036 | B37: Front Seat Mount | C37: Interior
A38: SRP8-037 | B38: Dashboard | C38: Interior
A39: SRP8-038 | B39: Motors | C39: Powertrain | D39: Chassis & Bodywork
A40: SRP8-039 | B40: Powertrain Electronics | C40: Powertrain | D40: Energy Systems
A41: SRP8-040 | B41: XXXX
A42: SRP8-041 | B42: RD Emergency Brake
A43: SRP8-042 | B43: RD LSP Units
A44: SRP8-043 | B44: Front Suspension | C44: Vehicle Dynamics | D44: Chassis & Bodywork | E44: ADR-90
A45: SRP8-044 | B45: Rear Suspension | C45: Vehicle Dynamics | D45: Chassis & Bodywork
A46: SRP8-045 | B46: Front Brakes | C46: Vehicle Dynamics | E46: ADR-31 | F46: ADR-90 | G46: ADR-42
A47: SRP8-046 | B47: Rear Brakes | C47: Vehicle Dynamics | E47: ADR-31 | F47: ADR-42
A48: SRP8-047 | B48: Handbrake | C48: Vehicle Dynamics | D48: Interior | E48: ADR-31
A49: SRP8-048 | B49: Steering Column | C49: Vehicle Dynamics | D49: Chassis & Bodywork | E49: ADR-90
A50: SRP8-049 | B50: Steering Rack | C50: Vehicle Dynamics | D50: Chassis & Bodywork
A51: SRP8-050 | B51: Front Wheels | C51: Vehicle Dynamics | E51: ADR-42 | F51: ADR-92 | G51: ADR-95 | H51: ADR-43
A52: SRP8-051 | B52: Rear Wheels | C52: Vehicle Dynamics | E52: ADR-42 | F52: ADR-92 | G52: ADR-95 | H52: ADR-43
A53: SRP8-052 | B53: BOM
A54: SRP8-053 | B54: Requirements Management
A55: SRP8-054 | B55: Performance Optimisation
A56: SRP8-055 | B56: Internal Embedded Network | C56: Embedded Systems | E56: ADR-45 | F56: ADR-90
A57: SRP8-056 | B57: Embedded Testbed | C57: Embedded Systems
A58: SRP8-057 | B58: Horn | C58: Embedded Systems | E58: ADR-94
A59: SRP8-058 | B59: Drive Control Systems | C59: Embedded Systems | D59: Powertrain
A60: SRP8-059 | B60: Sensors | C60: Embedded Systems
A61: SRP8-060 | B61: Fatigue Monitoring System | C61: Embedded Systems | D61: Interior
A62: SRP8-061 | B62: Telemetry | C62: Technical Support Systems
A63: SRP8-062 | B63: ADAS | C63: Embedded Systems
A64: SRP8-063 | B64: In Car Radio | C64: Technical Support Systems | D64: Embedded Systems
A65: SRP8-064 | B65: Wiring | E65: ADR-92
A66: SRP8-065 | B66: Occupant Cell | C66: Chassis & Bodywork | E66: ADR-93 | F66: ADR-43 | G66: ADR-92
A67: SRP8-066 | B67: Front Crash Structures | C67: Chassis & Bodywork
A68: SRP8-067 | B68: Secondary Battery Box
A69: SRP8-068 | B69: Battery Mounting
A70: SRP8-069 | B70: Charging Mounting
A71: SRP8-070 | B71: Charging Port
A72: SRP8-071 | B72: Solar Current Sensor
A73: SRP8-072 | B73: Suspension Sensor
A74: SRP8-073 | B74: Brake Pressure Sensor
A75: SRP8-074 | B75: Solar Irradiance Sensor
A76: SRP8-075 | B76: Ice Pack Vests
A77: SRP8-076 | B77: Safestate button
A78: SRP8-077 | B78: Central Stop Lamp | C78: Embedded Systems | E78: ADR-13
A79: SRP8-078 | B79: Interior Storage
A80: SRP8-079 | B80: Junction Box | C80: Energy Systems
A81: SRP8-080 | B81: Track Aero kit | C81: Chassis & Bodywork
A82: SRP8-081 | B82: Subframes | C82: Chassis & Bodywork
A83: SRP8-082 | B83: Windscreen Wipers | C83: Chassis & Bodywork
A84: SRP8-083 | B84: Active Aero | C84: Chassis & Bodywork
A85: SRP8-084 | B85: Audio | C85: Embedded Systems | D85: Interior
A86: SRP8-085 | B86: NVH | C86: Interior
A87: SRP8-086 | B87: Transmission | C87: Powertrain
A88: SRP8-087 | B88: Packaging | C88: Chassis & Bodywork
A89: SRP8-088 | B89: Front Uprights | C89: Vehicle Dynamics | E89: ADR-90
A90: SRP8-089 | B90: Rear Uprights | C90: Vehicle Dynamics
A91: SRP8-090 | B91: Wireless Charging | C91: Energy Systems
A92: SRP8-091 | B92: C-V2X | C92: Embedded Systems
A93: SRP8-092 | B93: Auxiliary Systems Logic | C93: Embedded Systems
A94: SRP8-093 | B94: Air Conditioning | C94: Chassis & Bodywork
A95: SRP8-094 | B95: Thermal management | C95: Chassis & Bodywork
A96: SRP8-095 | B96: Blind Spot Monitoring | C96: Embedded Systems
A97: SRP8-096 | B97: Park Assist | C97: Embedded Systems
A98: SRP8-097 | B98: Electronic Stability Program | C98: Embedded Systems
A99: SRP8-098 | B99: Automated Parking | C99: Embedded Systems | D99: Vehicle Dynamics
A100: SRP8-099 | B100: Traction Control | C100: Embedded Systems | D100: Powertrain
...

Sheet MASTER V&V
A1: Project ID | B1: Project Name | C1: Primary Department | D1: Secondary Department | E1: 1st ADR | F1: 2nd ADR | G1: 3rd ADR | H1: 4th ADR | I1: 5th ADR | J1: 6th ADR
A2: SRP8-001 | B2: Doors | C2: Chassis & Bodywork | E2: =IFERROR( INDEX('Project Assignment Check'!$G$1:$ZX$1, MATCH( LARGE( INDEX('ADR Tracking'!$G:$ZX, MATCH($A2, 'ADR Tracking'!$A:$A, 0), ), COLUMN()-4 ), INDEX('ADR Tracking'!$G:$ZX, MATCH($A2, 'ADR Tracking'!$A:$A, 0), ), 0 ) ), "" ) -> ADR-02 | F2: =IFERROR( INDEX('Project Assignment Check'!$G$1:$ZX$1, MATCH( LARGE( INDEX('ADR Tracking'!$G:$ZX, MATCH($A2, 'ADR Tracking'!$A:$A, 0), ), COLUMN()-4 ), INDEX('ADR Tracking'!$G:$ZX, MATCH($A2, 'ADR Tracking'!$A:$A, 0), ), 0 ) ), "" ) -> ADR-29 | G2: =IFERROR( INDEX('Project Assignment Check'!$G$1:$ZX$1, MATCH( LARGE( INDEX('ADR Tracking'!$G:$ZX, MATCH($A2, 'ADR Tracking'!$A:$A, 0), ), COLUMN()-4 ), INDEX('ADR Tracking'!$G:$ZX, MATCH($A2, 'ADR Tracking'!$A:$A, 0), ), 0 ) ), "" ) -> ADR-93 | H2: =IFERROR( INDEX('Project Assignment Check'!$G$1:$ZX$1, MATCH( LARGE( INDEX('ADR Tracking'!$G:$ZX, MATCH($A2, 'ADR Tracking'!$A:$A, 0), ), COLUMN()-4 ), INDEX('ADR Tracking'!$G:$ZX, MATCH($A2, 'ADR Tracking'!$A:$A, 0), ), 0 ) ), "" ) -> ADR-92 | I2: =IFERROR( INDEX('Project Assignment Check'!$G$1:$ZX$1, MATCH( LARGE( INDEX('ADR Tracking'!$G:$ZX, MATCH($A2, 'ADR Tracking'!$A:$A, 0), ), COLUMN()-4 ), INDEX('ADR Tracking'!$G:$ZX, MATCH($A2, 'ADR Tracking'!$A:$A, 0), ), 0 ) ), "" ) | J2: =IFERROR( INDEX('Project Assignment Check'!$G$1:$ZX$1, MATCH( LARGE( INDEX('ADR Tracking'!$G:$ZX, MATCH($A2, 'ADR Tracking'!$A:$A, 0), ), COLUMN()-4 ), INDEX('ADR Tracking'!$G:$ZX, MATCH($A2, 'ADR Tracking'!$A:$A, 0), ), 0 ) ), "" )
A3: SRP8-002 | B3: Door Handles | C3: Chassis & Bodywork | E3: =IFERROR( INDEX('Project Assignment Check'!$G$1:$ZX$1, MATCH( LARGE( INDEX('ADR Tracking'!$G:$ZX, MATCH($A3, 'ADR Tracking'!$A:$A, 0), ), COLUMN()-4 ), INDEX('ADR Tracking'!$G:$ZX, MATCH($A3, 'ADR Tracking'!$A:$A, 0), ), 0 ) ), "" ) -> ADR-92 | F3: =IFERROR( INDEX('Project Assignment Check'!$G$1:$ZX$1, MATCH( LARGE( INDEX('ADR Tracking'!$G:$ZX, MATCH($A3, 'ADR Tracking'!$A:$A, 0), ), COLUMN()-4 ), INDEX('ADR Tracking'!$G:$ZX, MATCH($A3, 'ADR Tracking'!$A:$A, 0), ), 0 ) ), "" ) | G3: =IFERROR( INDEX('Project Assignment Check'!$G$1:$ZX$1, MATCH( LARGE( INDEX('ADR Tracking'!$G:$ZX, MATCH($A3, 'ADR Tracking'!$A:$A, 0), ), COLUMN()-4 ), INDEX('ADR Tracking'!$G:$ZX, MATCH($A3, 'ADR Tracking'!$A:$A, 0), ), 0 ) ), "" ) | H3: =IFERROR( INDEX('Project Assignment Check'!$G$1:$ZX$1, MATCH( LARGE( INDEX('ADR Tracking'!$G:$ZX, MATCH($A3, 'ADR Tracking'!$A:$A, 0), ), COLUMN()-4 ), INDEX('ADR Tracking'!$G:$ZX, MATCH($A3, 'ADR Tracking'!$A:$A, 0), ), 0 ) ), "" ) | I3: =IFERROR( INDEX('Project Assignment Check'!$G$1:$ZX$1, MATCH( LARGE( INDEX('ADR Tracking'!$G:$ZX, MATCH($A3, 'ADR Tracking'!$A:$A, 0), ), COLUMN()-4 ), INDEX('ADR Tracking'!$G:$ZX, MATCH($A3, 'ADR Tracking'!$A:$A, 0), ), 0 ) ), "" ) | J3: =IFERROR( INDEX('Project Assignment Check'!$G$1:$ZX$1, MATCH( LARGE( INDEX('ADR Tracking'!$G:$ZX, MATCH($A3, 'ADR Tracking'!$A:$A, 0), ), COLUMN()-4 ), INDEX('ADR Tracking'!$G:$ZX, MATCH($A3, 'ADR Tracking'!$A:$A, 0), ), 0 ) ), "" )
A4: SRP8-003 | B4: Windscreen | C4: Chassis & Bodywork | E4: =IFERROR( INDEX('Project Assignment Check'!$G$1:$ZX$1, MATCH( LARGE( INDEX('ADR Tracking'!$G:$ZX, MATCH($A4, 'ADR Tracking'!$A:$A, 0), ), COLUMN()-4 ), INDEX('ADR Tracking'!$G:$ZX, MATCH($A4, 'ADR Tracking'!$A:$A, 0), ), 0 ) ), "" ) -> ADR-08 | F4: =IFERROR( INDEX('Project Assignment Check'!$G$1:$ZX$1, MATCH( LARGE( INDEX('ADR Tracking'!$G:$ZX, MATCH($A4, 'ADR Tracking'!$A:$A, 0), ), COLUMN()-4 ), INDEX('ADR Tracking'!$G:$ZX, MATCH($A4, 'ADR Tracking'!$A:$A, 0), ), 0 ) ), "" ) -> ADR-93 | G4: =IFERROR( INDEX('Project Assignment Check'!$G$1:$ZX$1, MATCH( LARGE( INDEX('ADR Tracking'!$G:$ZX, MATCH($A4, 'ADR Tracking'!$A:$A, 0), ), COLUMN()-4 ), INDEX('ADR Tracking'!$G:$ZX, MATCH($A4, 'ADR Tracking'!$A:$A, 0), ), 0 ) ), "" ) -> ADR-92 | H4: =IFERROR( INDEX('Project Assignment Check'!$G$1:$ZX$1, MATCH( LARGE( INDEX('ADR Tracking'!$G:$ZX, MATCH($A4, 'ADR Tracking'!$A:$A, 0), ), COLUMN()-4 ), INDEX('ADR Tracking'!$G:$ZX, MATCH($A4, 'ADR Tracking'!$A:$A, 0), ), 0 ) ), "" ) | I4: =IFERROR( INDEX('Project Assignment Check'!$G$1:$ZX$1, MATCH( LARGE( INDEX('ADR Tracking'!$G:$ZX, MATCH($A4, 'ADR Tracking'!$A:$A, 0), ), COLUMN()-4 ), INDEX('ADR Tracking'!$G:$ZX, MATCH($A4, 'ADR Tracking'!$A:$A, 0), ), 0 ) ), "" ) | J4: =IFERROR( INDEX('Project Assignment Check'!$G$1:$ZX$1, MATCH( LARGE( INDEX('ADR Tracking'!$G:$ZX, MATCH($A4, 'ADR Tracking'!$A:$A, 0), ), COLUMN()-4 ), INDEX('ADR Tracking'!$G:$ZX, MATCH($A4, 'ADR Tracking'!$A:$A, 0), ), 0 ) ), "" )
A5: SRP8-004 | B5: Boot | C5: Chassis & Bodywork | E5: =IFERROR( INDEX('Project Assignment Check'!$G$1:$ZX$1, MATCH( LARGE( INDEX('ADR Tracking'!$G:$ZX, MATCH($A5, 'ADR Tracking'!$A:$A, 0), ), COLUMN()-4 ), INDEX('ADR Tracking'!$G:$ZX, MATCH($A5, 'ADR Tracking'!$A:$A, 0), ), 0 ) ), "" ) -> ADR-92 | F5: =IFERROR( INDEX('Project Assignment Check'!$G$1:$ZX$1, MATCH( LARGE( INDEX('ADR Tracking'!$G:$ZX, MATCH($A5, 'ADR Tracking'!$A:$A, 0), ), COLUMN()-4 ), INDEX('ADR Tracking'!$G:$ZX, MATCH($A5, 'ADR Tracking'!$A:$A, 0), ), 0 ) ), "" ) -> ADR-43 | G5: =IFERROR( INDEX('Project Assignment Check'!$G$1:$ZX$1, MATCH( LARGE( INDEX('ADR Tracking'!$G:$ZX, MATCH($A5, 'ADR Tracking'!$A:$A, 0), ), COLUMN()-4 ), INDEX('ADR Tracking'!$G:$ZX, MATCH($A5, 'ADR Tracking'!$A:$A, 0), ), 0 ) ), "" ) | H5: =IFERROR( INDEX('Project Assignment Check'!$G$1:$ZX$1, MATCH( LARGE( INDEX('ADR Tracking'!$G:$ZX, MATCH($A5, 'ADR Tracking'!$A:$A, 0), ), COLUMN()-4 ), INDEX('ADR Tracking'!$G:$ZX, MATCH($A5, 'ADR Tracking'!$A:$A, 0), ), 0 ) ), "" ) | I5: =IFERROR( INDEX('Project Assignment Check'!$G$1:$ZX$1, MATCH( LARGE( INDEX('ADR Tracking'!$G:$ZX, MATCH($A5, 'ADR Tracking'!$A:$A, 0), ), COLUMN()-4 ), INDEX('ADR Tracking'!$G:$ZX, MATCH($A5, 'ADR Tracking'!$A:$A, 0), ), 0 ) ), "" ) | J5: =IFERROR( INDEX('Project Assignment Check'!$G$1:$ZX$1, MATCH( LARGE( INDEX('ADR Tracking'!$G:$ZX, MATCH($A5, 'ADR Tracking'!$A:$A, 0), ), COLUMN()-4 ), INDEX('ADR Tracking'!$G:$ZX, MATCH($A5, 'ADR Tracking'!$A:$A, 0), ), 0 ) ), "" )
A6: SRP8-005 | B6: Bonnet | C6: Chassis & Bodywork | E6: =IFERROR( INDEX('Project Assignment Check'!$G$1:$ZX$1, MATCH( LARGE( INDEX('ADR Tracking'!$G:$ZX, MATCH($A6, 'ADR Tracking'!$A:$A, 0), ), COLUMN()-4 ), INDEX('ADR Tracking'!$G:$ZX, MATCH($A6, 'ADR Tracking'!$A:$A, 0), ), 0 ) ), "" ) -> ADR-42 | F6: =IFERROR( INDEX('Project Assignment Check'!$G$1:$ZX$1, MATCH( LARGE( INDEX('ADR Tracking'!$G:$ZX, MATCH($A6, 'ADR Tracking'!$A:$A, 0), ), COLUMN()-4 ), INDEX('ADR Tracking'!$G:$ZX, MATCH($A6, 'ADR Tracking'!$A:$A, 0), ), 0 ) ), "" ) -> ADR-92 | G6: =IFERROR( INDEX('Project Assignment Check'!$G$1:$ZX$1, MATCH( LARGE( INDEX('ADR Tracking'!$G:$ZX, MATCH($A6, 'ADR Tracking'!$A:$A, 0), ), COLUMN()-4 ), INDEX('ADR Tracking'!$G:$ZX, MATCH($A6, 'ADR Tracking'!$A:$A, 0), ), 0 ) ), "" ) | H6: =IFERROR( INDEX('Project Assignment Check'!$G$1:$ZX$1, MATCH( LARGE( INDEX('ADR Tracking'!$G:$ZX, MATCH($A6, 'ADR Tracking'!$A:$A, 0), ), COLUMN()-4 ), INDEX('ADR Tracking'!$G:$ZX, MATCH($A6, 'ADR Tracking'!$A:$A, 0), ), 0 ) ), "" ) | I6: =IFERROR( INDEX('Project Assignment Check'!$G$1:$ZX$1, MATCH( LARGE( INDEX('ADR Tracking'!$G:$ZX, MATCH($A6, 'ADR Tracking'!$A:$A, 0), ), COLUMN()-4 ), INDEX('ADR Tracking'!$G:$ZX, MATCH($A6, 'ADR Tracking'!$A:$A, 0), ), 0 ) ), "" ) | J6: =IFERROR( INDEX('Project Assignment Check'!$G$1:$ZX$1, MATCH( LARGE( INDEX('ADR Tracking'!$G:$ZX, MATCH($A6, 'ADR Tracking'!$A:$A, 0), ), COLUMN()-4 ), INDEX('ADR Tracking'!$G:$ZX, MATCH($A6, 'ADR Tracking'!$A:$A, 0), ), 0 ) ), "" )
A7: SRP8-010 | B7: Ventilation | C7: Chassis & Bodywork | D7: Energy Systems | E7: =IFERROR( INDEX('Project Assignment Check'!$G$1:$ZX$1, MATCH( LARGE( INDEX('ADR Tracking'!$G:$ZX, MATCH($A7, 'ADR Tracking'!$A:$A, 0), ), COLUMN()-4 ), INDEX('ADR Tracking'!$G:$ZX, MATCH($A7, 'ADR Tracking'!$A:$A, 0), ), 0 ) ), "" ) | F7: =IFERROR( INDEX('Project Assignment Check'!$G$1:$ZX$1, MATCH( LARGE( INDEX('ADR Tracking'!$G:$ZX, MATCH($A7, 'ADR Tracking'!$A:$A, 0), ), COLUMN()-4 ), INDEX('ADR Tracking'!$G:$ZX, MATCH($A7, 'ADR Tracking'!$A:$A, 0), ), 0 ) ), "" ) | G7: =IFERROR( INDEX('Project Assignment Check'!$G$1:$ZX$1, MATCH( LARGE( INDEX('ADR Tracking'!$G:$ZX, MATCH($A7, 'ADR Tracking'!$A:$A, 0), ), COLUMN()-4 ), INDEX('ADR Tracking'!$G:$ZX, MATCH($A7, 'ADR Tracking'!$A:$A, 0), ), 0 ) ), "" ) | H7: =IFERROR( INDEX('Project Assignment Check'!$G$1:$ZX$1, MATCH( LARGE( INDEX('ADR Tracking'!$G:$ZX, MATCH($A7, 'ADR Tracking'!$A:$A, 0), ), COLUMN()-4 ), INDEX('ADR Tracking'!$G:$ZX, MATCH($A7, 'ADR Tracking'!$A:$A, 0), ), 0 ) ), "" ) | I7: =IFERROR( INDEX('Project Assignment Check'!$G$1:$ZX$1, MATCH( LARGE( INDEX('ADR Tracking'!$G:$ZX, MATCH($A7, 'ADR Tracking'!$A:$A, 0), ), COLUMN()-4 ), INDEX('ADR Tracking'!$G:$ZX, MATCH($A7, 'ADR Tracking'!$A:$A, 0), ), 0 ) ), "" ) | J7: =IFERROR( INDEX('Project Assignment Check'!$G$1:$ZX$1, MATCH( LARGE( INDEX('ADR Tracking'!$G:$ZX, MATCH($A7, 'ADR Tracking'!$A:$A, 0), ), COLUMN()-4 ), INDEX('ADR Tracking'!$G:$ZX, MATCH($A7, 'ADR Tracking'!$A:$A, 0), ), 0 ) ), "" )
A8: SRP8-011 | B8: Tailights | C8: Embedded Systems | D8: Chassis & Bodywork | E8: =IFERROR( INDEX('Project Assignment Check'!$G$1:$ZX$1, MATCH( LARGE( INDEX('ADR Tracking'!$G:$ZX, MATCH($A8, 'ADR Tracking'!$A:$A, 0), ), COLUMN()-4 ), INDEX('ADR Tracking'!$G:$ZX, MATCH($A8, 'ADR Tracking'!$A:$A, 0), ), 0 ) ), "" ) -> ADR-13 | F8: =IFERROR( INDEX('Project Assignment Check'!$G$1:$ZX$1, MATCH( LARGE( INDEX('ADR Tracking'!$G:$ZX, MATCH($A8, 'ADR Tracking'!$A:$A, 0), ), COLUMN()-4 ), INDEX('ADR Tracking'!$G:$ZX, MATCH($A8, 'ADR Tracking'!$A:$A, 0), ), 0 ) ), "" ) -> ADR-01 | G8: =IFERROR( INDEX('Project Assignment Check'!$G$1:$ZX$1, MATCH( LARGE( INDEX('ADR Tracking'!$G:$ZX, MATCH($A8, 'ADR Tracking'!$A:$A, 0), ), COLUMN()-4 ), INDEX('ADR Tracking'!$G:$ZX, MATCH($A8, 'ADR Tracking'!$A:$A, 0), ), 0 ) ), "" ) -> ADR-49 | H8: =IFERROR( INDEX('Project Assignment Check'!$G$1:$ZX$1, MATCH( LARGE( INDEX('ADR Tracking'!$G:$ZX, MATCH($A8, 'ADR Tracking'!$A:$A, 0), ), COLUMN()-4 ), INDEX('ADR Tracking'!$G:$ZX, MATCH($A8, 'ADR Tracking'!$A:$A, 0), ), 0 ) ), "" ) -> ADR-48 | I8: =IFERROR( INDEX('Project Assignment Check'!$G$1:$ZX$1, MATCH( LARGE( INDEX('ADR Tracking'!$G:$ZX, MATCH($A8, 'ADR Tracking'!$A:$A, 0), ), COLUMN()-4 ), INDEX('ADR Tracking'!$G:$ZX, MATCH($A8, 'ADR Tracking'!$A:$A, 0), ), 0 ) ), "" ) | J8: =IFERROR( INDEX('Project Assignment Check'!$G$1:$ZX$1, MATCH( LARGE( INDEX('ADR Tracking'!$G:$ZX, MATCH($A8, 'ADR Tracking'!$A:$A, 0), ), COLUMN()-4 ), INDEX('ADR Tracking'!$G:$ZX, MATCH($A8, 'ADR Tracking'!$A:$A, 0), ), 0 ) ), "" )
A9: SRP8-012 | B9: Headlights | C9: Embedded Systems | D9: Chassis & Bodywork | E9: =IFERROR( INDEX('Project Assignment Check'!$G$1:$ZX$1, MATCH( LARGE( INDEX('ADR Tracking'!$G:$ZX, MATCH($A9, 'ADR Tracking'!$A:$A, 0), ), COLUMN()-4 ), INDEX('ADR Tracking'!$G:$ZX, MATCH($A9, 'ADR Tracking'!$A:$A, 0), ), 0 ) ), "" ) -> ADR-13 | F9: =IFERROR( INDEX('Project Assignment Check'!$G$1:$ZX$1, MATCH( LARGE( INDEX('ADR Tracking'!$G:$ZX, MATCH($A9, 'ADR Tracking'!$A:$A, 0), ), COLUMN()-4 ), INDEX('ADR Tracking'!$G:$ZX, MATCH($A9, 'ADR Tracking'!$A:$A, 0), ), 0 ) ), "" ) -> ADR-76 | G9: =IFERROR( INDEX('Project Assignment Check'!$G$1:$ZX$1, MATCH( LARGE( INDEX('ADR Tracking'!$G:$ZX, MATCH($A9, 'ADR Tracking'!$A:$A, 0), ), COLUMN()-4 ), INDEX('ADR Tracking'!$G:$ZX, MATCH($A9, 'ADR Tracking'!$A:$A, 0), ), 0 ) ), "" ) -> ADR-46 | H9: =IFERROR( INDEX('Project Assignment Check'!$G$1:$ZX$1, MATCH( LARGE( INDEX('ADR Tracking'!$G:$ZX, MATCH($A9, 'ADR Tracking'!$A:$A, 0), ), COLUMN()-4 ), INDEX('ADR Tracking'!$G:$ZX, MATCH($A9, 'ADR Tracking'!$A:$A, 0), ), 0 ) ), "" ) -> ADR-92 | I9: =IFERROR( INDEX('Project Assignment Check'!$G$1:$ZX$1, MATCH( LARGE( INDEX('ADR Tracking'!$G:$ZX, MATCH($A9, 'ADR Tracking'!$A:$A, 0), ), COLUMN()-4 ), INDEX('ADR Tracking'!$G:$ZX, MATCH($A9, 'ADR Tracking'!$A:$A, 0), ), 0 ) ), "" ) -> ADR-06 | J9: =IFERROR( INDEX('Project Assignment Check'!$G$1:$ZX$1, MATCH( LARGE( INDEX('ADR Tracking'!$G:$ZX, MATCH($A9, 'ADR Tracking'!$A:$A, 0), ), COLUMN()-4 ), INDEX('ADR Tracking'!$G:$ZX, MATCH($A9, 'ADR Tracking'!$A:$A, 0), ), 0 ) ), "" )
A10: SRP8-013 | B10: Indicators | C10: Embedded Systems | D10: Chassis & Bodywork | E10: =IFERROR( INDEX('Project Assignment Check'!$G$1:$ZX$1, MATCH( LARGE( INDEX('ADR Tracking'!$G:$ZX, MATCH($A10, 'ADR Tracking'!$A:$A, 0), ), COLUMN()-4 ), INDEX('ADR Tracking'!$G:$ZX, MATCH($A10, 'ADR Tracking'!$A:$A, 0), ), 0 ) ), "" ) -> ADR-13 | F10: =IFERROR( INDEX('Project Assignment Check'!$G$1:$ZX$1, MATCH( LARGE( INDEX('ADR Tracking'!$G:$ZX, MATCH($A10, 'ADR Tracking'!$A:$A, 0), ), COLUMN()-4 ), INDEX('ADR Tracking'!$G:$ZX, MATCH($A10, 'ADR Tracking'!$A:$A, 0), ), 0 ) ), "" ) -> ADR-06 | G10: =IFERROR( INDEX('Project Assignment Check'!$G$1:$ZX$1, MATCH( LARGE( INDEX('ADR Tracking'!$G:$ZX, MATCH($A10, 'ADR Tracking'!$A:$A, 0), ), COLUMN()-4 ), INDEX('ADR Tracking'!$G:$ZX, MATCH($A10, 'ADR Tracking'!$A:$A, 0), ), 0 ) ), "" ) | H10: =IFERROR( INDEX('Project Assignment Check'!$G$1:$ZX$1, MATCH( LARGE( INDEX('ADR Tracking'!$G:$ZX, MATCH($A10, 'ADR Tracking'!$A:$A, 0), ), COLUMN()-4 ), INDEX('ADR Tracking'!$G:$ZX, MATCH($A10, 'ADR Tracking'!$A:$A, 0), ), 0 ) ), "" ) | I10: =IFERROR( INDEX('Project Assignment Check'!$G$1:$ZX$1, MATCH( LARGE( INDEX('ADR Tracking'!$G:$ZX, MATCH($A10, 'ADR Tracking'!$A:$A, 0), ), COLUMN()-4 ), INDEX('ADR Tracking'!$G:$ZX, MATCH($A10, 'ADR Tracking'!$A:$A, 0), ), 0 ) ), "" ) | J10: =IFERROR( INDEX('Project Assignment Check'!$G$1:$ZX$1, MATCH( LARGE( INDEX('ADR Tracking'!$G:$ZX, MATCH($A10, 'ADR Tracking'!$A:$A, 0), ), COLUMN()-4 ), INDEX('ADR Tracking'!$G:$ZX, MATCH($A10, 'ADR Tracking'!$A:$A, 0), ), 0 ) ), "" )
A11: SRP8-014 | B11: Regen Braking | C11: Embedded Systems | E11: =IFERROR( INDEX('Project Assignment Check'!$G$1:$ZX$1, MATCH( LARGE( INDEX('ADR Tracking'!$G:$ZX, MATCH($A11, 'ADR Tracking'!$A:$A, 0), ), COLUMN()-4 ), INDEX('ADR Tracking'!$G:$ZX, MATCH($A11, 'ADR Tracking'!$A:$A, 0), ), 0 ) ), "" ) -> ADR-31 | F11: =IFERROR( INDEX('Project Assignment Check'!$G$1:$ZX$1, MATCH( LARGE( INDEX('ADR Tracking'!$G:$ZX, MATCH($A11, 'ADR Tracking'!$A:$A, 0), ), COLUMN()-4 ), INDEX('ADR Tracking'!$G:$ZX, MATCH($A11, 'ADR Tracking'!$A:$A, 0), ), 0 ) ), "" ) | G11: =IFERROR( INDEX('Project Assignment Check'!$G$1:$ZX$1, MATCH( LARGE( INDEX('ADR Tracking'!$G:$ZX, MATCH($A11, 'ADR Tracking'!$A:$A, 0), ), COLUMN()-4 ), INDEX('ADR Tracking'!$G:$ZX, MATCH($A11, 'ADR Tracking'!$A:$A, 0), ), 0 ) ), "" ) | H11: =IFERROR( INDEX('Project Assignment Check'!$G$1:$ZX$1, MATCH( LARGE( INDEX('ADR Tracking'!$G:$ZX, MATCH($A11, 'ADR Tracking'!$A:$A, 0), ), COLUMN()-4 ), INDEX('ADR Tracking'!$G:$ZX, MATCH($A11, 'ADR Tracking'!$A:$A, 0), ), 0 ) ), "" ) | I11: =IFERROR( INDEX('Project Assignment Check'!$G$1:$ZX$1, MATCH( LARGE( INDEX('ADR Tracking'!$G:$ZX, MATCH($A11, 'ADR Tracking'!$A:$A, 0), ), COLUMN()-4 ), INDEX('ADR Tracking'!$G:$ZX, MATCH($A11, 'ADR Tracking'!$A:$A, 0), ), 0 ) ), "" ) | J11: =IFERROR( INDEX('Project Assignment Check'!$G$1:$ZX$1, MATCH( LARGE( INDEX('ADR Tracking'!$G:$ZX, MATCH($A11, 'ADR Tracking'!$A:$A, 0), ), COLUMN()-4 ), INDEX('ADR Tracking'!$G:$ZX, MATCH($A11, 'ADR Tracking'!$A:$A, 0), ), 0 ) ), "" )
A12: SRP8-016 | B12: Battery | C12: Energy Systems | D12: Chassis & Bodywork | E12: =IFERROR( INDEX('Project Assignment Check'!$G$1:$ZX$1, MATCH( LARGE( INDEX('ADR Tracking'!$G:$ZX, MATCH($A12, 'ADR Tracking'!$A:$A, 0), ), COLUMN()-4 ), INDEX('ADR Tracking'!$G:$ZX, MATCH($A12, 'ADR Tracking'!$A:$A, 0), ), 0 ) ), "" ) -> ADR-109 | F12: =IFERROR( INDEX('Project Assignment Check'!$G$1:$ZX$1, MATCH( LARGE( INDEX('ADR Tracking'!$G:$ZX, MATCH($A12, 'ADR Tracking'!$A:$A, 0), ), COLUMN()-4 ), INDEX('ADR Tracking'!$G:$ZX, MATCH($A12, 'ADR Tracking'!$A:$A, 0), ), 0 ) ), "" ) | G12: =IFERROR( INDEX('Project Assignment Check'!$G$1:$ZX$1, MATCH( LARGE( INDEX('ADR Tracking'!$G:$ZX, MATCH($A12, 'ADR Tracking'!$A:$A, 0), ), COLUMN()-4 ), INDEX('ADR Tracking'!$G:$ZX, MATCH($A12, 'ADR Tracking'!$A:$A, 0), ), 0 ) ), "" ) | H12: =IFERROR( INDEX('Project Assignment Check'!$G$1:$ZX$1, MATCH( LARGE( INDEX('ADR Tracking'!$G:$ZX, MATCH($A12, 'ADR Tracking'!$A:$A, 0), ), COLUMN()-4 ), INDEX('ADR Tracking'!$G:$ZX, MATCH($A12, 'ADR Tracking'!$A:$A, 0), ), 0 ) ), "" ) | I12: =IFERROR( INDEX('Project Assignment Check'!$G$1:$ZX$1, MATCH( LARGE( INDEX('ADR Tracking'!$G:$ZX, MATCH($A12, 'ADR Tracking'!$A:$A, 0), ), COLUMN()-4 ), INDEX('ADR Tracking'!$G:$ZX, MATCH($A12, 'ADR Tracking'!$A:$A, 0), ), 0 ) ), "" ) | J12: =IFERROR( INDEX('Project Assignment Check'!$G$1:$ZX$1, MATCH( LARGE( INDEX('ADR Tracking'!$G:$ZX, MATCH($A12, 'ADR Tracking'!$A:$A, 0), ), COLUMN()-4 ), INDEX('ADR Tracking'!$G:$ZX, MATCH($A12, 'ADR Tracking'!$A:$A, 0), ), 0 ) ), "" )
A13: SRP8-017 | B13: Auxillary Power Distribution | C13: Energy Systems | D13: Energy Systems | E13: =IFERROR( INDEX('Project Assignment Check'!$G$1:$ZX$1, MATCH( LARGE( INDEX('ADR Tracking'!$G:$ZX, MATCH($A13, 'ADR Tracking'!$A:$A, 0), ), COLUMN()-4 ), INDEX('ADR Tracking'!$G:$ZX, MATCH($A13, 'ADR Tracking'!$A:$A, 0), ), 0 ) ), "" ) | F13: =IFERROR( INDEX('Project Assignment Check'!$G$1:$ZX$1, MATCH( LARGE( INDEX('ADR Tracking'!$G:$ZX, MATCH($A13, 'ADR Tracking'!$A:$A, 0), ), COLUMN()-4 ), INDEX('ADR Tracking'!$G:$ZX, MATCH($A13, 'ADR Tracking'!$A:$A, 0), ), 0 ) ), "" ) | G13: =IFERROR( INDEX('Project Assignment Check'!$G$1:$ZX$1, MATCH( LARGE( INDEX('ADR Tracking'!$G:$ZX, MATCH($A13, 'ADR Tracking'!$A:$A, 0), ), COLUMN()-4 ), INDEX('ADR Tracking'!$G:$ZX, MATCH($A13, 'ADR Tracking'!$A:$A, 0), ), 0 ) ), "" ) | H13: =IFERROR( INDEX('Project Assignment Check'!$G$1:$ZX$1, MATCH( LARGE( INDEX('ADR Tracking'!$G:$ZX, MATCH($A13, 'ADR Tracking'!$A:$A, 0), ), COLUMN()-4 ), INDEX('ADR Tracking'!$G:$ZX, MATCH($A13, 'ADR Tracking'!$A:$A, 0), ), 0 ) ), "" ) | I13: =IFERROR( INDEX('Project Assignment Check'!$G$1:$ZX$1, MATCH( LARGE( INDEX('ADR Tracking'!$G:$ZX, MATCH($A13, 'ADR Tracking'!$A:$A, 0), ), COLUMN()-4 ), INDEX('ADR Tracking'!$G:$ZX, MATCH($A13, 'ADR Tracking'!$A:$A, 0), ), 0 ) ), "" ) | J13: =IFERROR( INDEX('Project Assignment Check'!$G$1:$ZX$1, MATCH( LARGE( INDEX('ADR Tracking'!$G:$ZX, MATCH($A13, 'ADR Tracking'!$A:$A, 0), ), COLUMN()-4 ), INDEX('ADR Tracking'!$G:$ZX, MATCH($A13, 'ADR Tracking'!$A:$A, 0), ), 0 ) ), "" )
A14: SRP8-018 | B14: Energy Control | C14: Energy Systems | E14: =IFERROR( INDEX('Project Assignment Check'!$G$1:$ZX$1, MATCH( LARGE( INDEX('ADR Tracking'!$G:$ZX, MATCH($A14, 'ADR Tracking'!$A:$A, 0), ), COLUMN()-4 ), INDEX('ADR Tracking'!$G:$ZX, MATCH($A14, 'ADR Tracking'!$A:$A, 0), ), 0 ) ), "" ) -> ADR-90 | F14: =IFERROR( INDEX('Project Assignment Check'!$G$1:$ZX$1, MATCH( LARGE( INDEX('ADR Tracking'!$G:$ZX, MATCH($A14, 'ADR Tracking'!$A:$A, 0), ), COLUMN()-4 ), INDEX('ADR Tracking'!$G:$ZX, MATCH($A14, 'ADR Tracking'!$A:$A, 0), ), 0 ) ), "" ) -> ADR-90 | G14: =IFERROR( INDEX('Project Assignment Check'!$G$1:$ZX$1, MATCH( LARGE( INDEX('ADR Tracking'!$G:$ZX, MATCH($A14, 'ADR Tracking'!$A:$A, 0), ), COLUMN()-4 ), INDEX('ADR Tracking'!$G:$ZX, MATCH($A14, 'ADR Tracking'!$A:$A, 0), ), 0 ) ), "" ) | H14: =IFERROR( INDEX('Project Assignment Check'!$G$1:$ZX$1, MATCH( LARGE( INDEX('ADR Tracking'!$G:$ZX, MATCH($A14, 'ADR Tracking'!$A:$A, 0), ), COLUMN()-4 ), INDEX('ADR Tracking'!$G:$ZX, MATCH($A14, 'ADR Tracking'!$A:$A, 0), ), 0 ) ), "" ) | I14: =IFERROR( INDEX('Project Assignment Check'!$G$1:$ZX$1, MATCH( LARGE( INDEX('ADR Tracking'!$G:$ZX, MATCH($A14, 'ADR Tracking'!$A:$A, 0), ), COLUMN()-4 ), INDEX('ADR Tracking'!$G:$ZX, MATCH($A14, 'ADR Tracking'!$A:$A, 0), ), 0 ) ), "" ) | J14: =IFERROR( INDEX('Project Assignment Check'!$G$1:$ZX$1, MATCH( LARGE( INDEX('ADR Tracking'!$G:$ZX, MATCH($A14, 'ADR Tracking'!$A:$A, 0), ), COLUMN()-4 ), INDEX('ADR Tracking'!$G:$ZX, MATCH($A14, 'ADR Tracking'!$A:$A, 0), ), 0 ) ), "" )
A15: SRP8-019 | B15: MPPTs | C15: Energy Systems | E15: =IFERROR( INDEX('Project Assignment Check'!$G$1:$ZX$1, MATCH( LARGE( INDEX('ADR Tracking'!$G:$ZX, MATCH($A15, 'ADR Tracking'!$A:$A, 0), ), COLUMN()-4 ), INDEX('ADR Tracking'!$G:$ZX, MATCH($A15, 'ADR Tracking'!$A:$A, 0), ), 0 ) ), "" ) | F15: =IFERROR( INDEX('Project Assignment Check'!$G$1:$ZX$1, MATCH( LARGE( INDEX('ADR Tracking'!$G:$ZX, MATCH($A15, 'ADR Tracking'!$A:$A, 0), ), COLUMN()-4 ), INDEX('ADR Tracking'!$G:$ZX, MATCH($A15, 'ADR Tracking'!$A:$A, 0), ), 0 ) ), "" ) | G15: =IFERROR( INDEX('Project Assignment Check'!$G$1:$ZX$1, MATCH( LARGE( INDEX('ADR Tracking'!$G:$ZX, MATCH($A15, 'ADR Tracking'!$A:$A, 0), ), COLUMN()-4 ), INDEX('ADR Tracking'!$G:$ZX, MATCH($A15, 'ADR Tracking'!$A:$A, 0), ), 0 ) ), "" ) | H15: =IFERROR( INDEX('Project Assignment Check'!$G$1:$ZX$1, MATCH( LARGE( INDEX('ADR Tracking'!$G:$ZX, MATCH($A15, 'ADR Tracking'!$A:$A, 0), ), COLUMN()-4 ), INDEX('ADR Tracking'!$G:$ZX, MATCH($A15, 'ADR Tracking'!$A:$A, 0), ), 0 ) ), "" ) | I15: =IFERROR( INDEX('Project Assignment Check'!$G$1:$ZX$1, MATCH( LARGE( INDEX('ADR Tracking'!$G:$ZX, MATCH($A15, 'ADR Tracking'!$A:$A, 0), ), COLUMN()-4 ), INDEX('ADR Tracking'!$G:$ZX, MATCH($A15, 'ADR Tracking'!$A:$A, 0), ), 0 ) ), "" ) | J15: =IFERROR( INDEX('Project Assignment Check'!$G$1:$ZX$1, MATCH( LARGE( INDEX('ADR Tracking'!$G:$ZX, MATCH($A15, 'ADR Tracking'!$A:$A, 0), ), COLUMN()-4 ), INDEX('ADR Tracking'!$G:$ZX, MATCH($A15, 'ADR Tracking'!$A:$A, 0), ), 0 ) ), "" )
A16: SRP8-020 | B16: Solar Array | C16: Energy Systems | D16: Chassis & Bodywork | E16: =IFERROR( INDEX('Project Assignment Check'!$G$1:$ZX$1, MATCH( LARGE( INDEX('ADR Tracking'!$G:$ZX, MATCH($A16, 'ADR Tracking'!$A:$A, 0), ), COLUMN()-4 ), INDEX('ADR Tracking'!$G:$ZX, MATCH($A16, 'ADR Tracking'!$A:$A, 0), ), 0 ) ), "" ) | F16: =IFERROR( INDEX('Project Assignment Check'!$G$1:$ZX$1, MATCH( LARGE( INDEX('ADR Tracking'!$G:$ZX, MATCH($A16, 'ADR Tracking'!$A:$A, 0), ), COLUMN()-4 ), INDEX('ADR Tracking'!$G:$ZX, MATCH($A16, 'ADR Tracking'!$A:$A, 0), ), 0 ) ), "" ) | G16: =IFERROR( INDEX('Project Assignment Check'!$G$1:$ZX$1, MATCH( LARGE( INDEX('ADR Tracking'!$G:$ZX, MATCH($A16, 'ADR Tracking'!$A:$A, 0), ), COLUMN()-4 ), INDEX('ADR Tracking'!$G:$ZX, MATCH($A16, 'ADR Tracking'!$A:$A, 0), ), 0 ) ), "" ) | H16: =IFERROR( INDEX('Project Assignment Check'!$G$1:$ZX$1, MATCH( LARGE( INDEX('ADR Tracking'!$G:$ZX, MATCH($A16, 'ADR Tracking'!$A:$A, 0), ), COLUMN()-4 ), INDEX('ADR Tracking'!$G:$ZX, MATCH($A16, 'ADR Tracking'!$A:$A, 0), ), 0 ) ), "" ) | I16: =IFERROR( INDEX('Project Assignment Check'!$G$1:$ZX$1, MATCH( LARGE( INDEX('ADR Tracking'!$G:$ZX, MATCH($A16, 'ADR Tracking'!$A:$A, 0), ), COLUMN()-4 ), INDEX('ADR Tracking'!$G:$ZX, MATCH($A16, 'ADR Tracking'!$A:$A, 0), ), 0 ) ), "" ) | J16: =IFERROR( INDEX('Project Assignment Check'!$G$1:$ZX$1, MATCH( LARGE( INDEX('ADR Tracking'!$G:$ZX, MATCH($A16, 'ADR Tracking'!$A:$A, 0), ), COLUMN()-4 ), INDEX('ADR Tracking'!$G:$ZX, MATCH($A16, 'ADR Tracking'!$A:$A, 0), ), 0 ) ), "" )
A17: SRP8-021 | B17: Charging | C17: Energy Systems | D17: Chassis & Bodywork | E17: =IFERROR( INDEX('Project Assignment Check'!$G$1:$ZX$1, MATCH( LARGE( INDEX('ADR Tracking'!$G:$ZX, MATCH($A17, 'ADR Tracking'!$A:$A, 0), ), COLUMN()-4 ), INDEX('ADR Tracking'!$G:$ZX, MATCH($A17, 'ADR Tracking'!$A:$A, 0), ), 0 ) ), "" ) -> ADR-109 | F17: =IFERROR( INDEX('Project Assignment Check'!$G$1:$ZX$1, MATCH( LARGE( INDEX('ADR Tracking'!$G:$ZX, MATCH($A17, 'ADR Tracking'!$A:$A, 0), ), COLUMN()-4 ), INDEX('ADR Tracking'!$G:$ZX, MATCH($A17, 'ADR Tracking'!$A:$A, 0), ), 0 ) ), "" ) | G17: =IFERROR( INDEX('Project Assignment Check'!$G$1:$ZX$1, MATCH( LARGE( INDEX('ADR Tracking'!$G:$ZX, MATCH($A17, 'ADR Tracking'!$A:$A, 0), ), COLUMN()-4 ), INDEX('ADR Tracking'!$G:$ZX, MATCH($A17, 'ADR Tracking'!$A:$A, 0), ), 0 ) ), "" ) | H17: =IFERROR( INDEX('Project Assignment Check'!$G$1:$ZX$1, MATCH( LARGE( INDEX('ADR Tracking'!$G:$ZX, MATCH($A17, 'ADR Tracking'!$A:$A, 0), ), COLUMN()-4 ), INDEX('ADR Tracking'!$G:$ZX, MATCH($A17, 'ADR Tracking'!$A:$A, 0), ), 0 ) ), "" ) | I17: =IFERROR( INDEX('Project Assignment Check'!$G$1:$ZX$1, MATCH( LARGE( INDEX('ADR Tracking'!$G:$ZX, MATCH($A17, 'ADR Tracking'!$A:$A, 0), ), COLUMN()-4 ), INDEX('ADR Tracking'!$G:$ZX, MATCH($A17, 'ADR Tracking'!$A:$A, 0), ), 0 ) ), "" ) | J17: =IFERROR( INDEX('Project Assignment Check'!$G$1:$ZX$1, MATCH( LARGE( INDEX('ADR Tracking'!$G:$ZX, MATCH($A17, 'ADR Tracking'!$A:$A, 0), ), COLUMN()-4 ), INDEX('ADR Tracking'!$G:$ZX, MATCH($A17, 'ADR Tracking'!$A:$A, 0), ), 0 ) ), "" )
A18: SRP8-022 | B18: Steering Wheel | C18: Interior | D18: Embedded Systems | E18: =IFERROR( INDEX('Project Assignment Check'!$G$1:$ZX$1, MATCH( LARGE( INDEX('ADR Tracking'!$G:$ZX, MATCH($A18, 'ADR Tracking'!$A:$A, 0), ), COLUMN()-4 ), INDEX('ADR Tracking'!$G:$ZX, MATCH($A18, 'ADR Tracking'!$A:$A, 0), ), 0 ) ), "" ) -> ADR-10 | F18: =IFERROR( INDEX('Project Assignment Check'!$G$1:$ZX$1, MATCH( LARGE( INDEX('ADR Tracking'!$G:$ZX, MATCH($A18, 'ADR Tracking'!$A:$A, 0), ), COLUMN()-4 ), INDEX('ADR Tracking'!$G:$ZX, MATCH($A18, 'ADR Tracking'!$A:$A, 0), ), 0 ) ), "" ) -> ADR-10 | G18: =IFERROR( INDEX('Project Assignment Check'!$G$1:$ZX$1, MATCH( LARGE( INDEX('ADR Tracking'!$G:$ZX, MATCH($A18, 'ADR Tracking'!$A:$A, 0), ), COLUMN()-4 ), INDEX('ADR Tracking'!$G:$ZX, MATCH($A18, 'ADR Tracking'!$A:$A, 0), ), 0 ) ), "" ) -> ADR-93 | H18: =IFERROR( INDEX('Project Assignment Check'!$G$1:$ZX$1, MATCH( LARGE( INDEX('ADR Tracking'!$G:$ZX, MATCH($A18, 'ADR Tracking'!$A:$A, 0), ), COLUMN()-4 ), INDEX('ADR Tracking'!$G:$ZX, MATCH($A18, 'ADR Tracking'!$A:$A, 0), ), 0 ) ), "" ) | I18: =IFERROR( INDEX('Project Assignment Check'!$G$1:$ZX$1, MATCH( LARGE( INDEX('ADR Tracking'!$G:$ZX, MATCH($A18, 'ADR Tracking'!$A:$A, 0), ), COLUMN()-4 ), INDEX('ADR Tracking'!$G:$ZX, MATCH($A18, 'ADR Tracking'!$A:$A, 0), ), 0 ) ), "" ) | J18: =IFERROR( INDEX('Project Assignment Check'!$G$1:$ZX$1, MATCH( LARGE( INDEX('ADR Tracking'!$G:$ZX, MATCH($A18, 'ADR Tracking'!$A:$A, 0), ), COLUMN()-4 ), INDEX('ADR Tracking'!$G:$ZX, MATCH($A18, 'ADR Tracking'!$A:$A, 0), ), 0 ) ), "" )
A19: SRP8-023 | B19: Interior Lights | C19: Interior | D19: Embedded Systems | E19: =IFERROR( INDEX('Project Assignment Check'!$G$1:$ZX$1, MATCH( LARGE( INDEX('ADR Tracking'!$G:$ZX, MATCH($A19, 'ADR Tracking'!$A:$A, 0), ), COLUMN()-4 ), INDEX('ADR Tracking'!$G:$ZX, MATCH($A19, 'ADR Tracking'!$A:$A, 0), ), 0 ) ), "" ) | F19: =IFERROR( INDEX('Project Assignment Check'!$G$1:$ZX$1, MATCH( LARGE( INDEX('ADR Tracking'!$G:$ZX, MATCH($A19, 'ADR Tracking'!$A:$A, 0), ), COLUMN()-4 ), INDEX('ADR Tracking'!$G:$ZX, MATCH($A19, 'ADR Tracking'!$A:$A, 0), ), 0 ) ), "" ) | G19: =IFERROR( INDEX('Project Assignment Check'!$G$1:$ZX$1, MATCH( LARGE( INDEX('ADR Tracking'!$G:$ZX, MATCH($A19, 'ADR Tracking'!$A:$A, 0), ), COLUMN()-4 ), INDEX('ADR Tracking'!$G:$ZX, MATCH($A19, 'ADR Tracking'!$A:$A, 0), ), 0 ) ), "" ) | H19: =IFERROR( INDEX('Project Assignment Check'!$G$1:$ZX$1, MATCH( LARGE( INDEX('ADR Tracking'!$G:$ZX, MATCH($A19, 'ADR Tracking'!$A:$A, 0), ), COLUMN()-4 ), INDEX('ADR Tracking'!$G:$ZX, MATCH($A19, 'ADR Tracking'!$A:$A, 0), ), 0 ) ), "" ) | I19: =IFERROR( INDEX('Project Assignment Check'!$G$1:$ZX$1, MATCH( LARGE( INDEX('ADR Tracking'!$G:$ZX, MATCH($A19, 'ADR Tracking'!$A:$A, 0), ), COLUMN()-4 ), INDEX('ADR Tracking'!$G:$ZX, MATCH($A19, 'ADR Tracking'!$A:$A, 0), ), 0 ) ), "" ) | J19: =IFERROR( INDEX('Project Assignment Check'!$G$1:$ZX$1, MATCH( LARGE( INDEX('ADR Tracking'!$G:$ZX, MATCH($A19, 'ADR Tracking'!$A:$A, 0), ), COLUMN()-4 ), INDEX('ADR Tracking'!$G:$ZX, MATCH($A19, 'ADR Tracking'!$A:$A, 0), ), 0 ) ), "" )
A20: SRP8-024 | B20: Rear Vision System | C20: Interior | D20: Chassis & Bodywork | E20: =IFERROR( INDEX('Project Assignment Check'!$G$1:$ZX$1, MATCH( LARGE( INDEX('ADR Tracking'!$G:$ZX, MATCH($A20, 'ADR Tracking'!$A:$A, 0), ), COLUMN()-4 ), INDEX('ADR Tracking'!$G:$ZX, MATCH($A20, 'ADR Tracking'!$A:$A, 0), ), 0 ) ), "" ) -> ADR-14 | F20: =IFERROR( INDEX('Project Assignment Check'!$G$1:$ZX$1, MATCH( LARGE( INDEX('ADR Tracking'!$G:$ZX, MATCH($A20, 'ADR Tracking'!$A:$A, 0), ), COLUMN()-4 ), INDEX('ADR Tracking'!$G:$ZX, MATCH($A20, 'ADR Tracking'!$A:$A, 0), ), 0 ) ), "" ) | G20: =IFERROR( INDEX('Project Assignment Check'!$G$1:$ZX$1, MATCH( LARGE( INDEX('ADR Tracking'!$G:$ZX, MATCH($A20, 'ADR Tracking'!$A:$A, 0), ), COLUMN()-4 ), INDEX('ADR Tracking'!$G:$ZX, MATCH($A20, 'ADR Tracking'!$A:$A, 0), ), 0 ) ), "" ) | H20: =IFERROR( INDEX('Project Assignment Check'!$G$1:$ZX$1, MATCH( LARGE( INDEX('ADR Tracking'!$G:$ZX, MATCH($A20, 'ADR Tracking'!$A:$A, 0), ), COLUMN()-4 ), INDEX('ADR Tracking'!$G:$ZX, MATCH($A20, 'ADR Tracking'!$A:$A, 0), ), 0 ) ), "" ) | I20: =IFERROR( INDEX('Project Assignment Check'!$G$1:$ZX$1, MATCH( LARGE( INDEX('ADR Tracking'!$G:$ZX, MATCH($A20, 'ADR Tracking'!$A:$A, 0), ), COLUMN()-4 ), INDEX('ADR Tracking'!$G:$ZX, MATCH($A20, 'ADR Tracking'!$A:$A, 0), ), 0 ) ), "" ) | J20: =IFERROR( INDEX('Project Assignment Check'!$G$1:$ZX$1, MATCH( LARGE( INDEX('ADR Tracking'!$G:$ZX, MATCH($A20, 'ADR Tracking'!$A:$A, 0), ), COLUMN()-4 ), INDEX('ADR Tracking'!$G:$ZX, MATCH($A20, 'ADR Tracking'!$A:$A, 0), ), 0 ) ), "" )
A21: SRP8-025 | B21: Side Vision System | C21: Interior | D21: Chassis & Bodywork | E21: =IFERROR( INDEX('Project Assignment Check'!$G$1:$ZX$1, MATCH( LARGE( INDEX('ADR Tracking'!$G:$ZX, MATCH($A21, 'ADR Tracking'!$A:$A, 0), ), COLUMN()-4 ), INDEX('ADR Tracking'!$G:$ZX, MATCH($A21, 'ADR Tracking'!$A:$A, 0), ), 0 ) ), "" ) | F21: =IFERROR( INDEX('Project Assignment Check'!$G$1:$ZX$1, MATCH( LARGE( INDEX('ADR Tracking'!$G:$ZX, MATCH($A21, 'ADR Tracking'!$A:$A, 0), ), COLUMN()-4 ), INDEX('ADR Tracking'!$G:$ZX, MATCH($A21, 'ADR Tracking'!$A:$A, 0), ), 0 ) ), "" ) | G21: =IFERROR( INDEX('Project Assignment Check'!$G$1:$ZX$1, MATCH( LARGE( INDEX('ADR Tracking'!$G:$ZX, MATCH($A21, 'ADR Tracking'!$A:$A, 0), ), COLUMN()-4 ), INDEX('ADR Tracking'!$G:$ZX, MATCH($A21, 'ADR Tracking'!$A:$A, 0), ), 0 ) ), "" ) | H21: =IFERROR( INDEX('Project Assignment Check'!$G$1:$ZX$1, MATCH( LARGE( INDEX('ADR Tracking'!$G:$ZX, MATCH($A21, 'ADR Tracking'!$A:$A, 0), ), COLUMN()-4 ), INDEX('ADR Tracking'!$G:$ZX, MATCH($A21, 'ADR Tracking'!$A:$A, 0), ), 0 ) ), "" ) | I21: =IFERROR( INDEX('Project Assignment Check'!$G$1:$ZX$1, MATCH( LARGE( INDEX('ADR Tracking'!$G:$ZX, MATCH($A21, 'ADR Tracking'!$A:$A, 0), ), COLUMN()-4 ), INDEX('ADR Tracking'!$G:$ZX, MATCH($A21, 'ADR Tracking'!$A:$A, 0), ), 0 ) ), "" ) | J21: =IFERROR( INDEX('Project Assignment Check'!$G$1:$ZX$1, MATCH( LARGE( INDEX('ADR Tracking'!$G:$ZX, MATCH($A21, 'ADR Tracking'!$A:$A, 0), ), COLUMN()-4 ), INDEX('ADR Tracking'!$G:$ZX, MATCH($A21, 'ADR Tracking'!$A:$A, 0), ), 0 ) ), "" )
A22: SRP8-026 | B22: Pedals | C22: Interior | E22: =IFERROR( INDEX('Project Assignment Check'!$G$1:$ZX$1, MATCH( LARGE( INDEX('ADR Tracking'!$G:$ZX, MATCH($A22, 'ADR Tracking'!$A:$A, 0), ), COLUMN()-4 ), INDEX('ADR Tracking'!$G:$ZX, MATCH($A22, 'ADR Tracking'!$A:$A, 0), ), 0 ) ), "" ) -> ADR-31 | F22: =IFERROR( INDEX('Project Assignment Check'!$G$1:$ZX$1, MATCH( LARGE( INDEX('ADR Tracking'!$G:$ZX, MATCH($A22, 'ADR Tracking'!$A:$A, 0), ), COLUMN()-4 ), INDEX('ADR Tracking'!$G:$ZX, MATCH($A22, 'ADR Tracking'!$A:$A, 0), ), 0 ) ), "" ) | G22: =IFERROR( INDEX('Project Assignment Check'!$G$1:$ZX$1, MATCH( LARGE( INDEX('ADR Tracking'!$G:$ZX, MATCH($A22, 'ADR Tracking'!$A:$A, 0), ), COLUMN()-4 ), INDEX('ADR Tracking'!$G:$ZX, MATCH($A22, 'ADR Tracking'!$A:$A, 0), ), 0 ) ), "" ) | H22: =IFERROR( INDEX('Project Assignment Check'!$G$1:$ZX$1, MATCH( LARGE( INDEX('ADR Tracking'!$G:$ZX, MATCH($A22, 'ADR Tracking'!$A:$A, 0), ), COLUMN()-4 ), INDEX('ADR Tracking'!$G:$ZX, MATCH($A22, 'ADR Tracking'!$A:$A, 0), ), 0 ) ), "" ) | I22: =IFERROR( INDEX('Project Assignment Check'!$G$1:$ZX$1, MATCH( LARGE( INDEX('ADR Tracking'!$G:$ZX, MATCH($A22, 'ADR Tracking'!$A:$A, 0), ), COLUMN()-4 ), INDEX('ADR Tracking'!$G:$ZX, MATCH($A22, 'ADR Tracking'!$A:$A, 0), ), 0 ) ), "" ) | J22: =IFERROR( INDEX('Project Assignment Check'!$G$1:$ZX$1, MATCH( LARGE( INDEX('ADR Tracking'!$G:$ZX, MATCH($A22, 'ADR Tracking'!$A:$A, 0), ), COLUMN()-4 ), INDEX('ADR Tracking'!$G:$ZX, MATCH($A22, 'ADR Tracking'!$A:$A, 0), ), 0 ) ), "" )
A23: SRP8-027 | B23: Ceiling | C23: Interior | D23: Chassis & Bodywork | E23: =IFERROR( INDEX('Project Assignment Check'!$G$1:$ZX$1, MATCH( LARGE( INDEX('ADR Tracking'!$G:$ZX, MATCH($A23, 'ADR Tracking'!$A:$A, 0), ), COLUMN()-4 ), INDEX('ADR Tracking'!$G:$ZX, MATCH($A23, 'ADR Tracking'!$A:$A, 0), ), 0 ) ), "" ) -> ADR-11 | F23: =IFERROR( INDEX('Project Assignment Check'!$G$1:$ZX$1, MATCH( LARGE( INDEX('ADR Tracking'!$G:$ZX, MATCH($A23, 'ADR Tracking'!$A:$A, 0), ), COLUMN()-4 ), INDEX('ADR Tracking'!$G:$ZX, MATCH($A23, 'ADR Tracking'!$A:$A, 0), ), 0 ) ), "" ) -> ADR-21 | G23: =IFERROR( INDEX('Project Assignment Check'!$G$1:$ZX$1, MATCH( LARGE( INDEX('ADR Tracking'!$G:$ZX, MATCH($A23, 'ADR Tracking'!$A:$A, 0), ), COLUMN()-4 ), INDEX('ADR Tracking'!$G:$ZX, MATCH($A23, 'ADR Tracking'!$A:$A, 0), ), 0 ) ), "" ) -> ADR-42 | H23: =IFERROR( INDEX('Project Assignment Check'!$G$1:$ZX$1, MATCH( LARGE( INDEX('ADR Tracking'!$G:$ZX, MATCH($A23, 'ADR Tracking'!$A:$A, 0), ), COLUMN()-4 ), INDEX('ADR Tracking'!$G:$ZX, MATCH($A23, 'ADR Tracking'!$A:$A, 0), ), 0 ) ), "" ) | I23: =IFERROR( INDEX('Project Assignment Check'!$G$1:$ZX$1, MATCH( LARGE( INDEX('ADR Tracking'!$G:$ZX, MATCH($A23, 'ADR Tracking'!$A:$A, 0), ), COLUMN()-4 ), INDEX('ADR Tracking'!$G:$ZX, MATCH($A23, 'ADR Tracking'!$A:$A, 0), ), 0 ) ), "" ) | J23: =IFERROR( INDEX('Project Assignment Check'!$G$1:$ZX$1, MATCH( LARGE( INDEX('ADR Tracking'!$G:$ZX, MATCH($A23, 'ADR Tracking'!$A:$A, 0), ), COLUMN()-4 ), INDEX('ADR Tracking'!$G:$ZX, MATCH($A23, 'ADR Tracking'!$A:$A, 0), ), 0 ) ), "" )
A24: SRP8-028 | B24: Central Display | C24: Interior | D24: Chassis & Bodywork | E24: =IFERROR( INDEX('Project Assignment Check'!$G$1:$ZX$1, MATCH( LARGE( INDEX('ADR Tracking'!$G:$ZX, MATCH($A24, 'ADR Tracking'!$A:$A, 0), ), COLUMN()-4 ), INDEX('ADR Tracking'!$G:$ZX, MATCH($A24, 'ADR Tracking'!$A:$A, 0), ), 0 ) ), "" ) -> ADR-42 | F24: =IFERROR( INDEX('Project Assignment Check'!$G$1:$ZX$1, MATCH( LARGE( INDEX('ADR Tracking'!$G:$ZX, MATCH($A24, 'ADR Tracking'!$A:$A, 0), ), COLUMN()-4 ), INDEX('ADR Tracking'!$G:$ZX, MATCH($A24, 'ADR Tracking'!$A:$A, 0), ), 0 ) ), "" ) -> ADR-21 | G24: =IFERROR( INDEX('Project Assignment Check'!$G$1:$ZX$1, MATCH( LARGE( INDEX('ADR Tracking'!$G:$ZX, MATCH($A24, 'ADR Tracking'!$A:$A, 0), ), COLUMN()-4 ), INDEX('ADR Tracking'!$G:$ZX, MATCH($A24, 'ADR Tracking'!$A:$A, 0), ), 0 ) ), "" ) | H24: =IFERROR( INDEX('Project Assignment Check'!$G$1:$ZX$1, MATCH( LARGE( INDEX('ADR Tracking'!$G:$ZX, MATCH($A24, 'ADR Tracking'!$A:$A, 0), ), COLUMN()-4 ), INDEX('ADR Tracking'!$G:$ZX, MATCH($A24, 'ADR Tracking'!$A:$A, 0), ), 0 ) ), "" ) | I24: =IFERROR( INDEX('Project Assignment Check'!$G$1:$ZX$1, MATCH( LARGE( INDEX('ADR Tracking'!$G:$ZX, MATCH($A24, 'ADR Tracking'!$A:$A, 0), ), COLUMN()-4 ), INDEX('ADR Tracking'!$G:$ZX, MATCH($A24, 'ADR Tracking'!$A:$A, 0), ), 0 ) ), "" ) | J24: =IFERROR( INDEX('Project Assignment Check'!$G$1:$ZX$1, MATCH( LARGE( INDEX('ADR Tracking'!$G:$ZX, MATCH($A24, 'ADR Tracking'!$A:$A, 0), ), COLUMN()-4 ), INDEX('ADR Tracking'!$G:$ZX, MATCH($A24, 'ADR Tracking'!$A:$A, 0), ), 0 ) ), "" )
A25: SRP8-029 | B25: Driver Display | C25: Interior | D25: Embedded Systems | E25: =IFERROR( INDEX('Project Assignment Check'!$G$1:$ZX$1, MATCH( LARGE( INDEX('ADR Tracking'!$G:$ZX, MATCH($A25, 'ADR Tracking'!$A:$A, 0), ), COLUMN()-4 ), INDEX('ADR Tracking'!$G:$ZX, MATCH($A25, 'ADR Tracking'!$A:$A, 0), ), 0 ) ), "" ) -> ADR-42 | F25: =IFERROR( INDEX('Project Assignment Check'!$G$1:$ZX$1, MATCH( LARGE( INDEX('ADR Tracking'!$G:$ZX, MATCH($A25, 'ADR Tracking'!$A:$A, 0), ), COLUMN()-4 ), INDEX('ADR Tracking'!$G:$ZX, MATCH($A25, 'ADR Tracking'!$A:$A, 0), ), 0 ) ), "" ) -> ADR-18 | G25: =IFERROR( INDEX('Project Assignment Check'!$G$1:$ZX$1, MATCH( LARGE( INDEX('ADR Tracking'!$G:$ZX, MATCH($A25, 'ADR Tracking'!$A:$A, 0), ), COLUMN()-4 ), INDEX('ADR Tracking'!$G:$ZX, MATCH($A25, 'ADR Tracking'!$A:$A, 0), ), 0 ) ), "" ) -> ADR-18 | H25: =IFERROR( INDEX('Project Assignment Check'!$G$1:$ZX$1, MATCH( LARGE( INDEX('ADR Tracking'!$G:$ZX, MATCH($A25, 'ADR Tracking'!$A:$A, 0), ), COLUMN()-4 ), INDEX('ADR Tracking'!$G:$ZX, MATCH($A25, 'ADR Tracking'!$A:$A, 0), ), 0 ) ), "" ) -> ADR-31 | I25: =IFERROR( INDEX('Project Assignment Check'!$G$1:$ZX$1, MATCH( LARGE( INDEX('ADR Tracking'!$G:$ZX, MATCH($A25, 'ADR Tracking'!$A:$A, 0), ), COLUMN()-4 ), INDEX('ADR Tracking'!$G:$ZX, MATCH($A25, 'ADR Tracking'!$A:$A, 0), ), 0 ) ), "" ) -> ADR-90 | J25: =IFERROR( INDEX('Project Assignment Check'!$G$1:$ZX$1, MATCH( LARGE( INDEX('ADR Tracking'!$G:$ZX, MATCH($A25, 'ADR Tracking'!$A:$A, 0), ), COLUMN()-4 ), INDEX('ADR Tracking'!$G:$ZX, MATCH($A25, 'ADR Tracking'!$A:$A, 0), ), 0 ) ), "" ) -> ADR-90
A26: SRP8-032 | B26: Front Seats | C26: Interior | E26: =IFERROR( INDEX('Project Assignment Check'!$G$1:$ZX$1, MATCH( LARGE( INDEX('ADR Tracking'!$G:$ZX, MATCH($A26, 'ADR Tracking'!$A:$A, 0), ), COLUMN()-4 ), INDEX('ADR Tracking'!$G:$ZX, MATCH($A26, 'ADR Tracking'!$A:$A, 0), ), 0 ) ), "" ) -> ADR-03 | F26: =IFERROR( INDEX('Project Assignment Check'!$G$1:$ZX$1, MATCH( LARGE( INDEX('ADR Tracking'!$G:$ZX, MATCH($A26, 'ADR Tracking'!$A:$A, 0), ), COLUMN()-4 ), INDEX('ADR Tracking'!$G:$ZX, MATCH($A26, 'ADR Tracking'!$A:$A, 0), ), 0 ) ), "" ) -> ADR-21 | G26: =IFERROR( INDEX('Project Assignment Check'!$G$1:$ZX$1, MATCH( LARGE( INDEX('ADR Tracking'!$G:$ZX, MATCH($A26, 'ADR Tracking'!$A:$A, 0), ), COLUMN()-4 ), INDEX('ADR Tracking'!$G:$ZX, MATCH($A26, 'ADR Tracking'!$A:$A, 0), ), 0 ) ), "" ) -> ADR-42 | H26: =IFERROR( INDEX('Project Assignment Check'!$G$1:$ZX$1, MATCH( LARGE( INDEX('ADR Tracking'!$G:$ZX, MATCH($A26, 'ADR Tracking'!$A:$A, 0), ), COLUMN()-4 ), INDEX('ADR Tracking'!$G:$ZX, MATCH($A26, 'ADR Tracking'!$A:$A, 0), ), 0 ) ), "" ) -> ADR-42 | I26: =IFERROR( INDEX('Project Assignment Check'!$G$1:$ZX$1, MATCH( LARGE( INDEX('ADR Tracking'!$G:$ZX, MATCH($A26, 'ADR Tracking'!$A:$A, 0), ), COLUMN()-4 ), INDEX('ADR Tracking'!$G:$ZX, MATCH($A26, 'ADR Tracking'!$A:$A, 0), ), 0 ) ), "" ) | J26: =IFERROR( INDEX('Project Assignment Check'!$G$1:$ZX$1, MATCH( LARGE( INDEX('ADR Tracking'!$G:$ZX, MATCH($A26, 'ADR Tracking'!$A:$A, 0), ), COLUMN()-4 ), INDEX('ADR Tracking'!$G:$ZX, MATCH($A26, 'ADR Tracking'!$A:$A, 0), ), 0 ) ), "" )
A27: SRP8-034 | B27: Front Seatbelts | C27: Interior | E27: =IFERROR( INDEX('Project Assignment Check'!$G$1:$ZX$1, MATCH( LARGE( INDEX('ADR Tracking'!$G:$ZX, MATCH($A27, 'ADR Tracking'!$A:$A, 0), ), COLUMN()-4 ), INDEX('ADR Tracking'!$G:$ZX, MATCH($A27, 'ADR Tracking'!$A:$A, 0), ), 0 ) ), "" ) -> ADR-04 | F27: =IFERROR( INDEX('Project Assignment Check'!$G$1:$ZX$1, MATCH( LARGE( INDEX('ADR Tracking'!$G:$ZX, MATCH($A27, 'ADR Tracking'!$A:$A, 0), ), COLUMN()-4 ), INDEX('ADR Tracking'!$G:$ZX, MATCH($A27, 'ADR Tracking'!$A:$A, 0), ), 0 ) ), "" ) -> ADR-05 | G27: =IFERROR( INDEX('Project Assignment Check'!$G$1:$ZX$1, MATCH( LARGE( INDEX('ADR Tracking'!$G:$ZX, MATCH($A27, 'ADR Tracking'!$A:$A, 0), ), COLUMN()-4 ), INDEX('ADR Tracking'!$G:$ZX, MATCH($A27, 'ADR Tracking'!$A:$A, 0), ), 0 ) ), "" ) -> ADR-69 | H27: =IFERROR( INDEX('Project Assignment Check'!$G$1:$ZX$1, MATCH( LARGE( INDEX('ADR Tracking'!$G:$ZX, MATCH($A27, 'ADR Tracking'!$A:$A, 0), ), COLUMN()-4 ), INDEX('ADR Tracking'!$G:$ZX, MATCH($A27, 'ADR Tracking'!$A:$A, 0), ), 0 ) ), "" ) -> ADR-42 | I27: =IFERROR( INDEX('Project Assignment Check'!$G$1:$ZX$1, MATCH( LARGE( INDEX('ADR Tracking'!$G:$ZX, MATCH($A27, 'ADR Tracking'!$A:$A, 0), ), COLUMN()-4 ), INDEX('ADR Tracking'!$G:$ZX, MATCH($A27, 'ADR Tracking'!$A:$A, 0), ), 0 ) ), "" ) | J27: =IFERROR( INDEX('Project Assignment Check'!$G$1:$ZX$1, MATCH( LARGE( INDEX('ADR Tracking'!$G:$ZX, MATCH($A27, 'ADR Tracking'!$A:$A, 0), ), COLUMN()-4 ), INDEX('ADR Tracking'!$G:$ZX, MATCH($A27, 'ADR Tracking'!$A:$A, 0), ), 0 ) ), "" )
A28: SRP8-036 | B28: Front Seat Mount | C28: Interior | E28: =IFERROR( INDEX('Project Assignment Check'!$G$1:$ZX$1, MATCH( LARGE( INDEX('ADR Tracking'!$G:$ZX, MATCH($A28, 'ADR Tracking'!$A:$A, 0), ), COLUMN()-4 ), INDEX('ADR Tracking'!$G:$ZX, MATCH($A28, 'ADR Tracking'!$A:$A, 0), ), 0 ) ), "" ) -> ADR-03 | F28: =IFERROR( INDEX('Project Assignment Check'!$G$1:$ZX$1, MATCH( LARGE( INDEX('ADR Tracking'!$G:$ZX, MATCH($A28, 'ADR Tracking'!$A:$A, 0), ), COLUMN()-4 ), INDEX('ADR Tracking'!$G:$ZX, MATCH($A28, 'ADR Tracking'!$A:$A, 0), ), 0 ) ), "" ) -> ADR-42 | G28: =IFERROR( INDEX('Project Assignment Check'!$G$1:$ZX$1, MATCH( LARGE( INDEX('ADR Tracking'!$G:$ZX, MATCH($A28, 'ADR Tracking'!$A:$A, 0), ), COLUMN()-4 ), INDEX('ADR Tracking'!$G:$ZX, MATCH($A28, 'ADR Tracking'!$A:$A, 0), ), 0 ) ), "" ) | H28: =IFERROR( INDEX('Project Assignment Check'!$G$1:$ZX$1, MATCH( LARGE( INDEX('ADR Tracking'!$G:$ZX, MATCH($A28, 'ADR Tracking'!$A:$A, 0), ), COLUMN()-4 ), INDEX('ADR Tracking'!$G:$ZX, MATCH($A28, 'ADR Tracking'!$A:$A, 0), ), 0 ) ), "" ) | I28: =IFERROR( INDEX('Project Assignment Check'!$G$1:$ZX$1, MATCH( LARGE( INDEX('ADR Tracking'!$G:$ZX, MATCH($A28, 'ADR Tracking'!$A:$A, 0), ), COLUMN()-4 ), INDEX('ADR Tracking'!$G:$ZX, MATCH($A28, 'ADR Tracking'!$A:$A, 0), ), 0 ) ), "" ) | J28: =IFERROR( INDEX('Project Assignment Check'!$G$1:$ZX$1, MATCH( LARGE( INDEX('ADR Tracking'!$G:$ZX, MATCH($A28, 'ADR Tracking'!$A:$A, 0), ), COLUMN()-4 ), INDEX('ADR Tracking'!$G:$ZX, MATCH($A28, 'ADR Tracking'!$A:$A, 0), ), 0 ) ), "" )
A29: SRP8-037 | B29: Dashboard | C29: Interior | E29: =IFERROR( INDEX('Project Assignment Check'!$G$1:$ZX$1, MATCH( LARGE( INDEX('ADR Tracking'!$G:$ZX, MATCH($A29, 'ADR Tracking'!$A:$A, 0), ), COLUMN()-4 ), INDEX('ADR Tracking'!$G:$ZX, MATCH($A29, 'ADR Tracking'!$A:$A, 0), ), 0 ) ), "" ) -> ADR-21 | F29: =IFERROR( INDEX('Project Assignment Check'!$G$1:$ZX$1, MATCH( LARGE( INDEX('ADR Tracking'!$G:$ZX, MATCH($A29, 'ADR Tracking'!$A:$A, 0), ), COLUMN()-4 ), INDEX('ADR Tracking'!$G:$ZX, MATCH($A29, 'ADR Tracking'!$A:$A, 0), ), 0 ) ), "" ) | G29: =IFERROR( INDEX('Project Assignment Check'!$G$1:$ZX$1, MATCH( LARGE( INDEX('ADR Tracking'!$G:$ZX, MATCH($A29, 'ADR Tracking'!$A:$A, 0), ), COLUMN()-4 ), INDEX('ADR Tracking'!$G:$ZX, MATCH($A29, 'ADR Tracking'!$A:$A, 0), ), 0 ) ), "" ) | H29: =IFERROR( INDEX('Project Assignment Check'!$G$1:$ZX$1, MATCH( LARGE( INDEX('ADR Tracking'!$G:$ZX, MATCH($A29, 'ADR Tracking'!$A:$A, 0), ), COLUMN()-4 ), INDEX('ADR Tracking'!$G:$ZX, MATCH($A29, 'ADR Tracking'!$A:$A, 0), ), 0 ) ), "" ) | I29: =IFERROR( INDEX('Project Assignment Check'!$G$1:$ZX$1, MATCH( LARGE( INDEX('ADR Tracking'!$G:$ZX, MATCH($A29, 'ADR Tracking'!$A:$A, 0), ), COLUMN()-4 ), INDEX('ADR Tracking'!$G:$ZX, MATCH($A29, 'ADR Tracking'!$A:$A, 0), ), 0 ) ), "" ) | J29: =IFERROR( INDEX('Project Assignment Check'!$G$1:$ZX$1, MATCH( LARGE( INDEX('ADR Tracking'!$G:$ZX, MATCH($A29, 'ADR Tracking'!$A:$A, 0), ), COLUMN()-4 ), INDEX('ADR Tracking'!$G:$ZX, MATCH($A29, 'ADR Tracking'!$A:$A, 0), ), 0 ) ), "" )
A30: SRP8-038 | B30: Motors | C30: Powertrain | D30: Chassis & Bodywork | E30: =IFERROR( INDEX('Project Assignment Check'!$G$1:$ZX$1, MATCH( LARGE( INDEX('ADR Tracking'!$G:$ZX, MATCH($A30, 'ADR Tracking'!$A:$A, 0), ), COLUMN()-4 ), INDEX('ADR Tracking'!$G:$ZX, MATCH($A30, 'ADR Tracking'!$A:$A, 0), ), 0 ) ), "" ) | F30: =IFERROR( INDEX('Project Assignment Check'!$G$1:$ZX$1, MATCH( LARGE( INDEX('ADR Tracking'!$G:$ZX, MATCH($A30, 'ADR Tracking'!$A:$A, 0), ), COLUMN()-4 ), INDEX('ADR Tracking'!$G:$ZX, MATCH($A30, 'ADR Tracking'!$A:$A, 0), ), 0 ) ), "" ) | G30: =IFERROR( INDEX('Project Assignment Check'!$G$1:$ZX$1, MATCH( LARGE( INDEX('ADR Tracking'!$G:$ZX, MATCH($A30, 'ADR Tracking'!$A:$A, 0), ), COLUMN()-4 ), INDEX('ADR Tracking'!$G:$ZX, MATCH($A30, 'ADR Tracking'!$A:$A, 0), ), 0 ) ), "" ) | H30: =IFERROR( INDEX('Project Assignment Check'!$G$1:$ZX$1, MATCH( LARGE( INDEX('ADR Tracking'!$G:$ZX, MATCH($A30, 'ADR Tracking'!$A:$A, 0), ), COLUMN()-4 ), INDEX('ADR Tracking'!$G:$ZX, MATCH($A30, 'ADR Tracking'!$A:$A, 0), ), 0 ) ), "" ) | I30: =IFERROR( INDEX('Project Assignment Check'!$G$1:$ZX$1, MATCH( LARGE( INDEX('ADR Tracking'!$G:$ZX, MATCH($A30, 'ADR Tracking'!$A:$A, 0), ), COLUMN()-4 ), INDEX('ADR Tracking'!$G:$ZX, MATCH($A30, 'ADR Tracking'!$A:$A, 0), ), 0 ) ), "" ) | J30: =IFERROR( INDEX('Project Assignment Check'!$G$1:$ZX$1, MATCH( LARGE( INDEX('ADR Tracking'!$G:$ZX, MATCH($A30, 'ADR Tracking'!$A:$A, 0), ), COLUMN()-4 ), INDEX('ADR Tracking'!$G:$ZX, MATCH($A30, 'ADR Tracking'!$A:$A, 0), ), 0 ) ), "" )
A31: SRP8-039 | B31: Powertrain Electronics | C31: Powertrain | D31: Energy Systems | E31: =IFERROR( INDEX('Project Assignment Check'!$G$1:$ZX$1, MATCH( LARGE( INDEX('ADR Tracking'!$G:$ZX, MATCH($A31, 'ADR Tracking'!$A:$A, 0), ), COLUMN()-4 ), INDEX('ADR Tracking'!$G:$ZX, MATCH($A31, 'ADR Tracking'!$A:$A, 0), ), 0 ) ), "" ) -> ADR-113 | F31: =IFERROR( INDEX('Project Assignment Check'!$G$1:$ZX$1, MATCH( LARGE( INDEX('ADR Tracking'!$G:$ZX, MATCH($A31, 'ADR Tracking'!$A:$A, 0), ), COLUMN()-4 ), INDEX('ADR Tracking'!$G:$ZX, MATCH($A31, 'ADR Tracking'!$A:$A, 0), ), 0 ) ), "" ) -> ADR-109 | G31: =IFERROR( INDEX('Project Assignment Check'!$G$1:$ZX$1, MATCH( LARGE( INDEX('ADR Tracking'!$G:$ZX, MATCH($A31, 'ADR Tracking'!$A:$A, 0), ), COLUMN()-4 ), INDEX('ADR Tracking'!$G:$ZX, MATCH($A31, 'ADR Tracking'!$A:$A, 0), ), 0 ) ), "" ) | H31: =IFERROR( INDEX('Project Assignment Check'!$G$1:$ZX$1, MATCH( LARGE( INDEX('ADR Tracking'!$G:$ZX, MATCH($A31, 'ADR Tracking'!$A:$A, 0), ), COLUMN()-4 ), INDEX('ADR Tracking'!$G:$ZX, MATCH($A31, 'ADR Tracking'!$A:$A, 0), ), 0 ) ), "" ) | I31: =IFERROR( INDEX('Project Assignment Check'!$G$1:$ZX$1, MATCH( LARGE( INDEX('ADR Tracking'!$G:$ZX, MATCH($A31, 'ADR Tracking'!$A:$A, 0), ), COLUMN()-4 ), INDEX('ADR Tracking'!$G:$ZX, MATCH($A31, 'ADR Tracking'!$A:$A, 0), ), 0 ) ), "" ) | J31: =IFERROR( INDEX('Project Assignment Check'!$G$1:$ZX$1, MATCH( LARGE( INDEX('ADR Tracking'!$G:$ZX, MATCH($A31, 'ADR Tracking'!$A:$A, 0), ), COLUMN()-4 ), INDEX('ADR Tracking'!$G:$ZX, MATCH($A31, 'ADR Tracking'!$A:$A, 0), ), 0 ) ), "" )
A32: SRP8-043 | B32: Front Suspension | C32: Vehicle Dynamics | D32: Chassis & Bodywork | E32: =IFERROR( INDEX('Project Assignment Check'!$G$1:$ZX$1, MATCH( LARGE( INDEX('ADR Tracking'!$G:$ZX, MATCH($A32, 'ADR Tracking'!$A:$A, 0), ), COLUMN()-4 ), INDEX('ADR Tracking'!$G:$ZX, MATCH($A32, 'ADR Tracking'!$A:$A, 0), ), 0 ) ), "" ) -> ADR-90 | F32: =IFERROR( INDEX('Project Assignment Check'!$G$1:$ZX$1, MATCH( LARGE( INDEX('ADR Tracking'!$G:$ZX, MATCH($A32, 'ADR Tracking'!$A:$A, 0), ), COLUMN()-4 ), INDEX('ADR Tracking'!$G:$ZX, MATCH($A32, 'ADR Tracking'!$A:$A, 0), ), 0 ) ), "" ) | G32: =IFERROR( INDEX('Project Assignment Check'!$G$1:$ZX$1, MATCH( LARGE( INDEX('ADR Tracking'!$G:$ZX, MATCH($A32, 'ADR Tracking'!$A:$A, 0), ), COLUMN()-4 ), INDEX('ADR Tracking'!$G:$ZX, MATCH($A32, 'ADR Tracking'!$A:$A, 0), ), 0 ) ), "" ) | H32: =IFERROR( INDEX('Project Assignment Check'!$G$1:$ZX$1, MATCH( LARGE( INDEX('ADR Tracking'!$G:$ZX, MATCH($A32, 'ADR Tracking'!$A:$A, 0), ), COLUMN()-4 ), INDEX('ADR Tracking'!$G:$ZX, MATCH($A32, 'ADR Tracking'!$A:$A, 0), ), 0 ) ), "" ) | I32: =IFERROR( INDEX('Project Assignment Check'!$G$1:$ZX$1, MATCH( LARGE( INDEX('ADR Tracking'!$G:$ZX, MATCH($A32, 'ADR Tracking'!$A:$A, 0), ), COLUMN()-4 ), INDEX('ADR Tracking'!$G:$ZX, MATCH($A32, 'ADR Tracking'!$A:$A, 0), ), 0 ) ), "" ) | J32: =IFERROR( INDEX('Project Assignment Check'!$G$1:$ZX$1, MATCH( LARGE( INDEX('ADR Tracking'!$G:$ZX, MATCH($A32, 'ADR Tracking'!$A:$A, 0), ), COLUMN()-4 ), INDEX('ADR Tracking'!$G:$ZX, MATCH($A32, 'ADR Tracking'!$A:$A, 0), ), 0 ) ), "" )
A33: SRP8-044 | B33: Rear Suspension | C33: Vehicle Dynamics | D33: Chassis & Bodywork | E33: =IFERROR( INDEX('Project Assignment Check'!$G$1:$ZX$1, MATCH( LARGE( INDEX('ADR Tracking'!$G:$ZX, MATCH($A33, 'ADR Tracking'!$A:$A, 0), ), COLUMN()-4 ), INDEX('ADR Tracking'!$G:$ZX, MATCH($A33, 'ADR Tracking'!$A:$A, 0), ), 0 ) ), "" ) | F33: =IFERROR( INDEX('Project Assignment Check'!$G$1:$ZX$1, MATCH( LARGE( INDEX('ADR Tracking'!$G:$ZX, MATCH($A33, 'ADR Tracking'!$A:$A, 0), ), COLUMN()-4 ), INDEX('ADR Tracking'!$G:$ZX, MATCH($A33, 'ADR Tracking'!$A:$A, 0), ), 0 ) ), "" ) | G33: =IFERROR( INDEX('Project Assignment Check'!$G$1:$ZX$1, MATCH( LARGE( INDEX('ADR Tracking'!$G:$ZX, MATCH($A33, 'ADR Tracking'!$A:$A, 0), ), COLUMN()-4 ), INDEX('ADR Tracking'!$G:$ZX, MATCH($A33, 'ADR Tracking'!$A:$A, 0), ), 0 ) ), "" ) | H33: =IFERROR( INDEX('Project Assignment Check'!$G$1:$ZX$1, MATCH( LARGE( INDEX('ADR Tracking'!$G:$ZX, MATCH($A33, 'ADR Tracking'!$A:$A, 0), ), COLUMN()-4 ), INDEX('ADR Tracking'!$G:$ZX, MATCH($A33, 'ADR Tracking'!$A:$A, 0), ), 0 ) ), "" ) | I33: =IFERROR( INDEX('Project Assignment Check'!$G$1:$ZX$1, MATCH( LARGE( INDEX('ADR Tracking'!$G:$ZX, MATCH($A33, 'ADR Tracking'!$A:$A, 0), ), COLUMN()-4 ), INDEX('ADR Tracking'!$G:$ZX, MATCH($A33, 'ADR Tracking'!$A:$A, 0), ), 0 ) ), "" ) | J33: =IFERROR( INDEX('Project Assignment Check'!$G$1:$ZX$1, MATCH( LARGE( INDEX('ADR Tracking'!$G:$ZX, MATCH($A33, 'ADR Tracking'!$A:$A, 0), ), COLUMN()-4 ), INDEX('ADR Tracking'!$G:$ZX, MATCH($A33, 'ADR Tracking'!$A:$A, 0), ), 0 ) ), "" )
A34: SRP8-045 | B34: Front Brakes | C34: Vehicle Dynamics | E34: =IFERROR( INDEX('Project Assignment Check'!$G$1:$ZX$1, MATCH( LARGE( INDEX('ADR Tracking'!$G:$ZX, MATCH($A34, 'ADR Tracking'!$A:$A, 0), ), COLUMN()-4 ), INDEX('ADR Tracking'!$G:$ZX, MATCH($A34, 'ADR Tracking'!$A:$A, 0), ), 0 ) ), "" ) -> ADR-31 | F34: =IFERROR( INDEX('Project Assignment Check'!$G$1:$ZX$1, MATCH( LARGE( INDEX('ADR Tracking'!$G:$ZX, MATCH($A34, 'ADR Tracking'!$A:$A, 0), ), COLUMN()-4 ), INDEX('ADR Tracking'!$G:$ZX, MATCH($A34, 'ADR Tracking'!$A:$A, 0), ), 0 ) ), "" ) -> ADR-42 | G34: =IFERROR( INDEX('Project Assignment Check'!$G$1:$ZX$1, MATCH( LARGE( INDEX('ADR Tracking'!$G:$ZX, MATCH($A34, 'ADR Tracking'!$A:$A, 0), ), COLUMN()-4 ), INDEX('ADR Tracking'!$G:$ZX, MATCH($A34, 'ADR Tracking'!$A:$A, 0), ), 0 ) ), "" ) -> ADR-90 | H34: =IFERROR( INDEX('Project Assignment Check'!$G$1:$ZX$1, MATCH( LARGE( INDEX('ADR Tracking'!$G:$ZX, MATCH($A34, 'ADR Tracking'!$A:$A, 0), ), COLUMN()-4 ), INDEX('ADR Tracking'!$G:$ZX, MATCH($A34, 'ADR Tracking'!$A:$A, 0), ), 0 ) ), "" ) | I34: =IFERROR( INDEX('Project Assignment Check'!$G$1:$ZX$1, MATCH( LARGE( INDEX('ADR Tracking'!$G:$ZX, MATCH($A34, 'ADR Tracking'!$A:$A, 0), ), COLUMN()-4 ), INDEX('ADR Tracking'!$G:$ZX, MATCH($A34, 'ADR Tracking'!$A:$A, 0), ), 0 ) ), "" ) | J34: =IFERROR( INDEX('Project Assignment Check'!$G$1:$ZX$1, MATCH( LARGE( INDEX('ADR Tracking'!$G:$ZX, MATCH($A34, 'ADR Tracking'!$A:$A, 0), ), COLUMN()-4 ), INDEX('ADR Tracking'!$G:$ZX, MATCH($A34, 'ADR Tracking'!$A:$A, 0), ), 0 ) ), "" )
A35: SRP8-046 | B35: Rear Brakes | C35: Vehicle Dynamics | E35: =IFERROR( INDEX('Project Assignment Check'!$G$1:$ZX$1, MATCH( LARGE( INDEX('ADR Tracking'!$G:$ZX, MATCH($A35, 'ADR Tracking'!$A:$A, 0), ), COLUMN()-4 ), INDEX('ADR Tracking'!$G:$ZX, MATCH($A35, 'ADR Tracking'!$A:$A, 0), ), 0 ) ), "" ) -> ADR-31 | F35: =IFERROR( INDEX('Project Assignment Check'!$G$1:$ZX$1, MATCH( LARGE( INDEX('ADR Tracking'!$G:$ZX, MATCH($A35, 'ADR Tracking'!$A:$A, 0), ), COLUMN()-4 ), INDEX('ADR Tracking'!$G:$ZX, MATCH($A35, 'ADR Tracking'!$A:$A, 0), ), 0 ) ), "" ) -> ADR-42 | G35: =IFERROR( INDEX('Project Assignment Check'!$G$1:$ZX$1, MATCH( LARGE( INDEX('ADR Tracking'!$G:$ZX, MATCH($A35, 'ADR Tracking'!$A:$A, 0), ), COLUMN()-4 ), INDEX('ADR Tracking'!$G:$ZX, MATCH($A35, 'ADR Tracking'!$A:$A, 0), ), 0 ) ), "" ) | H35: =IFERROR( INDEX('Project Assignment Check'!$G$1:$ZX$1, MATCH( LARGE( INDEX('ADR Tracking'!$G:$ZX, MATCH($A35, 'ADR Tracking'!$A:$A, 0), ), COLUMN()-4 ), INDEX('ADR Tracking'!$G:$ZX, MATCH($A35, 'ADR Tracking'!$A:$A, 0), ), 0 ) ), "" ) | I35: =IFERROR( INDEX('Project Assignment Check'!$G$1:$ZX$1, MATCH( LARGE( INDEX('ADR Tracking'!$G:$ZX, MATCH($A35, 'ADR Tracking'!$A:$A, 0), ), COLUMN()-4 ), INDEX('ADR Tracking'!$G:$ZX, MATCH($A35, 'ADR Tracking'!$A:$A, 0), ), 0 ) ), "" ) | J35: =IFERROR( INDEX('Project Assignment Check'!$G$1:$ZX$1, MATCH( LARGE( INDEX('ADR Tracking'!$G:$ZX, MATCH($A35, 'ADR Tracking'!$A:$A, 0), ), COLUMN()-4 ), INDEX('ADR Tracking'!$G:$ZX, MATCH($A35, 'ADR Tracking'!$A:$A, 0), ), 0 ) ), "" )
A36: SRP8-047 | B36: Handbrake | C36: Vehicle Dynamics | D36: Interior | E36: =IFERROR( INDEX('Project Assignment Check'!$G$1:$ZX$1, MATCH( LARGE( INDEX('ADR Tracking'!$G:$ZX, MATCH($A36, 'ADR Tracking'!$A:$A, 0), ), COLUMN()-4 ), INDEX('ADR Tracking'!$G:$ZX, MATCH($A36, 'ADR Tracking'!$A:$A, 0), ), 0 ) ), "" ) -> ADR-31 | F36: =IFERROR( INDEX('Project Assignment Check'!$G$1:$ZX$1, MATCH( LARGE( INDEX('ADR Tracking'!$G:$ZX, MATCH($A36, 'ADR Tracking'!$A:$A, 0), ), COLUMN()-4 ), INDEX('ADR Tracking'!$G:$ZX, MATCH($A36, 'ADR Tracking'!$A:$A, 0), ), 0 ) ), "" ) | G36: =IFERROR( INDEX('Project Assignment Check'!$G$1:$ZX$1, MATCH( LARGE( INDEX('ADR Tracking'!$G:$ZX, MATCH($A36, 'ADR Tracking'!$A:$A, 0), ), COLUMN()-4 ), INDEX('ADR Tracking'!$G:$ZX, MATCH($A36, 'ADR Tracking'!$A:$A, 0), ), 0 ) ), "" ) | H36: =IFERROR( INDEX('Project Assignment Check'!$G$1:$ZX$1, MATCH( LARGE( INDEX('ADR Tracking'!$G:$ZX, MATCH($A36, 'ADR Tracking'!$A:$A, 0), ), COLUMN()-4 ), INDEX('ADR Tracking'!$G:$ZX, MATCH($A36, 'ADR Tracking'!$A:$A, 0), ), 0 ) ), "" ) | I36: =IFERROR( INDEX('Project Assignment Check'!$G$1:$ZX$1, MATCH( LARGE( INDEX('ADR Tracking'!$G:$ZX, MATCH($A36, 'ADR Tracking'!$A:$A, 0), ), COLUMN()-4 ), INDEX('ADR Tracking'!$G:$ZX, MATCH($A36, 'ADR Tracking'!$A:$A, 0), ), 0 ) ), "" ) | J36: =IFERROR( INDEX('Project Assignment Check'!$G$1:$ZX$1, MATCH( LARGE( INDEX('ADR Tracking'!$G:$ZX, MATCH($A36, 'ADR Tracking'!$A:$A, 0), ), COLUMN()-4 ), INDEX('ADR Tracking'!$G:$ZX, MATCH($A36, 'ADR Tracking'!$A:$A, 0), ), 0 ) ), "" )
A37: SRP8-048 | B37: Steering Column | C37: Vehicle Dynamics | D37: Chassis & Bodywork | E37: =IFERROR( INDEX('Project Assignment Check'!$G$1:$ZX$1, MATCH( LARGE( INDEX('ADR Tracking'!$G:$ZX, MATCH($A37, 'ADR Tracking'!$A:$A, 0), ), COLUMN()-4 ), INDEX('ADR Tracking'!$G:$ZX, MATCH($A37, 'ADR Tracking'!$A:$A, 0), ), 0 ) ), "" ) -> ADR-10 | F37: =IFERROR( INDEX('Project Assignment Check'!$G$1:$ZX$1, MATCH( LARGE( INDEX('ADR Tracking'!$G:$ZX, MATCH($A37, 'ADR Tracking'!$A:$A, 0), ), COLUMN()-4 ), INDEX('ADR Tracking'!$G:$ZX, MATCH($A37, 'ADR Tracking'!$A:$A, 0), ), 0 ) ), "" ) -> ADR-90 | G37: =IFERROR( INDEX('Project Assignment Check'!$G$1:$ZX$1, MATCH( LARGE( INDEX('ADR Tracking'!$G:$ZX, MATCH($A37, 'ADR Tracking'!$A:$A, 0), ), COLUMN()-4 ), INDEX('ADR Tracking'!$G:$ZX, MATCH($A37, 'ADR Tracking'!$A:$A, 0), ), 0 ) ), "" ) | H37: =IFERROR( INDEX('Project Assignment Check'!$G$1:$ZX$1, MATCH( LARGE( INDEX('ADR Tracking'!$G:$ZX, MATCH($A37, 'ADR Tracking'!$A:$A, 0), ), COLUMN()-4 ), INDEX('ADR Tracking'!$G:$ZX, MATCH($A37, 'ADR Tracking'!$A:$A, 0), ), 0 ) ), "" ) | I37: =IFERROR( INDEX('Project Assignment Check'!$G$1:$ZX$1, MATCH( LARGE( INDEX('ADR Tracking'!$G:$ZX, MATCH($A37, 'ADR Tracking'!$A:$A, 0), ), COLUMN()-4 ), INDEX('ADR Tracking'!$G:$ZX, MATCH($A37, 'ADR Tracking'!$A:$A, 0), ), 0 ) ), "" ) | J37: =IFERROR( INDEX('Project Assignment Check'!$G$1:$ZX$1, MATCH( LARGE( INDEX('ADR Tracking'!$G:$ZX, MATCH($A37, 'ADR Tracking'!$A:$A, 0), ), COLUMN()-4 ), INDEX('ADR Tracking'!$G:$ZX, MATCH($A37, 'ADR Tracking'!$A:$A, 0), ), 0 ) ), "" )
A38: SRP8-049 | B38: Steering Rack | C38: Vehicle Dynamics | D38: Chassis & Bodywork | E38: =IFERROR( INDEX('Project Assignment Check'!$G$1:$ZX$1, MATCH( LARGE( INDEX('ADR Tracking'!$G:$ZX, MATCH($A38, 'ADR Tracking'!$A:$A, 0), ), COLUMN()-4 ), INDEX('ADR Tracking'!$G:$ZX, MATCH($A38, 'ADR Tracking'!$A:$A, 0), ), 0 ) ), "" ) -> ADR-90 | F38: =IFERROR( INDEX('Project Assignment Check'!$G$1:$ZX$1, MATCH( LARGE( INDEX('ADR Tracking'!$G:$ZX, MATCH($A38, 'ADR Tracking'!$A:$A, 0), ), COLUMN()-4 ), INDEX('ADR Tracking'!$G:$ZX, MATCH($A38, 'ADR Tracking'!$A:$A, 0), ), 0 ) ), "" ) -> ADR-43 | G38: =IFERROR( INDEX('Project Assignment Check'!$G$1:$ZX$1, MATCH( LARGE( INDEX('ADR Tracking'!$G:$ZX, MATCH($A38, 'ADR Tracking'!$A:$A, 0), ), COLUMN()-4 ), INDEX('ADR Tracking'!$G:$ZX, MATCH($A38, 'ADR Tracking'!$A:$A, 0), ), 0 ) ), "" ) | H38: =IFERROR( INDEX('Project Assignment Check'!$G$1:$ZX$1, MATCH( LARGE( INDEX('ADR Tracking'!$G:$ZX, MATCH($A38, 'ADR Tracking'!$A:$A, 0), ), COLUMN()-4 ), INDEX('ADR Tracking'!$G:$ZX, MATCH($A38, 'ADR Tracking'!$A:$A, 0), ), 0 ) ), "" ) | I38: =IFERROR( INDEX('Project Assignment Check'!$G$1:$ZX$1, MATCH( LARGE( INDEX('ADR Tracking'!$G:$ZX, MATCH($A38, 'ADR Tracking'!$A:$A, 0), ), COLUMN()-4 ), INDEX('ADR Tracking'!$G:$ZX, MATCH($A38, 'ADR Tracking'!$A:$A, 0), ), 0 ) ), "" ) | J38: =IFERROR( INDEX('Project Assignment Check'!$G$1:$ZX$1, MATCH( LARGE( INDEX('ADR Tracking'!$G:$ZX, MATCH($A38, 'ADR Tracking'!$A:$A, 0), ), COLUMN()-4 ), INDEX('ADR Tracking'!$G:$ZX, MATCH($A38, 'ADR Tracking'!$A:$A, 0), ), 0 ) ), "" )
A39: SRP8-050 | B39: Front Wheels | C39: Vehicle Dynamics | E39: =IFERROR( INDEX('Project Assignment Check'!$G$1:$ZX$1, MATCH( LARGE( INDEX('ADR Tracking'!$G:$ZX, MATCH($A39, 'ADR Tracking'!$A:$A, 0), ), COLUMN()-4 ), INDEX('ADR Tracking'!$G:$ZX, MATCH($A39, 'ADR Tracking'!$A:$A, 0), ), 0 ) ), "" ) -> ADR-42 | F39: =IFERROR( INDEX('Project Assignment Check'!$G$1:$ZX$1, MATCH( LARGE( INDEX('ADR Tracking'!$G:$ZX, MATCH($A39, 'ADR Tracking'!$A:$A, 0), ), COLUMN()-4 ), INDEX('ADR Tracking'!$G:$ZX, MATCH($A39, 'ADR Tracking'!$A:$A, 0), ), 0 ) ), "" ) -> ADR-92 | G39: =IFERROR( INDEX('Project Assignment Check'!$G$1:$ZX$1, MATCH( LARGE( INDEX('ADR Tracking'!$G:$ZX, MATCH($A39, 'ADR Tracking'!$A:$A, 0), ), COLUMN()-4 ), INDEX('ADR Tracking'!$G:$ZX, MATCH($A39, 'ADR Tracking'!$A:$A, 0), ), 0 ) ), "" ) -> ADR-95 | H39: =IFERROR( INDEX('Project Assignment Check'!$G$1:$ZX$1, MATCH( LARGE( INDEX('ADR Tracking'!$G:$ZX, MATCH($A39, 'ADR Tracking'!$A:$A, 0), ), COLUMN()-4 ), INDEX('ADR Tracking'!$G:$ZX, MATCH($A39, 'ADR Tracking'!$A:$A, 0), ), 0 ) ), "" ) -> ADR-23 | I39: =IFERROR( INDEX('Project Assignment Check'!$G$1:$ZX$1, MATCH( LARGE( INDEX('ADR Tracking'!$G:$ZX, MATCH($A39, 'ADR Tracking'!$A:$A, 0), ), COLUMN()-4 ), INDEX('ADR Tracking'!$G:$ZX, MATCH($A39, 'ADR Tracking'!$A:$A, 0), ), 0 ) ), "" ) -> ADR-43 | J39: =IFERROR( INDEX('Project Assignment Check'!$G$1:$ZX$1, MATCH( LARGE( INDEX('ADR Tracking'!$G:$ZX, MATCH($A39, 'ADR Tracking'!$A:$A, 0), ), COLUMN()-4 ), INDEX('ADR Tracking'!$G:$ZX, MATCH($A39, 'ADR Tracking'!$A:$A, 0), ), 0 ) ), "" )
A40: SRP8-051 | B40: Rear Wheels | C40: Vehicle Dynamics | E40: =IFERROR( INDEX('Project Assignment Check'!$G$1:$ZX$1, MATCH( LARGE( INDEX('ADR Tracking'!$G:$ZX, MATCH($A40, 'ADR Tracking'!$A:$A, 0), ), COLUMN()-4 ), INDEX('ADR Tracking'!$G:$ZX, MATCH($A40, 'ADR Tracking'!$A:$A, 0), ), 0 ) ), "" ) -> ADR-42 | F40: =IFERROR( INDEX('Project Assignment Check'!$G$1:$ZX$1, MATCH( LARGE( INDEX('ADR Tracking'!$G:$ZX, MATCH($A40, 'ADR Tracking'!$A:$A, 0), ), COLUMN()-4 ), INDEX('ADR Tracking'!$G:$ZX, MATCH($A40, 'ADR Tracking'!$A:$A, 0), ), 0 ) ), "" ) -> ADR-92 | G40: =IFERROR( INDEX('Project Assignment Check'!$G$1:$ZX$1, MATCH( LARGE( INDEX('ADR Tracking'!$G:$ZX, MATCH($A40, 'ADR Tracking'!$A:$A, 0), ), COLUMN()-4 ), INDEX('ADR Tracking'!$G:$ZX, MATCH($A40, 'ADR Tracking'!$A:$A, 0), ), 0 ) ), "" ) -> ADR-23 | H40: =IFERROR( INDEX('Project Assignment Check'!$G$1:$ZX$1, MATCH( LARGE( INDEX('ADR Tracking'!$G:$ZX, MATCH($A40, 'ADR Tracking'!$A:$A, 0), ), COLUMN()-4 ), INDEX('ADR Tracking'!$G:$ZX, MATCH($A40, 'ADR Tracking'!$A:$A, 0), ), 0 ) ), "" ) -> ADR-23 | I40: =IFERROR( INDEX('Project Assignment Check'!$G$1:$ZX$1, MATCH( LARGE( INDEX('ADR Tracking'!$G:$ZX, MATCH($A40, 'ADR Tracking'!$A:$A, 0), ), COLUMN()-4 ), INDEX('ADR Tracking'!$G:$ZX, MATCH($A40, 'ADR Tracking'!$A:$A, 0), ), 0 ) ), "" ) -> ADR-43 | J40: =IFERROR( INDEX('Project Assignment Check'!$G$1:$ZX$1, MATCH( LARGE( INDEX('ADR Tracking'!$G:$ZX, MATCH($A40, 'ADR Tracking'!$A:$A, 0), ), COLUMN()-4 ), INDEX('ADR Tracking'!$G:$ZX, MATCH($A40, 'ADR Tracking'!$A:$A, 0), ), 0 ) ), "" )
A41: SRP8-055 | B41: Unified Embedded Node | C41: Embedded Systems | E41: =IFERROR( INDEX('Project Assignment Check'!$G$1:$ZX$1, MATCH( LARGE( INDEX('ADR Tracking'!$G:$ZX, MATCH($A41, 'ADR Tracking'!$A:$A, 0), ), COLUMN()-4 ), INDEX('ADR Tracking'!$G:$ZX, MATCH($A41, 'ADR Tracking'!$A:$A, 0), ), 0 ) ), "" ) -> ADR-42 | F41: =IFERROR( INDEX('Project Assignment Check'!$G$1:$ZX$1, MATCH( LARGE( INDEX('ADR Tracking'!$G:$ZX, MATCH($A41, 'ADR Tracking'!$A:$A, 0), ), COLUMN()-4 ), INDEX('ADR Tracking'!$G:$ZX, MATCH($A41, 'ADR Tracking'!$A:$A, 0), ), 0 ) ), "" ) -> ADR-45 | G41: =IFERROR( INDEX('Project Assignment Check'!$G$1:$ZX$1, MATCH( LARGE( INDEX('ADR Tracking'!$G:$ZX, MATCH($A41, 'ADR Tracking'!$A:$A, 0), ), COLUMN()-4 ), INDEX('ADR Tracking'!$G:$ZX, MATCH($A41, 'ADR Tracking'!$A:$A, 0), ), 0 ) ), "" ) -> ADR-90 | H41: =IFERROR( INDEX('Project Assignment Check'!$G$1:$ZX$1, MATCH( LARGE( INDEX('ADR Tracking'!$G:$ZX, MATCH($A41, 'ADR Tracking'!$A:$A, 0), ), COLUMN()-4 ), INDEX('ADR Tracking'!$G:$ZX, MATCH($A41, 'ADR Tracking'!$A:$A, 0), ), 0 ) ), "" ) | I41: =IFERROR( INDEX('Project Assignment Check'!$G$1:$ZX$1, MATCH( LARGE( INDEX('ADR Tracking'!$G:$ZX, MATCH($A41, 'ADR Tracking'!$A:$A, 0), ), COLUMN()-4 ), INDEX('ADR Tracking'!$G:$ZX, MATCH($A41, 'ADR Tracking'!$A:$A, 0), ), 0 ) ), "" ) | J41: =IFERROR( INDEX('Project Assignment Check'!$G$1:$ZX$1, MATCH( LARGE( INDEX('ADR Tracking'!$G:$ZX, MATCH($A41, 'ADR Tracking'!$A:$A, 0), ), COLUMN()-4 ), INDEX('ADR Tracking'!$G:$ZX, MATCH($A41, 'ADR Tracking'!$A:$A, 0), ), 0 ) ), "" )
A42: SRP8-056 | B42: Embedded Testbed | C42: Embedded Systems | E42: =IFERROR( INDEX('Project Assignment Check'!$G$1:$ZX$1, MATCH( LARGE( INDEX('ADR Tracking'!$G:$ZX, MATCH($A42, 'ADR Tracking'!$A:$A, 0), ), COLUMN()-4 ), INDEX('ADR Tracking'!$G:$ZX, MATCH($A42, 'ADR Tracking'!$A:$A, 0), ), 0 ) ), "" ) -> ADR-109 | F42: =IFERROR( INDEX('Project Assignment Check'!$G$1:$ZX$1, MATCH( LARGE( INDEX('ADR Tracking'!$G:$ZX, MATCH($A42, 'ADR Tracking'!$A:$A, 0), ), COLUMN()-4 ), INDEX('ADR Tracking'!$G:$ZX, MATCH($A42, 'ADR Tracking'!$A:$A, 0), ), 0 ) ), "" ) | G42: =IFERROR( INDEX('Project Assignment Check'!$G$1:$ZX$1, MATCH( LARGE( INDEX('ADR Tracking'!$G:$ZX, MATCH($A42, 'ADR Tracking'!$A:$A, 0), ), COLUMN()-4 ), INDEX('ADR Tracking'!$G:$ZX, MATCH($A42, 'ADR Tracking'!$A:$A, 0), ), 0 ) ), "" ) | H42: =IFERROR( INDEX('Project Assignment Check'!$G$1:$ZX$1, MATCH( LARGE( INDEX('ADR Tracking'!$G:$ZX, MATCH($A42, 'ADR Tracking'!$A:$A, 0), ), COLUMN()-4 ), INDEX('ADR Tracking'!$G:$ZX, MATCH($A42, 'ADR Tracking'!$A:$A, 0), ), 0 ) ), "" ) | I42: =IFERROR( INDEX('Project Assignment Check'!$G$1:$ZX$1, MATCH( LARGE( INDEX('ADR Tracking'!$G:$ZX, MATCH($A42, 'ADR Tracking'!$A:$A, 0), ), COLUMN()-4 ), INDEX('ADR Tracking'!$G:$ZX, MATCH($A42, 'ADR Tracking'!$A:$A, 0), ), 0 ) ), "" ) | J42: =IFERROR( INDEX('Project Assignment Check'!$G$1:$ZX$1, MATCH( LARGE( INDEX('ADR Tracking'!$G:$ZX, MATCH($A42, 'ADR Tracking'!$A:$A, 0), ), COLUMN()-4 ), INDEX('ADR Tracking'!$G:$ZX, MATCH($A42, 'ADR Tracking'!$A:$A, 0), ), 0 ) ), "" )
A43: SRP8-057 | B43: Horn | C43: Embedded Systems | E43: =IFERROR( INDEX('Project Assignment Check'!$G$1:$ZX$1, MATCH( LARGE( INDEX('ADR Tracking'!$G:$ZX, MATCH($A43, 'ADR Tracking'!$A:$A, 0), ), COLUMN()-4 ), INDEX('ADR Tracking'!$G:$ZX, MATCH($A43, 'ADR Tracking'!$A:$A, 0), ), 0 ) ), "" ) -> ADR-94 | F43: =IFERROR( INDEX('Project Assignment Check'!$G$1:$ZX$1, MATCH( LARGE( INDEX('ADR Tracking'!$G:$ZX, MATCH($A43, 'ADR Tracking'!$A:$A, 0), ), COLUMN()-4 ), INDEX('ADR Tracking'!$G:$ZX, MATCH($A43, 'ADR Tracking'!$A:$A, 0), ), 0 ) ), "" ) -> ADR-02 | G43: =IFERROR( INDEX('Project Assignment Check'!$G$1:$ZX$1, MATCH( LARGE( INDEX('ADR Tracking'!$G:$ZX, MATCH($A43, 'ADR Tracking'!$A:$A, 0), ), COLUMN()-4 ), INDEX('ADR Tracking'!$G:$ZX, MATCH($A43, 'ADR Tracking'!$A:$A, 0), ), 0 ) ), "" ) -> ADR-02 | H43: =IFERROR( INDEX('Project Assignment Check'!$G$1:$ZX$1, MATCH( LARGE( INDEX('ADR Tracking'!$G:$ZX, MATCH($A43, 'ADR Tracking'!$A:$A, 0), ), COLUMN()-4 ), INDEX('ADR Tracking'!$G:$ZX, MATCH($A43, 'ADR Tracking'!$A:$A, 0), ), 0 ) ), "" ) | I43: =IFERROR( INDEX('Project Assignment Check'!$G$1:$ZX$1, MATCH( LARGE( INDEX('ADR Tracking'!$G:$ZX, MATCH($A43, 'ADR Tracking'!$A:$A, 0), ), COLUMN()-4 ), INDEX('ADR Tracking'!$G:$ZX, MATCH($A43, 'ADR Tracking'!$A:$A, 0), ), 0 ) ), "" ) | J43: =IFERROR( INDEX('Project Assignment Check'!$G$1:$ZX$1, MATCH( LARGE( INDEX('ADR Tracking'!$G:$ZX, MATCH($A43, 'ADR Tracking'!$A:$A, 0), ), COLUMN()-4 ), INDEX('ADR Tracking'!$G:$ZX, MATCH($A43, 'ADR Tracking'!$A:$A, 0), ), 0 ) ), "" )
A44: SRP8-058 | B44: Drive Control Systems | C44: Embedded Systems | D44: Powertrain | E44: =IFERROR( INDEX('Project Assignment Check'!$G$1:$ZX$1, MATCH( LARGE( INDEX('ADR Tracking'!$G:$ZX, MATCH($A44, 'ADR Tracking'!$A:$A, 0), ), COLUMN()-4 ), INDEX('ADR Tracking'!$G:$ZX, MATCH($A44, 'ADR Tracking'!$A:$A, 0), ), 0 ) ), "" ) -> ADR-109 | F44: =IFERROR( INDEX('Project Assignment Check'!$G$1:$ZX$1, MATCH( LARGE( INDEX('ADR Tracking'!$G:$ZX, MATCH($A44, 'ADR Tracking'!$A:$A, 0), ), COLUMN()-4 ), INDEX('ADR Tracking'!$G:$ZX, MATCH($A44, 'ADR Tracking'!$A:$A, 0), ), 0 ) ), "" ) | G44: =IFERROR( INDEX('Project Assignment Check'!$G$1:$ZX$1, MATCH( LARGE( INDEX('ADR Tracking'!$G:$ZX, MATCH($A44, 'ADR Tracking'!$A:$A, 0), ), COLUMN()-4 ), INDEX('ADR Tracking'!$G:$ZX, MATCH($A44, 'ADR Tracking'!$A:$A, 0), ), 0 ) ), "" ) | H44: =IFERROR( INDEX('Project Assignment Check'!$G$1:$ZX$1, MATCH( LARGE( INDEX('ADR Tracking'!$G:$ZX, MATCH($A44, 'ADR Tracking'!$A:$A, 0), ), COLUMN()-4 ), INDEX('ADR Tracking'!$G:$ZX, MATCH($A44, 'ADR Tracking'!$A:$A, 0), ), 0 ) ), "" ) | I44: =IFERROR( INDEX('Project Assignment Check'!$G$1:$ZX$1, MATCH( LARGE( INDEX('ADR Tracking'!$G:$ZX, MATCH($A44, 'ADR Tracking'!$A:$A, 0), ), COLUMN()-4 ), INDEX('ADR Tracking'!$G:$ZX, MATCH($A44, 'ADR Tracking'!$A:$A, 0), ), 0 ) ), "" ) | J44: =IFERROR( INDEX('Project Assignment Check'!$G$1:$ZX$1, MATCH( LARGE( INDEX('ADR Tracking'!$G:$ZX, MATCH($A44, 'ADR Tracking'!$A:$A, 0), ), COLUMN()-4 ), INDEX('ADR Tracking'!$G:$ZX, MATCH($A44, 'ADR Tracking'!$A:$A, 0), ), 0 ) ), "" )
A45: SRP8-059 | B45: Sensors | C45: Embedded Systems | E45: =IFERROR( INDEX('Project Assignment Check'!$G$1:$ZX$1, MATCH( LARGE( INDEX('ADR Tracking'!$G:$ZX, MATCH($A45, 'ADR Tracking'!$A:$A, 0), ), COLUMN()-4 ), INDEX('ADR Tracking'!$G:$ZX, MATCH($A45, 'ADR Tracking'!$A:$A, 0), ), 0 ) ), "" ) -> ADR-109 | F45: =IFERROR( INDEX('Project Assignment Check'!$G$1:$ZX$1, MATCH( LARGE( INDEX('ADR Tracking'!$G:$ZX, MATCH($A45, 'ADR Tracking'!$A:$A, 0), ), COLUMN()-4 ), INDEX('ADR Tracking'!$G:$ZX, MATCH($A45, 'ADR Tracking'!$A:$A, 0), ), 0 ) ), "" ) | G45: =IFERROR( INDEX('Project Assignment Check'!$G$1:$ZX$1, MATCH( LARGE( INDEX('ADR Tracking'!$G:$ZX, MATCH($A45, 'ADR Tracking'!$A:$A, 0), ), COLUMN()-4 ), INDEX('ADR Tracking'!$G:$ZX, MATCH($A45, 'ADR Tracking'!$A:$A, 0), ), 0 ) ), "" ) | H45: =IFERROR( INDEX('Project Assignment Check'!$G$1:$ZX$1, MATCH( LARGE( INDEX('ADR Tracking'!$G:$ZX, MATCH($A45, 'ADR Tracking'!$A:$A, 0), ), COLUMN()-4 ), INDEX('ADR Tracking'!$G:$ZX, MATCH($A45, 'ADR Tracking'!$A:$A, 0), ), 0 ) ), "" ) | I45: =IFERROR( INDEX('Project Assignment Check'!$G$1:$ZX$1, MATCH( LARGE( INDEX('ADR Tracking'!$G:$ZX, MATCH($A45, 'ADR Tracking'!$A:$A, 0), ), COLUMN()-4 ), INDEX('ADR Tracking'!$G:$ZX, MATCH($A45, 'ADR Tracking'!$A:$A, 0), ), 0 ) ), "" ) | J45: =IFERROR( INDEX('Project Assignment Check'!$G$1:$ZX$1, MATCH( LARGE( INDEX('ADR Tracking'!$G:$ZX, MATCH($A45, 'ADR Tracking'!$A:$A, 0), ), COLUMN()-4 ), INDEX('ADR Tracking'!$G:$ZX, MATCH($A45, 'ADR Tracking'!$A:$A, 0), ), 0 ) ), "" )
A46: SRP8-061 | B46: Telemetry | C46: Technical Support Systems | E46: =IFERROR( INDEX('Project Assignment Check'!$G$1:$ZX$1, MATCH( LARGE( INDEX('ADR Tracking'!$G:$ZX, MATCH($A46, 'ADR Tracking'!$A:$A, 0), ), COLUMN()-4 ), INDEX('ADR Tracking'!$G:$ZX, MATCH($A46, 'ADR Tracking'!$A:$A, 0), ), 0 ) ), "" ) | F46: =IFERROR( INDEX('Project Assignment Check'!$G$1:$ZX$1, MATCH( LARGE( INDEX('ADR Tracking'!$G:$ZX, MATCH($A46, 'ADR Tracking'!$A:$A, 0), ), COLUMN()-4 ), INDEX('ADR Tracking'!$G:$ZX, MATCH($A46, 'ADR Tracking'!$A:$A, 0), ), 0 ) ), "" ) | G46: =IFERROR( INDEX('Project Assignment Check'!$G$1:$ZX$1, MATCH( LARGE( INDEX('ADR Tracking'!$G:$ZX, MATCH($A46, 'ADR Tracking'!$A:$A, 0), ), COLUMN()-4 ), INDEX('ADR Tracking'!$G:$ZX, MATCH($A46, 'ADR Tracking'!$A:$A, 0), ), 0 ) ), "" ) | H46: =IFERROR( INDEX('Project Assignment Check'!$G$1:$ZX$1, MATCH( LARGE( INDEX('ADR Tracking'!$G:$ZX, MATCH($A46, 'ADR Tracking'!$A:$A, 0), ), COLUMN()-4 ), INDEX('ADR Tracking'!$G:$ZX, MATCH($A46, 'ADR Tracking'!$A:$A, 0), ), 0 ) ), "" ) | I46: =IFERROR( INDEX('Project Assignment Check'!$G$1:$ZX$1, MATCH( LARGE( INDEX('ADR Tracking'!$G:$ZX, MATCH($A46, 'ADR Tracking'!$A:$A, 0), ), COLUMN()-4 ), INDEX('ADR Tracking'!$G:$ZX, MATCH($A46, 'ADR Tracking'!$A:$A, 0), ), 0 ) ), "" ) | J46: =IFERROR( INDEX('Project Assignment Check'!$G$1:$ZX$1, MATCH( LARGE( INDEX('ADR Tracking'!$G:$ZX, MATCH($A46, 'ADR Tracking'!$A:$A, 0), ), COLUMN()-4 ), INDEX('ADR Tracking'!$G:$ZX, MATCH($A46, 'ADR Tracking'!$A:$A, 0), ), 0 ) ), "" )
A47: SRP8-064 | B47: Wiring Harnesses | C47: Embedded Systems | E47: =IFERROR( INDEX('Project Assignment Check'!$G$1:$ZX$1, MATCH( LARGE( INDEX('ADR Tracking'!$G:$ZX, MATCH($A47, 'ADR Tracking'!$A:$A, 0), ), COLUMN()-4 ), INDEX('ADR Tracking'!$G:$ZX, MATCH($A47, 'ADR Tracking'!$A:$A, 0), ), 0 ) ), "" ) | F47: =IFERROR( INDEX('Project Assignment Check'!$G$1:$ZX$1, MATCH( LARGE( INDEX('ADR Tracking'!$G:$ZX, MATCH($A47, 'ADR Tracking'!$A:$A, 0), ), COLUMN()-4 ), INDEX('ADR Tracking'!$G:$ZX, MATCH($A47, 'ADR Tracking'!$A:$A, 0), ), 0 ) ), "" ) | G47: =IFERROR( INDEX('Project Assignment Check'!$G$1:$ZX$1, MATCH( LARGE( INDEX('ADR Tracking'!$G:$ZX, MATCH($A47, 'ADR Tracking'!$A:$A, 0), ), COLUMN()-4 ), INDEX('ADR Tracking'!$G:$ZX, MATCH($A47, 'ADR Tracking'!$A:$A, 0), ), 0 ) ), "" ) | H47: =IFERROR( INDEX('Project Assignment Check'!$G$1:$ZX$1, MATCH( LARGE( INDEX('ADR Tracking'!$G:$ZX, MATCH($A47, 'ADR Tracking'!$A:$A, 0), ), COLUMN()-4 ), INDEX('ADR Tracking'!$G:$ZX, MATCH($A47, 'ADR Tracking'!$A:$A, 0), ), 0 ) ), "" ) | I47: =IFERROR( INDEX('Project Assignment Check'!$G$1:$ZX$1, MATCH( LARGE( INDEX('ADR Tracking'!$G:$ZX, MATCH($A47, 'ADR Tracking'!$A:$A, 0), ), COLUMN()-4 ), INDEX('ADR Tracking'!$G:$ZX, MATCH($A47, 'ADR Tracking'!$A:$A, 0), ), 0 ) ), "" ) | J47: =IFERROR( INDEX('Project Assignment Check'!$G$1:$ZX$1, MATCH( LARGE( INDEX('ADR Tracking'!$G:$ZX, MATCH($A47, 'ADR Tracking'!$A:$A, 0), ), COLUMN()-4 ), INDEX('ADR Tracking'!$G:$ZX, MATCH($A47, 'ADR Tracking'!$A:$A, 0), ), 0 ) ), "" )
A48: SRP8-065 | B48: Occupant Cell | C48: Chassis & Bodywork | E48: =IFERROR( INDEX('Project Assignment Check'!$G$1:$ZX$1, MATCH( LARGE( INDEX('ADR Tracking'!$G:$ZX, MATCH($A48, 'ADR Tracking'!$A:$A, 0), ), COLUMN()-4 ), INDEX('ADR Tracking'!$G:$ZX, MATCH($A48, 'ADR Tracking'!$A:$A, 0), ), 0 ) ), "" ) -> ADR-93 | F48: =IFERROR( INDEX('Project Assignment Check'!$G$1:$ZX$1, MATCH( LARGE( INDEX('ADR Tracking'!$G:$ZX, MATCH($A48, 'ADR Tracking'!$A:$A, 0), ), COLUMN()-4 ), INDEX('ADR Tracking'!$G:$ZX, MATCH($A48, 'ADR Tracking'!$A:$A, 0), ), 0 ) ), "" ) -> ADR-92 | G48: =IFERROR( INDEX('Project Assignment Check'!$G$1:$ZX$1, MATCH( LARGE( INDEX('ADR Tracking'!$G:$ZX, MATCH($A48, 'ADR Tracking'!$A:$A, 0), ), COLUMN()-4 ), INDEX('ADR Tracking'!$G:$ZX, MATCH($A48, 'ADR Tracking'!$A:$A, 0), ), 0 ) ), "" ) -> ADR-43 | H48: =IFERROR( INDEX('Project Assignment Check'!$G$1:$ZX$1, MATCH( LARGE( INDEX('ADR Tracking'!$G:$ZX, MATCH($A48, 'ADR Tracking'!$A:$A, 0), ), COLUMN()-4 ), INDEX('ADR Tracking'!$G:$ZX, MATCH($A48, 'ADR Tracking'!$A:$A, 0), ), 0 ) ), "" ) | I48: =IFERROR( INDEX('Project Assignment Check'!$G$1:$ZX$1, MATCH( LARGE( INDEX('ADR Tracking'!$G:$ZX, MATCH($A48, 'ADR Tracking'!$A:$A, 0), ), COLUMN()-4 ), INDEX('ADR Tracking'!$G:$ZX, MATCH($A48, 'ADR Tracking'!$A:$A, 0), ), 0 ) ), "" ) | J48: =IFERROR( INDEX('Project Assignment Check'!$G$1:$ZX$1, MATCH( LARGE( INDEX('ADR Tracking'!$G:$ZX, MATCH($A48, 'ADR Tracking'!$A:$A, 0), ), COLUMN()-4 ), INDEX('ADR Tracking'!$G:$ZX, MATCH($A48, 'ADR Tracking'!$A:$A, 0), ), 0 ) ), "" )
A49: SRP8-066 | B49: Front Crash Structures | C49: Chassis & Bodywork | E49: =IFERROR( INDEX('Project Assignment Check'!$G$1:$ZX$1, MATCH( LARGE( INDEX('ADR Tracking'!$G:$ZX, MATCH($A49, 'ADR Tracking'!$A:$A, 0), ), COLUMN()-4 ), INDEX('ADR Tracking'!$G:$ZX, MATCH($A49, 'ADR Tracking'!$A:$A, 0), ), 0 ) ), "" ) | F49: =IFERROR( INDEX('Project Assignment Check'!$G$1:$ZX$1, MATCH( LARGE( INDEX('ADR Tracking'!$G:$ZX, MATCH($A49, 'ADR Tracking'!$A:$A, 0), ), COLUMN()-4 ), INDEX('ADR Tracking'!$G:$ZX, MATCH($A49, 'ADR Tracking'!$A:$A, 0), ), 0 ) ), "" ) | G49: =IFERROR( INDEX('Project Assignment Check'!$G$1:$ZX$1, MATCH( LARGE( INDEX('ADR Tracking'!$G:$ZX, MATCH($A49, 'ADR Tracking'!$A:$A, 0), ), COLUMN()-4 ), INDEX('ADR Tracking'!$G:$ZX, MATCH($A49, 'ADR Tracking'!$A:$A, 0), ), 0 ) ), "" ) | H49: =IFERROR( INDEX('Project Assignment Check'!$G$1:$ZX$1, MATCH( LARGE( INDEX('ADR Tracking'!$G:$ZX, MATCH($A49, 'ADR Tracking'!$A:$A, 0), ), COLUMN()-4 ), INDEX('ADR Tracking'!$G:$ZX, MATCH($A49, 'ADR Tracking'!$A:$A, 0), ), 0 ) ), "" ) | I49: =IFERROR( INDEX('Project Assignment Check'!$G$1:$ZX$1, MATCH( LARGE( INDEX('ADR Tracking'!$G:$ZX, MATCH($A49, 'ADR Tracking'!$A:$A, 0), ), COLUMN()-4 ), INDEX('ADR Tracking'!$G:$ZX, MATCH($A49, 'ADR Tracking'!$A:$A, 0), ), 0 ) ), "" ) | J49: =IFERROR( INDEX('Project Assignment Check'!$G$1:$ZX$1, MATCH( LARGE( INDEX('ADR Tracking'!$G:$ZX, MATCH($A49, 'ADR Tracking'!$A:$A, 0), ), COLUMN()-4 ), INDEX('ADR Tracking'!$G:$ZX, MATCH($A49, 'ADR Tracking'!$A:$A, 0), ), 0 ) ), "" )
A50: SRP8-077 | B50: Central Stop Lamp | C50: Embedded Systems | E50: =IFERROR( INDEX('Project Assignment Check'!$G$1:$ZX$1, MATCH( LARGE( INDEX('ADR Tracking'!$G:$ZX, MATCH($A50, 'ADR Tracking'!$A:$A, 0), ), COLUMN()-4 ), INDEX('ADR Tracking'!$G:$ZX, MATCH($A50, 'ADR Tracking'!$A:$A, 0), ), 0 ) ), "" ) -> ADR-13 | F50: =IFERROR( INDEX('Project Assignment Check'!$G$1:$ZX$1, MATCH( LARGE( INDEX('ADR Tracking'!$G:$ZX, MATCH($A50, 'ADR Tracking'!$A:$A, 0), ), COLUMN()-4 ), INDEX('ADR Tracking'!$G:$ZX, MATCH($A50, 'ADR Tracking'!$A:$A, 0), ), 0 ) ), "" ) -> ADR-60 | G50: =IFERROR( INDEX('Project Assignment Check'!$G$1:$ZX$1, MATCH( LARGE( INDEX('ADR Tracking'!$G:$ZX, MATCH($A50, 'ADR Tracking'!$A:$A, 0), ), COLUMN()-4 ), INDEX('ADR Tracking'!$G:$ZX, MATCH($A50, 'ADR Tracking'!$A:$A, 0), ), 0 ) ), "" ) -> ADR-49 | H50: =IFERROR( INDEX('Project Assignment Check'!$G$1:$ZX$1, MATCH( LARGE( INDEX('ADR Tracking'!$G:$ZX, MATCH($A50, 'ADR Tracking'!$A:$A, 0), ), COLUMN()-4 ), INDEX('ADR Tracking'!$G:$ZX, MATCH($A50, 'ADR Tracking'!$A:$A, 0), ), 0 ) ), "" ) | I50: =IFERROR( INDEX('Project Assignment Check'!$G$1:$ZX$1, MATCH( LARGE( INDEX('ADR Tracking'!$G:$ZX, MATCH($A50, 'ADR Tracking'!$A:$A, 0), ), COLUMN()-4 ), INDEX('ADR Tracking'!$G:$ZX, MATCH($A50, 'ADR Tracking'!$A:$A, 0), ), 0 ) ), "" ) | J50: =IFERROR( INDEX('Project Assignment Check'!$G$1:$ZX$1, MATCH( LARGE( INDEX('ADR Tracking'!$G:$ZX, MATCH($A50, 'ADR Tracking'!$A:$A, 0), ), COLUMN()-4 ), INDEX('ADR Tracking'!$G:$ZX, MATCH($A50, 'ADR Tracking'!$A:$A, 0), ), 0 ) ), "" )
A51: SRP8-081 | B51: Subframes | C51: Chassis & Bodywork | E51: =IFERROR( INDEX('Project Assignment Check'!$G$1:$ZX$1, MATCH( LARGE( INDEX('ADR Tracking'!$G:$ZX, MATCH($A51, 'ADR Tracking'!$A:$A, 0), ), COLUMN()-4 ), INDEX('ADR Tracking'!$G:$ZX, MATCH($A51, 'ADR Tracking'!$A:$A, 0), ), 0 ) ), "" ) | F51: =IFERROR( INDEX('Project Assignment Check'!$G$1:$ZX$1, MATCH( LARGE( INDEX('ADR Tracking'!$G:$ZX, MATCH($A51, 'ADR Tracking'!$A:$A, 0), ), COLUMN()-4 ), INDEX('ADR Tracking'!$G:$ZX, MATCH($A51, 'ADR Tracking'!$A:$A, 0), ), 0 ) ), "" ) | G51: =IFERROR( INDEX('Project Assignment Check'!$G$1:$ZX$1, MATCH( LARGE( INDEX('ADR Tracking'!$G:$ZX, MATCH($A51, 'ADR Tracking'!$A:$A, 0), ), COLUMN()-4 ), INDEX('ADR Tracking'!$G:$ZX, MATCH($A51, 'ADR Tracking'!$A:$A, 0), ), 0 ) ), "" ) | H51: =IFERROR( INDEX('Project Assignment Check'!$G$1:$ZX$1, MATCH( LARGE( INDEX('ADR Tracking'!$G:$ZX, MATCH($A51, 'ADR Tracking'!$A:$A, 0), ), COLUMN()-4 ), INDEX('ADR Tracking'!$G:$ZX, MATCH($A51, 'ADR Tracking'!$A:$A, 0), ), 0 ) ), "" ) | I51: =IFERROR( INDEX('Project Assignment Check'!$G$1:$ZX$1, MATCH( LARGE( INDEX('ADR Tracking'!$G:$ZX, MATCH($A51, 'ADR Tracking'!$A:$A, 0), ), COLUMN()-4 ), INDEX('ADR Tracking'!$G:$ZX, MATCH($A51, 'ADR Tracking'!$A:$A, 0), ), 0 ) ), "" ) | J51: =IFERROR( INDEX('Project Assignment Check'!$G$1:$ZX$1, MATCH( LARGE( INDEX('ADR Tracking'!$G:$ZX, MATCH($A51, 'ADR Tracking'!$A:$A, 0), ), COLUMN()-4 ), INDEX('ADR Tracking'!$G:$ZX, MATCH($A51, 'ADR Tracking'!$A:$A, 0), ), 0 ) ), "" )
A52: SRP8-082 | B52: Windscreen Wipers | C52: Chassis & Bodywork | E52: =IFERROR( INDEX('Project Assignment Check'!$G$1:$ZX$1, MATCH( LARGE( INDEX('ADR Tracking'!$G:$ZX, MATCH($A52, 'ADR Tracking'!$A:$A, 0), ), COLUMN()-4 ), INDEX('ADR Tracking'!$G:$ZX, MATCH($A52, 'ADR Tracking'!$A:$A, 0), ), 0 ) ), "" ) -> ADR-42 | F52: =IFERROR( INDEX('Project Assignment Check'!$G$1:$ZX$1, MATCH( LARGE( INDEX('ADR Tracking'!$G:$ZX, MATCH($A52, 'ADR Tracking'!$A:$A, 0), ), COLUMN()-4 ), INDEX('ADR Tracking'!$G:$ZX, MATCH($A52, 'ADR Tracking'!$A:$A, 0), ), 0 ) ), "" ) | G52: =IFERROR( INDEX('Project Assignment Check'!$G$1:$ZX$1, MATCH( LARGE( INDEX('ADR Tracking'!$G:$ZX, MATCH($A52, 'ADR Tracking'!$A:$A, 0), ), COLUMN()-4 ), INDEX('ADR Tracking'!$G:$ZX, MATCH($A52, 'ADR Tracking'!$A:$A, 0), ), 0 ) ), "" ) | H52: =IFERROR( INDEX('Project Assignment Check'!$G$1:$ZX$1, MATCH( LARGE( INDEX('ADR Tracking'!$G:$ZX, MATCH($A52, 'ADR Tracking'!$A:$A, 0), ), COLUMN()-4 ), INDEX('ADR Tracking'!$G:$ZX, MATCH($A52, 'ADR Tracking'!$A:$A, 0), ), 0 ) ), "" ) | I52: =IFERROR( INDEX('Project Assignment Check'!$G$1:$ZX$1, MATCH( LARGE( INDEX('ADR Tracking'!$G:$ZX, MATCH($A52, 'ADR Tracking'!$A:$A, 0), ), COLUMN()-4 ), INDEX('ADR Tracking'!$G:$ZX, MATCH($A52, 'ADR Tracking'!$A:$A, 0), ), 0 ) ), "" ) | J52: =IFERROR( INDEX('Project Assignment Check'!$G$1:$ZX$1, MATCH( LARGE( INDEX('ADR Tracking'!$G:$ZX, MATCH($A52, 'ADR Tracking'!$A:$A, 0), ), COLUMN()-4 ), INDEX('ADR Tracking'!$G:$ZX, MATCH($A52, 'ADR Tracking'!$A:$A, 0), ), 0 ) ), "" )
A53: SRP8-083 | B53: Active Aero | C53: Chassis & Bodywork | E53: =IFERROR( INDEX('Project Assignment Check'!$G$1:$ZX$1, MATCH( LARGE( INDEX('ADR Tracking'!$G:$ZX, MATCH($A53, 'ADR Tracking'!$A:$A, 0), ), COLUMN()-4 ), INDEX('ADR Tracking'!$G:$ZX, MATCH($A53, 'ADR Tracking'!$A:$A, 0), ), 0 ) ), "" ) -> ADR-92 | F53: =IFERROR( INDEX('Project Assignment Check'!$G$1:$ZX$1, MATCH( LARGE( INDEX('ADR Tracking'!$G:$ZX, MATCH($A53, 'ADR Tracking'!$A:$A, 0), ), COLUMN()-4 ), INDEX('ADR Tracking'!$G:$ZX, MATCH($A53, 'ADR Tracking'!$A:$A, 0), ), 0 ) ), "" ) | G53: =IFERROR( INDEX('Project Assignment Check'!$G$1:$ZX$1, MATCH( LARGE( INDEX('ADR Tracking'!$G:$ZX, MATCH($A53, 'ADR Tracking'!$A:$A, 0), ), COLUMN()-4 ), INDEX('ADR Tracking'!$G:$ZX, MATCH($A53, 'ADR Tracking'!$A:$A, 0), ), 0 ) ), "" ) | H53: =IFERROR( INDEX('Project Assignment Check'!$G$1:$ZX$1, MATCH( LARGE( INDEX('ADR Tracking'!$G:$ZX, MATCH($A53, 'ADR Tracking'!$A:$A, 0), ), COLUMN()-4 ), INDEX('ADR Tracking'!$G:$ZX, MATCH($A53, 'ADR Tracking'!$A:$A, 0), ), 0 ) ), "" ) | I53: =IFERROR( INDEX('Project Assignment Check'!$G$1:$ZX$1, MATCH( LARGE( INDEX('ADR Tracking'!$G:$ZX, MATCH($A53, 'ADR Tracking'!$A:$A, 0), ), COLUMN()-4 ), INDEX('ADR Tracking'!$G:$ZX, MATCH($A53, 'ADR Tracking'!$A:$A, 0), ), 0 ) ), "" ) | J53: =IFERROR( INDEX('Project Assignment Check'!$G$1:$ZX$1, MATCH( LARGE( INDEX('ADR Tracking'!$G:$ZX, MATCH($A53, 'ADR Tracking'!$A:$A, 0), ), COLUMN()-4 ), INDEX('ADR Tracking'!$G:$ZX, MATCH($A53, 'ADR Tracking'!$A:$A, 0), ), 0 ) ), "" )
A54: SRP8-084 | B54: Audio | C54: Embedded Systems | D54: Interior | E54: =IFERROR( INDEX('Project Assignment Check'!$G$1:$ZX$1, MATCH( LARGE( INDEX('ADR Tracking'!$G:$ZX, MATCH($A54, 'ADR Tracking'!$A:$A, 0), ), COLUMN()-4 ), INDEX('ADR Tracking'!$G:$ZX, MATCH($A54, 'ADR Tracking'!$A:$A, 0), ), 0 ) ), "" ) | F54: =IFERROR( INDEX('Project Assignment Check'!$G$1:$ZX$1, MATCH( LARGE( INDEX('ADR Tracking'!$G:$ZX, MATCH($A54, 'ADR Tracking'!$A:$A, 0), ), COLUMN()-4 ), INDEX('ADR Tracking'!$G:$ZX, MATCH($A54, 'ADR Tracking'!$A:$A, 0), ), 0 ) ), "" ) | G54: =IFERROR( INDEX('Project Assignment Check'!$G$1:$ZX$1, MATCH( LARGE( INDEX('ADR Tracking'!$G:$ZX, MATCH($A54, 'ADR Tracking'!$A:$A, 0), ), COLUMN()-4 ), INDEX('ADR Tracking'!$G:$ZX, MATCH($A54, 'ADR Tracking'!$A:$A, 0), ), 0 ) ), "" ) | H54: =IFERROR( INDEX('Project Assignment Check'!$G$1:$ZX$1, MATCH( LARGE( INDEX('ADR Tracking'!$G:$ZX, MATCH($A54, 'ADR Tracking'!$A:$A, 0), ), COLUMN()-4 ), INDEX('ADR Tracking'!$G:$ZX, MATCH($A54, 'ADR Tracking'!$A:$A, 0), ), 0 ) ), "" ) | I54: =IFERROR( INDEX('Project Assignment Check'!$G$1:$ZX$1, MATCH( LARGE( INDEX('ADR Tracking'!$G:$ZX, MATCH($A54, 'ADR Tracking'!$A:$A, 0), ), COLUMN()-4 ), INDEX('ADR Tracking'!$G:$ZX, MATCH($A54, 'ADR Tracking'!$A:$A, 0), ), 0 ) ), "" ) | J54: =IFERROR( INDEX('Project Assignment Check'!$G$1:$ZX$1, MATCH( LARGE( INDEX('ADR Tracking'!$G:$ZX, MATCH($A54, 'ADR Tracking'!$A:$A, 0), ), COLUMN()-4 ), INDEX('ADR Tracking'!$G:$ZX, MATCH($A54, 'ADR Tracking'!$A:$A, 0), ), 0 ) ), "" )
A55: SRP8-085 | B55: NVH | C55: Interior | E55: =IFERROR( INDEX('Project Assignment Check'!$G$1:$ZX$1, MATCH( LARGE( INDEX('ADR Tracking'!$G:$ZX, MATCH($A55, 'ADR Tracking'!$A:$A, 0), ), COLUMN()-4 ), INDEX('ADR Tracking'!$G:$ZX, MATCH($A55, 'ADR Tracking'!$A:$A, 0), ), 0 ) ), "" ) -> ADR-113 | F55: =IFERROR( INDEX('Project Assignment Check'!$G$1:$ZX$1, MATCH( LARGE( INDEX('ADR Tracking'!$G:$ZX, MATCH($A55, 'ADR Tracking'!$A:$A, 0), ), COLUMN()-4 ), INDEX('ADR Tracking'!$G:$ZX, MATCH($A55, 'ADR Tracking'!$A:$A, 0), ), 0 ) ), "" ) -> ADR-92 | G55: =IFERROR( INDEX('Project Assignment Check'!$G$1:$ZX$1, MATCH( LARGE( INDEX('ADR Tracking'!$G:$ZX, MATCH($A55, 'ADR Tracking'!$A:$A, 0), ), COLUMN()-4 ), INDEX('ADR Tracking'!$G:$ZX, MATCH($A55, 'ADR Tracking'!$A:$A, 0), ), 0 ) ), "" ) -> ADR-109 | H55: =IFERROR( INDEX('Project Assignment Check'!$G$1:$ZX$1, MATCH( LARGE( INDEX('ADR Tracking'!$G:$ZX, MATCH($A55, 'ADR Tracking'!$A:$A, 0), ), COLUMN()-4 ), INDEX('ADR Tracking'!$G:$ZX, MATCH($A55, 'ADR Tracking'!$A:$A, 0), ), 0 ) ), "" ) | I55: =IFERROR( INDEX('Project Assignment Check'!$G$1:$ZX$1, MATCH( LARGE( INDEX('ADR Tracking'!$G:$ZX, MATCH($A55, 'ADR Tracking'!$A:$A, 0), ), COLUMN()-4 ), INDEX('ADR Tracking'!$G:$ZX, MATCH($A55, 'ADR Tracking'!$A:$A, 0), ), 0 ) ), "" ) | J55: =IFERROR( INDEX('Project Assignment Check'!$G$1:$ZX$1, MATCH( LARGE( INDEX('ADR Tracking'!$G:$ZX, MATCH($A55, 'ADR Tracking'!$A:$A, 0), ), COLUMN()-4 ), INDEX('ADR Tracking'!$G:$ZX, MATCH($A55, 'ADR Tracking'!$A:$A, 0), ), 0 ) ), "" )
A56: SRP8-086 | B56: Transmission | C56: Powertrain | E56: =IFERROR( INDEX('Project Assignment Check'!$G$1:$ZX$1, MATCH( LARGE( INDEX('ADR Tracking'!$G:$ZX, MATCH($A56, 'ADR Tracking'!$A:$A, 0), ), COLUMN()-4 ), INDEX('ADR Tracking'!$G:$ZX, MATCH($A56, 'ADR Tracking'!$A:$A, 0), ), 0 ) ), "" ) -> ADR-42 | F56: =IFERROR( INDEX('Project Assignment Check'!$G$1:$ZX$1, MATCH( LARGE( INDEX('ADR Tracking'!$G:$ZX, MATCH($A56, 'ADR Tracking'!$A:$A, 0), ), COLUMN()-4 ), INDEX('ADR Tracking'!$G:$ZX, MATCH($A56, 'ADR Tracking'!$A:$A, 0), ), 0 ) ), "" ) -> ADR-42 | G56: =IFERROR( INDEX('Project Assignment Check'!$G$1:$ZX$1, MATCH( LARGE( INDEX('ADR Tracking'!$G:$ZX, MATCH($A56, 'ADR Tracking'!$A:$A, 0), ), COLUMN()-4 ), INDEX('ADR Tracking'!$G:$ZX, MATCH($A56, 'ADR Tracking'!$A:$A, 0), ), 0 ) ), "" ) | H56: =IFERROR( INDEX('Project Assignment Check'!$G$1:$ZX$1, MATCH( LARGE( INDEX('ADR Tracking'!$G:$ZX, MATCH($A56, 'ADR Tracking'!$A:$A, 0), ), COLUMN()-4 ), INDEX('ADR Tracking'!$G:$ZX, MATCH($A56, 'ADR Tracking'!$A:$A, 0), ), 0 ) ), "" ) | I56: =IFERROR( INDEX('Project Assignment Check'!$G$1:$ZX$1, MATCH( LARGE( INDEX('ADR Tracking'!$G:$ZX, MATCH($A56, 'ADR Tracking'!$A:$A, 0), ), COLUMN()-4 ), INDEX('ADR Tracking'!$G:$ZX, MATCH($A56, 'ADR Tracking'!$A:$A, 0), ), 0 ) ), "" ) | J56: =IFERROR( INDEX('Project Assignment Check'!$G$1:$ZX$1, MATCH( LARGE( INDEX('ADR Tracking'!$G:$ZX, MATCH($A56, 'ADR Tracking'!$A:$A, 0), ), COLUMN()-4 ), INDEX('ADR Tracking'!$G:$ZX, MATCH($A56, 'ADR Tracking'!$A:$A, 0), ), 0 ) ), "" )
A57: SRP8-088 | B57: Front Uprights | C57: Vehicle Dynamics | E57: =IFERROR( INDEX('Project Assignment Check'!$G$1:$ZX$1, MATCH( LARGE( INDEX('ADR Tracking'!$G:$ZX, MATCH($A57, 'ADR Tracking'!$A:$A, 0), ), COLUMN()-4 ), INDEX('ADR Tracking'!$G:$ZX, MATCH($A57, 'ADR Tracking'!$A:$A, 0), ), 0 ) ), "" ) -> ADR-90 | F57: =IFERROR( INDEX('Project Assignment Check'!$G$1:$ZX$1, MATCH( LARGE( INDEX('ADR Tracking'!$G:$ZX, MATCH($A57, 'ADR Tracking'!$A:$A, 0), ), COLUMN()-4 ), INDEX('ADR Tracking'!$G:$ZX, MATCH($A57, 'ADR Tracking'!$A:$A, 0), ), 0 ) ), "" ) | G57: =IFERROR( INDEX('Project Assignment Check'!$G$1:$ZX$1, MATCH( LARGE( INDEX('ADR Tracking'!$G:$ZX, MATCH($A57, 'ADR Tracking'!$A:$A, 0), ), COLUMN()-4 ), INDEX('ADR Tracking'!$G:$ZX, MATCH($A57, 'ADR Tracking'!$A:$A, 0), ), 0 ) ), "" ) | H57: =IFERROR( INDEX('Project Assignment Check'!$G$1:$ZX$1, MATCH( LARGE( INDEX('ADR Tracking'!$G:$ZX, MATCH($A57, 'ADR Tracking'!$A:$A, 0), ), COLUMN()-4 ), INDEX('ADR Tracking'!$G:$ZX, MATCH($A57, 'ADR Tracking'!$A:$A, 0), ), 0 ) ), "" ) | I57: =IFERROR( INDEX('Project Assignment Check'!$G$1:$ZX$1, MATCH( LARGE( INDEX('ADR Tracking'!$G:$ZX, MATCH($A57, 'ADR Tracking'!$A:$A, 0), ), COLUMN()-4 ), INDEX('ADR Tracking'!$G:$ZX, MATCH($A57, 'ADR Tracking'!$A:$A, 0), ), 0 ) ), "" ) | J57: =IFERROR( INDEX('Project Assignment Check'!$G$1:$ZX$1, MATCH( LARGE( INDEX('ADR Tracking'!$G:$ZX, MATCH($A57, 'ADR Tracking'!$A:$A, 0), ), COLUMN()-4 ), INDEX('ADR Tracking'!$G:$ZX, MATCH($A57, 'ADR Tracking'!$A:$A, 0), ), 0 ) ), "" )
A58: SRP8-089 | B58: Rear Uprights | C58: Vehicle Dynamics | E58: =IFERROR( INDEX('Project Assignment Check'!$G$1:$ZX$1, MATCH( LARGE( INDEX('ADR Tracking'!$G:$ZX, MATCH($A58, 'ADR Tracking'!$A:$A, 0), ), COLUMN()-4 ), INDEX('ADR Tracking'!$G:$ZX, MATCH($A58, 'ADR Tracking'!$A:$A, 0), ), 0 ) ), "" ) | F58: =IFERROR( INDEX('Project Assignment Check'!$G$1:$ZX$1, MATCH( LARGE( INDEX('ADR Tracking'!$G:$ZX, MATCH($A58, 'ADR Tracking'!$A:$A, 0), ), COLUMN()-4 ), INDEX('ADR Tracking'!$G:$ZX, MATCH($A58, 'ADR Tracking'!$A:$A, 0), ), 0 ) ), "" ) | G58: =IFERROR( INDEX('Project Assignment Check'!$G$1:$ZX$1, MATCH( LARGE( INDEX('ADR Tracking'!$G:$ZX, MATCH($A58, 'ADR Tracking'!$A:$A, 0), ), COLUMN()-4 ), INDEX('ADR Tracking'!$G:$ZX, MATCH($A58, 'ADR Tracking'!$A:$A, 0), ), 0 ) ), "" ) | H58: =IFERROR( INDEX('Project Assignment Check'!$G$1:$ZX$1, MATCH( LARGE( INDEX('ADR Tracking'!$G:$ZX, MATCH($A58, 'ADR Tracking'!$A:$A, 0), ), COLUMN()-4 ), INDEX('ADR Tracking'!$G:$ZX, MATCH($A58, 'ADR Tracking'!$A:$A, 0), ), 0 ) ), "" ) | I58: =IFERROR( INDEX('Project Assignment Check'!$G$1:$ZX$1, MATCH( LARGE( INDEX('ADR Tracking'!$G:$ZX, MATCH($A58, 'ADR Tracking'!$A:$A, 0), ), COLUMN()-4 ), INDEX('ADR Tracking'!$G:$ZX, MATCH($A58, 'ADR Tracking'!$A:$A, 0), ), 0 ) ), "" ) | J58: =IFERROR( INDEX('Project Assignment Check'!$G$1:$ZX$1, MATCH( LARGE( INDEX('ADR Tracking'!$G:$ZX, MATCH($A58, 'ADR Tracking'!$A:$A, 0), ), COLUMN()-4 ), INDEX('ADR Tracking'!$G:$ZX, MATCH($A58, 'ADR Tracking'!$A:$A, 0), ), 0 ) ), "" )
A59: SRP8-092 | B59: Auxiliary Systems Logic | C59: Embedded Systems | E59: =IFERROR( INDEX('Project Assignment Check'!$G$1:$ZX$1, MATCH( LARGE( INDEX('ADR Tracking'!$G:$ZX, MATCH($A59, 'ADR Tracking'!$A:$A, 0), ), COLUMN()-4 ), INDEX('ADR Tracking'!$G:$ZX, MATCH($A59, 'ADR Tracking'!$A:$A, 0), ), 0 ) ), "" ) | F59: =IFERROR( INDEX('Project Assignment Check'!$G$1:$ZX$1, MATCH( LARGE( INDEX('ADR Tracking'!$G:$ZX, MATCH($A59, 'ADR Tracking'!$A:$A, 0), ), COLUMN()-4 ), INDEX('ADR Tracking'!$G:$ZX, MATCH($A59, 'ADR Tracking'!$A:$A, 0), ), 0 ) ), "" ) | G59: =IFERROR( INDEX('Project Assignment Check'!$G$1:$ZX$1, MATCH( LARGE( INDEX('ADR Tracking'!$G:$ZX, MATCH($A59, 'ADR Tracking'!$A:$A, 0), ), COLUMN()-4 ), INDEX('ADR Tracking'!$G:$ZX, MATCH($A59, 'ADR Tracking'!$A:$A, 0), ), 0 ) ), "" ) | H59: =IFERROR( INDEX('Project Assignment Check'!$G$1:$ZX$1, MATCH( LARGE( INDEX('ADR Tracking'!$G:$ZX, MATCH($A59, 'ADR Tracking'!$A:$A, 0), ), COLUMN()-4 ), INDEX('ADR Tracking'!$G:$ZX, MATCH($A59, 'ADR Tracking'!$A:$A, 0), ), 0 ) ), "" ) | I59: =IFERROR( INDEX('Project Assignment Check'!$G$1:$ZX$1, MATCH( LARGE( INDEX('ADR Tracking'!$G:$ZX, MATCH($A59, 'ADR Tracking'!$A:$A, 0), ), COLUMN()-4 ), INDEX('ADR Tracking'!$G:$ZX, MATCH($A59, 'ADR Tracking'!$A:$A, 0), ), 0 ) ), "" ) | J59: =IFERROR( INDEX('Project Assignment Check'!$G$1:$ZX$1, MATCH( LARGE( INDEX('ADR Tracking'!$G:$ZX, MATCH($A59, 'ADR Tracking'!$A:$A, 0), ), COLUMN()-4 ), INDEX('ADR Tracking'!$G:$ZX, MATCH($A59, 'ADR Tracking'!$A:$A, 0), ), 0 ) ), "" )
A60: SRP8-093 | B60: Air Conditioning | C60: Chassis & Bodywork | E60: =IFERROR( INDEX('Project Assignment Check'!$G$1:$ZX$1, MATCH( LARGE( INDEX('ADR Tracking'!$G:$ZX, MATCH($A60, 'ADR Tracking'!$A:$A, 0), ), COLUMN()-4 ), INDEX('ADR Tracking'!$G:$ZX, MATCH($A60, 'ADR Tracking'!$A:$A, 0), ), 0 ) ), "" ) -> ADR-42 | F60: =IFERROR( INDEX('Project Assignment Check'!$G$1:$ZX$1, MATCH( LARGE( INDEX('ADR Tracking'!$G:$ZX, MATCH($A60, 'ADR Tracking'!$A:$A, 0), ), COLUMN()-4 ), INDEX('ADR Tracking'!$G:$ZX, MATCH($A60, 'ADR Tracking'!$A:$A, 0), ), 0 ) ), "" ) | G60: =IFERROR( INDEX('Project Assignment Check'!$G$1:$ZX$1, MATCH( LARGE( INDEX('ADR Tracking'!$G:$ZX, MATCH($A60, 'ADR Tracking'!$A:$A, 0), ), COLUMN()-4 ), INDEX('ADR Tracking'!$G:$ZX, MATCH($A60, 'ADR Tracking'!$A:$A, 0), ), 0 ) ), "" ) | H60: =IFERROR( INDEX('Project Assignment Check'!$G$1:$ZX$1, MATCH( LARGE( INDEX('ADR Tracking'!$G:$ZX, MATCH($A60, 'ADR Tracking'!$A:$A, 0), ), COLUMN()-4 ), INDEX('ADR Tracking'!$G:$ZX, MATCH($A60, 'ADR Tracking'!$A:$A, 0), ), 0 ) ), "" ) | I60: =IFERROR( INDEX('Project Assignment Check'!$G$1:$ZX$1, MATCH( LARGE( INDEX('ADR Tracking'!$G:$ZX, MATCH($A60, 'ADR Tracking'!$A:$A, 0), ), COLUMN()-4 ), INDEX('ADR Tracking'!$G:$ZX, MATCH($A60, 'ADR Tracking'!$A:$A, 0), ), 0 ) ), "" ) | J60: =IFERROR( INDEX('Project Assignment Check'!$G$1:$ZX$1, MATCH( LARGE( INDEX('ADR Tracking'!$G:$ZX, MATCH($A60, 'ADR Tracking'!$A:$A, 0), ), COLUMN()-4 ), INDEX('ADR Tracking'!$G:$ZX, MATCH($A60, 'ADR Tracking'!$A:$A, 0), ), 0 ) ), "" )
A61: SRP8-094 | B61: Thermal management | C61: Chassis & Bodywork | E61: =IFERROR( INDEX('Project Assignment Check'!$G$1:$ZX$1, MATCH( LARGE( INDEX('ADR Tracking'!$G:$ZX, MATCH($A61, 'ADR Tracking'!$A:$A, 0), ), COLUMN()-4 ), INDEX('ADR Tracking'!$G:$ZX, MATCH($A61, 'ADR Tracking'!$A:$A, 0), ), 0 ) ), "" ) | F61: =IFERROR( INDEX('Project Assignment Check'!$G$1:$ZX$1, MATCH( LARGE( INDEX('ADR Tracking'!$G:$ZX, MATCH($A61, 'ADR Tracking'!$A:$A, 0), ), COLUMN()-4 ), INDEX('ADR Tracking'!$G:$ZX, MATCH($A61, 'ADR Tracking'!$A:$A, 0), ), 0 ) ), "" ) | G61: =IFERROR( INDEX('Project Assignment Check'!$G$1:$ZX$1, MATCH( LARGE( INDEX('ADR Tracking'!$G:$ZX, MATCH($A61, 'ADR Tracking'!$A:$A, 0), ), COLUMN()-4 ), INDEX('ADR Tracking'!$G:$ZX, MATCH($A61, 'ADR Tracking'!$A:$A, 0), ), 0 ) ), "" ) | H61: =IFERROR( INDEX('Project Assignment Check'!$G$1:$ZX$1, MATCH( LARGE( INDEX('ADR Tracking'!$G:$ZX, MATCH($A61, 'ADR Tracking'!$A:$A, 0), ), COLUMN()-4 ), INDEX('ADR Tracking'!$G:$ZX, MATCH($A61, 'ADR Tracking'!$A:$A, 0), ), 0 ) ), "" ) | I61: =IFERROR( INDEX('Project Assignment Check'!$G$1:$ZX$1, MATCH( LARGE( INDEX('ADR Tracking'!$G:$ZX, MATCH($A61, 'ADR Tracking'!$A:$A, 0), ), COLUMN()-4 ), INDEX('ADR Tracking'!$G:$ZX, MATCH($A61, 'ADR Tracking'!$A:$A, 0), ), 0 ) ), "" ) | J61: =IFERROR( INDEX('Project Assignment Check'!$G$1:$ZX$1, MATCH( LARGE( INDEX('ADR Tracking'!$G:$ZX, MATCH($A61, 'ADR Tracking'!$A:$A, 0), ), COLUMN()-4 ), INDEX('ADR Tracking'!$G:$ZX, MATCH($A61, 'ADR Tracking'!$A:$A, 0), ), 0 ) ), "" )
A62: SRP8-099 | B62: Traction Control | C62: Embedded Systems | D62: Powertrain | E62: =IFERROR( INDEX('Project Assignment Check'!$G$1:$ZX$1, MATCH( LARGE( INDEX('ADR Tracking'!$G:$ZX, MATCH($A62, 'ADR Tracking'!$A:$A, 0), ), COLUMN()-4 ), INDEX('ADR Tracking'!$G:$ZX, MATCH($A62, 'ADR Tracking'!$A:$A, 0), ), 0 ) ), "" ) | F62: =IFERROR( INDEX('Project Assignment Check'!$G$1:$ZX$1, MATCH( LARGE( INDEX('ADR Tracking'!$G:$ZX, MATCH($A62, 'ADR Tracking'!$A:$A, 0), ), COLUMN()-4 ), INDEX('ADR Tracking'!$G:$ZX, MATCH($A62, 'ADR Tracking'!$A:$A, 0), ), 0 ) ), "" ) | G62: =IFERROR( INDEX('Project Assignment Check'!$G$1:$ZX$1, MATCH( LARGE( INDEX('ADR Tracking'!$G:$ZX, MATCH($A62, 'ADR Tracking'!$A:$A, 0), ), COLUMN()-4 ), INDEX('ADR Tracking'!$G:$ZX, MATCH($A62, 'ADR Tracking'!$A:$A, 0), ), 0 ) ), "" ) | H62: =IFERROR( INDEX('Project Assignment Check'!$G$1:$ZX$1, MATCH( LARGE( INDEX('ADR Tracking'!$G:$ZX, MATCH($A62, 'ADR Tracking'!$A:$A, 0), ), COLUMN()-4 ), INDEX('ADR Tracking'!$G:$ZX, MATCH($A62, 'ADR Tracking'!$A:$A, 0), ), 0 ) ), "" ) | I62: =IFERROR( INDEX('Project Assignment Check'!$G$1:$ZX$1, MATCH( LARGE( INDEX('ADR Tracking'!$G:$ZX, MATCH($A62, 'ADR Tracking'!$A:$A, 0), ), COLUMN()-4 ), INDEX('ADR Tracking'!$G:$ZX, MATCH($A62, 'ADR Tracking'!$A:$A, 0), ), 0 ) ), "" ) | J62: =IFERROR( INDEX('Project Assignment Check'!$G$1:$ZX$1, MATCH( LARGE( INDEX('ADR Tracking'!$G:$ZX, MATCH($A62, 'ADR Tracking'!$A:$A, 0), ), COLUMN()-4 ), INDEX('ADR Tracking'!$G:$ZX, MATCH($A62, 'ADR Tracking'!$A:$A, 0), ), 0 ) ), "" )
A63: SRP8-101 | B63: Trip Energy Prediction | C63: Technical Support Systems | E63: =IFERROR( INDEX('Project Assignment Check'!$G$1:$ZX$1, MATCH( LARGE( INDEX('ADR Tracking'!$G:$ZX, MATCH($A63, 'ADR Tracking'!$A:$A, 0), ), COLUMN()-4 ), INDEX('ADR Tracking'!$G:$ZX, MATCH($A63, 'ADR Tracking'!$A:$A, 0), ), 0 ) ), "" ) | F63: =IFERROR( INDEX('Project Assignment Check'!$G$1:$ZX$1, MATCH( LARGE( INDEX('ADR Tracking'!$G:$ZX, MATCH($A63, 'ADR Tracking'!$A:$A, 0), ), COLUMN()-4 ), INDEX('ADR Tracking'!$G:$ZX, MATCH($A63, 'ADR Tracking'!$A:$A, 0), ), 0 ) ), "" ) | G63: =IFERROR( INDEX('Project Assignment Check'!$G$1:$ZX$1, MATCH( LARGE( INDEX('ADR Tracking'!$G:$ZX, MATCH($A63, 'ADR Tracking'!$A:$A, 0), ), COLUMN()-4 ), INDEX('ADR Tracking'!$G:$ZX, MATCH($A63, 'ADR Tracking'!$A:$A, 0), ), 0 ) ), "" ) | H63: =IFERROR( INDEX('Project Assignment Check'!$G$1:$ZX$1, MATCH( LARGE( INDEX('ADR Tracking'!$G:$ZX, MATCH($A63, 'ADR Tracking'!$A:$A, 0), ), COLUMN()-4 ), INDEX('ADR Tracking'!$G:$ZX, MATCH($A63, 'ADR Tracking'!$A:$A, 0), ), 0 ) ), "" ) | I63: =IFERROR( INDEX('Project Assignment Check'!$G$1:$ZX$1, MATCH( LARGE( INDEX('ADR Tracking'!$G:$ZX, MATCH($A63, 'ADR Tracking'!$A:$A, 0), ), COLUMN()-4 ), INDEX('ADR Tracking'!$G:$ZX, MATCH($A63, 'ADR Tracking'!$A:$A, 0), ), 0 ) ), "" ) | J63: =IFERROR( INDEX('Project Assignment Check'!$G$1:$ZX$1, MATCH( LARGE( INDEX('ADR Tracking'!$G:$ZX, MATCH($A63, 'ADR Tracking'!$A:$A, 0), ), COLUMN()-4 ), INDEX('ADR Tracking'!$G:$ZX, MATCH($A63, 'ADR Tracking'!$A:$A, 0), ), 0 ) ), "" )
A64: SRP8-103 | B64: Embedded Standard Low Level Circuitry | C64: Embedded Systems | E64: =IFERROR( INDEX('Project Assignment Check'!$G$1:$ZX$1, MATCH( LARGE( INDEX('ADR Tracking'!$G:$ZX, MATCH($A64, 'ADR Tracking'!$A:$A, 0), ), COLUMN()-4 ), INDEX('ADR Tracking'!$G:$ZX, MATCH($A64, 'ADR Tracking'!$A:$A, 0), ), 0 ) ), "" ) | F64: =IFERROR( INDEX('Project Assignment Check'!$G$1:$ZX$1, MATCH( LARGE( INDEX('ADR Tracking'!$G:$ZX, MATCH($A64, 'ADR Tracking'!$A:$A, 0), ), COLUMN()-4 ), INDEX('ADR Tracking'!$G:$ZX, MATCH($A64, 'ADR Tracking'!$A:$A, 0), ), 0 ) ), "" ) | G64: =IFERROR( INDEX('Project Assignment Check'!$G$1:$ZX$1, MATCH( LARGE( INDEX('ADR Tracking'!$G:$ZX, MATCH($A64, 'ADR Tracking'!$A:$A, 0), ), COLUMN()-4 ), INDEX('ADR Tracking'!$G:$ZX, MATCH($A64, 'ADR Tracking'!$A:$A, 0), ), 0 ) ), "" ) | H64: =IFERROR( INDEX('Project Assignment Check'!$G$1:$ZX$1, MATCH( LARGE( INDEX('ADR Tracking'!$G:$ZX, MATCH($A64, 'ADR Tracking'!$A:$A, 0), ), COLUMN()-4 ), INDEX('ADR Tracking'!$G:$ZX, MATCH($A64, 'ADR Tracking'!$A:$A, 0), ), 0 ) ), "" ) | I64: =IFERROR( INDEX('Project Assignment Check'!$G$1:$ZX$1, MATCH( LARGE( INDEX('ADR Tracking'!$G:$ZX, MATCH($A64, 'ADR Tracking'!$A:$A, 0), ), COLUMN()-4 ), INDEX('ADR Tracking'!$G:$ZX, MATCH($A64, 'ADR Tracking'!$A:$A, 0), ), 0 ) ), "" ) | J64: =IFERROR( INDEX('Project Assignment Check'!$G$1:$ZX$1, MATCH( LARGE( INDEX('ADR Tracking'!$G:$ZX, MATCH($A64, 'ADR Tracking'!$A:$A, 0), ), COLUMN()-4 ), INDEX('ADR Tracking'!$G:$ZX, MATCH($A64, 'ADR Tracking'!$A:$A, 0), ), 0 ) ), "" )
A65: SRP8-111 | B65: Central Locking | C65: Embedded Systems | D65: Vehicle Dynamics | E65: =IFERROR( INDEX('Project Assignment Check'!$G$1:$ZX$1, MATCH( LARGE( INDEX('ADR Tracking'!$G:$ZX, MATCH($A65, 'ADR Tracking'!$A:$A, 0), ), COLUMN()-4 ), INDEX('ADR Tracking'!$G:$ZX, MATCH($A65, 'ADR Tracking'!$A:$A, 0), ), 0 ) ), "" ) -> ADR-25 | F65: =IFERROR( INDEX('Project Assignment Check'!$G$1:$ZX$1, MATCH( LARGE( INDEX('ADR Tracking'!$G:$ZX, MATCH($A65, 'ADR Tracking'!$A:$A, 0), ), COLUMN()-4 ), INDEX('ADR Tracking'!$G:$ZX, MATCH($A65, 'ADR Tracking'!$A:$A, 0), ), 0 ) ), "" ) -> ADR-42 | G65: =IFERROR( INDEX('Project Assignment Check'!$G$1:$ZX$1, MATCH( LARGE( INDEX('ADR Tracking'!$G:$ZX, MATCH($A65, 'ADR Tracking'!$A:$A, 0), ), COLUMN()-4 ), INDEX('ADR Tracking'!$G:$ZX, MATCH($A65, 'ADR Tracking'!$A:$A, 0), ), 0 ) ), "" ) -> ADR-02 | H65: =IFERROR( INDEX('Project Assignment Check'!$G$1:$ZX$1, MATCH( LARGE( INDEX('ADR Tracking'!$G:$ZX, MATCH($A65, 'ADR Tracking'!$A:$A, 0), ), COLUMN()-4 ), INDEX('ADR Tracking'!$G:$ZX, MATCH($A65, 'ADR Tracking'!$A:$A, 0), ), 0 ) ), "" ) | I65: =IFERROR( INDEX('Project Assignment Check'!$G$1:$ZX$1, MATCH( LARGE( INDEX('ADR Tracking'!$G:$ZX, MATCH($A65, 'ADR Tracking'!$A:$A, 0), ), COLUMN()-4 ), INDEX('ADR Tracking'!$G:$ZX, MATCH($A65, 'ADR Tracking'!$A:$A, 0), ), 0 ) ), "" ) | J65: =IFERROR( INDEX('Project Assignment Check'!$G$1:$ZX$1, MATCH( LARGE( INDEX('ADR Tracking'!$G:$ZX, MATCH($A65, 'ADR Tracking'!$A:$A, 0), ), COLUMN()-4 ), INDEX('ADR Tracking'!$G:$ZX, MATCH($A65, 'ADR Tracking'!$A:$A, 0), ), 0 ) ), "" )
A66: SRP8-112 | B66: Electric Windows | C66: Chassis & Bodywork | D66: Embedded Systems | E66: =IFERROR( INDEX('Project Assignment Check'!$G$1:$ZX$1, MATCH( LARGE( INDEX('ADR Tracking'!$G:$ZX, MATCH($A66, 'ADR Tracking'!$A:$A, 0), ), COLUMN()-4 ), INDEX('ADR Tracking'!$G:$ZX, MATCH($A66, 'ADR Tracking'!$A:$A, 0), ), 0 ) ), "" ) -> ADR-42 | F66: =IFERROR( INDEX('Project Assignment Check'!$G$1:$ZX$1, MATCH( LARGE( INDEX('ADR Tracking'!$G:$ZX, MATCH($A66, 'ADR Tracking'!$A:$A, 0), ), COLUMN()-4 ), INDEX('ADR Tracking'!$G:$ZX, MATCH($A66, 'ADR Tracking'!$A:$A, 0), ), 0 ) ), "" ) -> ADR-08 | G66: =IFERROR( INDEX('Project Assignment Check'!$G$1:$ZX$1, MATCH( LARGE( INDEX('ADR Tracking'!$G:$ZX, MATCH($A66, 'ADR Tracking'!$A:$A, 0), ), COLUMN()-4 ), INDEX('ADR Tracking'!$G:$ZX, MATCH($A66, 'ADR Tracking'!$A:$A, 0), ), 0 ) ), "" ) -> ADR-21 | H66: =IFERROR( INDEX('Project Assignment Check'!$G$1:$ZX$1, MATCH( LARGE( INDEX('ADR Tracking'!$G:$ZX, MATCH($A66, 'ADR Tracking'!$A:$A, 0), ), COLUMN()-4 ), INDEX('ADR Tracking'!$G:$ZX, MATCH($A66, 'ADR Tracking'!$A:$A, 0), ), 0 ) ), "" ) | I66: =IFERROR( INDEX('Project Assignment Check'!$G$1:$ZX$1, MATCH( LARGE( INDEX('ADR Tracking'!$G:$ZX, MATCH($A66, 'ADR Tracking'!$A:$A, 0), ), COLUMN()-4 ), INDEX('ADR Tracking'!$G:$ZX, MATCH($A66, 'ADR Tracking'!$A:$A, 0), ), 0 ) ), "" ) | J66: =IFERROR( INDEX('Project Assignment Check'!$G$1:$ZX$1, MATCH( LARGE( INDEX('ADR Tracking'!$G:$ZX, MATCH($A66, 'ADR Tracking'!$A:$A, 0), ), COLUMN()-4 ), INDEX('ADR Tracking'!$G:$ZX, MATCH($A66, 'ADR Tracking'!$A:$A, 0), ), 0 ) ), "" )
A67: SRP8-115 | B67: Tyre Pressure Monitoring System | C67: Vehicle Dynamics | D67: Embedded Systems | E67: =IFERROR( INDEX('Project Assignment Check'!$G$1:$ZX$1, MATCH( LARGE( INDEX('ADR Tracking'!$G:$ZX, MATCH($A67, 'ADR Tracking'!$A:$A, 0), ), COLUMN()-4 ), INDEX('ADR Tracking'!$G:$ZX, MATCH($A67, 'ADR Tracking'!$A:$A, 0), ), 0 ) ), "" ) | F67: =IFERROR( INDEX('Project Assignment Check'!$G$1:$ZX$1, MATCH( LARGE( INDEX('ADR Tracking'!$G:$ZX, MATCH($A67, 'ADR Tracking'!$A:$A, 0), ), COLUMN()-4 ), INDEX('ADR Tracking'!$G:$ZX, MATCH($A67, 'ADR Tracking'!$A:$A, 0), ), 0 ) ), "" ) | G67: =IFERROR( INDEX('Project Assignment Check'!$G$1:$ZX$1, MATCH( LARGE( INDEX('ADR Tracking'!$G:$ZX, MATCH($A67, 'ADR Tracking'!$A:$A, 0), ), COLUMN()-4 ), INDEX('ADR Tracking'!$G:$ZX, MATCH($A67, 'ADR Tracking'!$A:$A, 0), ), 0 ) ), "" ) | H67: =IFERROR( INDEX('Project Assignment Check'!$G$1:$ZX$1, MATCH( LARGE( INDEX('ADR Tracking'!$G:$ZX, MATCH($A67, 'ADR Tracking'!$A:$A, 0), ), COLUMN()-4 ), INDEX('ADR Tracking'!$G:$ZX, MATCH($A67, 'ADR Tracking'!$A:$A, 0), ), 0 ) ), "" ) | I67: =IFERROR( INDEX('Project Assignment Check'!$G$1:$ZX$1, MATCH( LARGE( INDEX('ADR Tracking'!$G:$ZX, MATCH($A67, 'ADR Tracking'!$A:$A, 0), ), COLUMN()-4 ), INDEX('ADR Tracking'!$G:$ZX, MATCH($A67, 'ADR Tracking'!$A:$A, 0), ), 0 ) ), "" ) | J67: =IFERROR( INDEX('Project Assignment Check'!$G$1:$ZX$1, MATCH( LARGE( INDEX('ADR Tracking'!$G:$ZX, MATCH($A67, 'ADR Tracking'!$A:$A, 0), ), COLUMN()-4 ), INDEX('ADR Tracking'!$G:$ZX, MATCH($A67, 'ADR Tracking'!$A:$A, 0), ), 0 ) ), "" )
A68: SRP8-124 | B68: Hydrogen Energy System | C68: Alternative Energies | E68: =IFERROR( INDEX('Project Assignment Check'!$G$1:$ZX$1, MATCH( LARGE( INDEX('ADR Tracking'!$G:$ZX, MATCH($A68, 'ADR Tracking'!$A:$A, 0), ), COLUMN()-4 ), INDEX('ADR Tracking'!$G:$ZX, MATCH($A68, 'ADR Tracking'!$A:$A, 0), ), 0 ) ), "" ) -> ADR-109 | F68: =IFERROR( INDEX('Project Assignment Check'!$G$1:$ZX$1, MATCH( LARGE( INDEX('ADR Tracking'!$G:$ZX, MATCH($A68, 'ADR Tracking'!$A:$A, 0), ), COLUMN()-4 ), INDEX('ADR Tracking'!$G:$ZX, MATCH($A68, 'ADR Tracking'!$A:$A, 0), ), 0 ) ), "" ) -> ADR-109 | G68: =IFERROR( INDEX('Project Assignment Check'!$G$1:$ZX$1, MATCH( LARGE( INDEX('ADR Tracking'!$G:$ZX, MATCH($A68, 'ADR Tracking'!$A:$A, 0), ), COLUMN()-4 ), INDEX('ADR Tracking'!$G:$ZX, MATCH($A68, 'ADR Tracking'!$A:$A, 0), ), 0 ) ), "" ) | H68: =IFERROR( INDEX('Project Assignment Check'!$G$1:$ZX$1, MATCH( LARGE( INDEX('ADR Tracking'!$G:$ZX, MATCH($A68, 'ADR Tracking'!$A:$A, 0), ), COLUMN()-4 ), INDEX('ADR Tracking'!$G:$ZX, MATCH($A68, 'ADR Tracking'!$A:$A, 0), ), 0 ) ), "" ) | I68: =IFERROR( INDEX('Project Assignment Check'!$G$1:$ZX$1, MATCH( LARGE( INDEX('ADR Tracking'!$G:$ZX, MATCH($A68, 'ADR Tracking'!$A:$A, 0), ), COLUMN()-4 ), INDEX('ADR Tracking'!$G:$ZX, MATCH($A68, 'ADR Tracking'!$A:$A, 0), ), 0 ) ), "" ) | J68: =IFERROR( INDEX('Project Assignment Check'!$G$1:$ZX$1, MATCH( LARGE( INDEX('ADR Tracking'!$G:$ZX, MATCH($A68, 'ADR Tracking'!$A:$A, 0), ), COLUMN()-4 ), INDEX('ADR Tracking'!$G:$ZX, MATCH($A68, 'ADR Tracking'!$A:$A, 0), ), 0 ) ), "" )
A69: SRP8-128 | B69: ABS Brakes | C69: Embedded Systems | E69: =IFERROR( INDEX('Project Assignment Check'!$G$1:$ZX$1, MATCH( LARGE( INDEX('ADR Tracking'!$G:$ZX, MATCH($A69, 'ADR Tracking'!$A:$A, 0), ), COLUMN()-4 ), INDEX('ADR Tracking'!$G:$ZX, MATCH($A69, 'ADR Tracking'!$A:$A, 0), ), 0 ) ), "" ) | F69: =IFERROR( INDEX('Project Assignment Check'!$G$1:$ZX$1, MATCH( LARGE( INDEX('ADR Tracking'!$G:$ZX, MATCH($A69, 'ADR Tracking'!$A:$A, 0), ), COLUMN()-4 ), INDEX('ADR Tracking'!$G:$ZX, MATCH($A69, 'ADR Tracking'!$A:$A, 0), ), 0 ) ), "" ) | G69: =IFERROR( INDEX('Project Assignment Check'!$G$1:$ZX$1, MATCH( LARGE( INDEX('ADR Tracking'!$G:$ZX, MATCH($A69, 'ADR Tracking'!$A:$A, 0), ), COLUMN()-4 ), INDEX('ADR Tracking'!$G:$ZX, MATCH($A69, 'ADR Tracking'!$A:$A, 0), ), 0 ) ), "" ) | H69: =IFERROR( INDEX('Project Assignment Check'!$G$1:$ZX$1, MATCH( LARGE( INDEX('ADR Tracking'!$G:$ZX, MATCH($A69, 'ADR Tracking'!$A:$A, 0), ), COLUMN()-4 ), INDEX('ADR Tracking'!$G:$ZX, MATCH($A69, 'ADR Tracking'!$A:$A, 0), ), 0 ) ), "" ) | I69: =IFERROR( INDEX('Project Assignment Check'!$G$1:$ZX$1, MATCH( LARGE( INDEX('ADR Tracking'!$G:$ZX, MATCH($A69, 'ADR Tracking'!$A:$A, 0), ), COLUMN()-4 ), INDEX('ADR Tracking'!$G:$ZX, MATCH($A69, 'ADR Tracking'!$A:$A, 0), ), 0 ) ), "" ) | J69: =IFERROR( INDEX('Project Assignment Check'!$G$1:$ZX$1, MATCH( LARGE( INDEX('ADR Tracking'!$G:$ZX, MATCH($A69, 'ADR Tracking'!$A:$A, 0), ), COLUMN()-4 ), INDEX('ADR Tracking'!$G:$ZX, MATCH($A69, 'ADR Tracking'!$A:$A, 0), ), 0 ) ), "" )
A70: SRP8-129 | B70: Embedded Low Level Code | C70: Embedded Systems | D70: Vehicle Dynamics | E70: =IFERROR( INDEX('Project Assignment Check'!$G$1:$ZX$1, MATCH( LARGE( INDEX('ADR Tracking'!$G:$ZX, MATCH($A70, 'ADR Tracking'!$A:$A, 0), ), COLUMN()-4 ), INDEX('ADR Tracking'!$G:$ZX, MATCH($A70, 'ADR Tracking'!$A:$A, 0), ), 0 ) ), "" ) | F70: =IFERROR( INDEX('Project Assignment Check'!$G$1:$ZX$1, MATCH( LARGE( INDEX('ADR Tracking'!$G:$ZX, MATCH($A70, 'ADR Tracking'!$A:$A, 0), ), COLUMN()-4 ), INDEX('ADR Tracking'!$G:$ZX, MATCH($A70, 'ADR Tracking'!$A:$A, 0), ), 0 ) ), "" ) | G70: =IFERROR( INDEX('Project Assignment Check'!$G$1:$ZX$1, MATCH( LARGE( INDEX('ADR Tracking'!$G:$ZX, MATCH($A70, 'ADR Tracking'!$A:$A, 0), ), COLUMN()-4 ), INDEX('ADR Tracking'!$G:$ZX, MATCH($A70, 'ADR Tracking'!$A:$A, 0), ), 0 ) ), "" ) | H70: =IFERROR( INDEX('Project Assignment Check'!$G$1:$ZX$1, MATCH( LARGE( INDEX('ADR Tracking'!$G:$ZX, MATCH($A70, 'ADR Tracking'!$A:$A, 0), ), COLUMN()-4 ), INDEX('ADR Tracking'!$G:$ZX, MATCH($A70, 'ADR Tracking'!$A:$A, 0), ), 0 ) ), "" ) | I70: =IFERROR( INDEX('Project Assignment Check'!$G$1:$ZX$1, MATCH( LARGE( INDEX('ADR Tracking'!$G:$ZX, MATCH($A70, 'ADR Tracking'!$A:$A, 0), ), COLUMN()-4 ), INDEX('ADR Tracking'!$G:$ZX, MATCH($A70, 'ADR Tracking'!$A:$A, 0), ), 0 ) ), "" ) | J70: =IFERROR( INDEX('Project Assignment Check'!$G$1:$ZX$1, MATCH( LARGE( INDEX('ADR Tracking'!$G:$ZX, MATCH($A70, 'ADR Tracking'!$A:$A, 0), ), COLUMN()-4 ), INDEX('ADR Tracking'!$G:$ZX, MATCH($A70, 'ADR Tracking'!$A:$A, 0), ), 0 ) ), "" )
A71: SRP8-130 | B71: Embedded High Level Software Archictecture | C71: Embedded Systems | E71: =IFERROR( INDEX('Project Assignment Check'!$G$1:$ZX$1, MATCH( LARGE( INDEX('ADR Tracking'!$G:$ZX, MATCH($A71, 'ADR Tracking'!$A:$A, 0), ), COLUMN()-4 ), INDEX('ADR Tracking'!$G:$ZX, MATCH($A71, 'ADR Tracking'!$A:$A, 0), ), 0 ) ), "" ) | F71: =IFERROR( INDEX('Project Assignment Check'!$G$1:$ZX$1, MATCH( LARGE( INDEX('ADR Tracking'!$G:$ZX, MATCH($A71, 'ADR Tracking'!$A:$A, 0), ), COLUMN()-4 ), INDEX('ADR Tracking'!$G:$ZX, MATCH($A71, 'ADR Tracking'!$A:$A, 0), ), 0 ) ), "" ) | G71: =IFERROR( INDEX('Project Assignment Check'!$G$1:$ZX$1, MATCH( LARGE( INDEX('ADR Tracking'!$G:$ZX, MATCH($A71, 'ADR Tracking'!$A:$A, 0), ), COLUMN()-4 ), INDEX('ADR Tracking'!$G:$ZX, MATCH($A71, 'ADR Tracking'!$A:$A, 0), ), 0 ) ), "" ) | H71: =IFERROR( INDEX('Project Assignment Check'!$G$1:$ZX$1, MATCH( LARGE( INDEX('ADR Tracking'!$G:$ZX, MATCH($A71, 'ADR Tracking'!$A:$A, 0), ), COLUMN()-4 ), INDEX('ADR Tracking'!$G:$ZX, MATCH($A71, 'ADR Tracking'!$A:$A, 0), ), 0 ) ), "" ) | I71: =IFERROR( INDEX('Project Assignment Check'!$G$1:$ZX$1, MATCH( LARGE( INDEX('ADR Tracking'!$G:$ZX, MATCH($A71, 'ADR Tracking'!$A:$A, 0), ), COLUMN()-4 ), INDEX('ADR Tracking'!$G:$ZX, MATCH($A71, 'ADR Tracking'!$A:$A, 0), ), 0 ) ), "" ) | J71: =IFERROR( INDEX('Project Assignment Check'!$G$1:$ZX$1, MATCH( LARGE( INDEX('ADR Tracking'!$G:$ZX, MATCH($A71, 'ADR Tracking'!$A:$A, 0), ), COLUMN()-4 ), INDEX('ADR Tracking'!$G:$ZX, MATCH($A71, 'ADR Tracking'!$A:$A, 0), ), 0 ) ), "" )
A72: SRP8-131 | B72: Hydrogen Pressure Vessel | C72: Alternative Energies | E72: =IFERROR( INDEX('Project Assignment Check'!$G$1:$ZX$1, MATCH( LARGE( INDEX('ADR Tracking'!$G:$ZX, MATCH($A72, 'ADR Tracking'!$A:$A, 0), ), COLUMN()-4 ), INDEX('ADR Tracking'!$G:$ZX, MATCH($A72, 'ADR Tracking'!$A:$A, 0), ), 0 ) ), "" ) -> ADR-110 | F72: =IFERROR( INDEX('Project Assignment Check'!$G$1:$ZX$1, MATCH( LARGE( INDEX('ADR Tracking'!$G:$ZX, MATCH($A72, 'ADR Tracking'!$A:$A, 0), ), COLUMN()-4 ), INDEX('ADR Tracking'!$G:$ZX, MATCH($A72, 'ADR Tracking'!$A:$A, 0), ), 0 ) ), "" ) | G72: =IFERROR( INDEX('Project Assignment Check'!$G$1:$ZX$1, MATCH( LARGE( INDEX('ADR Tracking'!$G:$ZX, MATCH($A72, 'ADR Tracking'!$A:$A, 0), ), COLUMN()-4 ), INDEX('ADR Tracking'!$G:$ZX, MATCH($A72, 'ADR Tracking'!$A:$A, 0), ), 0 ) ), "" ) | H72: =IFERROR( INDEX('Project Assignment Check'!$G$1:$ZX$1, MATCH( LARGE( INDEX('ADR Tracking'!$G:$ZX, MATCH($A72, 'ADR Tracking'!$A:$A, 0), ), COLUMN()-4 ), INDEX('ADR Tracking'!$G:$ZX, MATCH($A72, 'ADR Tracking'!$A:$A, 0), ), 0 ) ), "" ) | I72: =IFERROR( INDEX('Project Assignment Check'!$G$1:$ZX$1, MATCH( LARGE( INDEX('ADR Tracking'!$G:$ZX, MATCH($A72, 'ADR Tracking'!$A:$A, 0), ), COLUMN()-4 ), INDEX('ADR Tracking'!$G:$ZX, MATCH($A72, 'ADR Tracking'!$A:$A, 0), ), 0 ) ), "" ) | J72: =IFERROR( INDEX('Project Assignment Check'!$G$1:$ZX$1, MATCH( LARGE( INDEX('ADR Tracking'!$G:$ZX, MATCH($A72, 'ADR Tracking'!$A:$A, 0), ), COLUMN()-4 ), INDEX('ADR Tracking'!$G:$ZX, MATCH($A72, 'ADR Tracking'!$A:$A, 0), ), 0 ) ), "" )
A73: SRP8-132 | B73: Infotainment | C73: Technical Support Systems | D73: Embedded Systems | E73: =IFERROR( INDEX('Project Assignment Check'!$G$1:$ZX$1, MATCH( LARGE( INDEX('ADR Tracking'!$G:$ZX, MATCH($A73, 'ADR Tracking'!$A:$A, 0), ), COLUMN()-4 ), INDEX('ADR Tracking'!$G:$ZX, MATCH($A73, 'ADR Tracking'!$A:$A, 0), ), 0 ) ), "" ) | F73: =IFERROR( INDEX('Project Assignment Check'!$G$1:$ZX$1, MATCH( LARGE( INDEX('ADR Tracking'!$G:$ZX, MATCH($A73, 'ADR Tracking'!$A:$A, 0), ), COLUMN()-4 ), INDEX('ADR Tracking'!$G:$ZX, MATCH($A73, 'ADR Tracking'!$A:$A, 0), ), 0 ) ), "" ) | G73: =IFERROR( INDEX('Project Assignment Check'!$G$1:$ZX$1, MATCH( LARGE( INDEX('ADR Tracking'!$G:$ZX, MATCH($A73, 'ADR Tracking'!$A:$A, 0), ), COLUMN()-4 ), INDEX('ADR Tracking'!$G:$ZX, MATCH($A73, 'ADR Tracking'!$A:$A, 0), ), 0 ) ), "" ) | H73: =IFERROR( INDEX('Project Assignment Check'!$G$1:$ZX$1, MATCH( LARGE( INDEX('ADR Tracking'!$G:$ZX, MATCH($A73, 'ADR Tracking'!$A:$A, 0), ), COLUMN()-4 ), INDEX('ADR Tracking'!$G:$ZX, MATCH($A73, 'ADR Tracking'!$A:$A, 0), ), 0 ) ), "" ) | I73: =IFERROR( INDEX('Project Assignment Check'!$G$1:$ZX$1, MATCH( LARGE( INDEX('ADR Tracking'!$G:$ZX, MATCH($A73, 'ADR Tracking'!$A:$A, 0), ), COLUMN()-4 ), INDEX('ADR Tracking'!$G:$ZX, MATCH($A73, 'ADR Tracking'!$A:$A, 0), ), 0 ) ), "" ) | J73: =IFERROR( INDEX('Project Assignment Check'!$G$1:$ZX$1, MATCH( LARGE( INDEX('ADR Tracking'!$G:$ZX, MATCH($A73, 'ADR Tracking'!$A:$A, 0), ), COLUMN()-4 ), INDEX('ADR Tracking'!$G:$ZX, MATCH($A73, 'ADR Tracking'!$A:$A, 0), ), 0 ) ), "" )
A74: SRP8-133 | B74: Hydrogen Fuel Cell | C74: Alternative Energies | E74: =IFERROR( INDEX('Project Assignment Check'!$G$1:$ZX$1, MATCH( LARGE( INDEX('ADR Tracking'!$G:$ZX, MATCH($A74, 'ADR Tracking'!$A:$A, 0), ), COLUMN()-4 ), INDEX('ADR Tracking'!$G:$ZX, MATCH($A74, 'ADR Tracking'!$A:$A, 0), ), 0 ) ), "" ) | F74: =IFERROR( INDEX('Project Assignment Check'!$G$1:$ZX$1, MATCH( LARGE( INDEX('ADR Tracking'!$G:$ZX, MATCH($A74, 'ADR Tracking'!$A:$A, 0), ), COLUMN()-4 ), INDEX('ADR Tracking'!$G:$ZX, MATCH($A74, 'ADR Tracking'!$A:$A, 0), ), 0 ) ), "" ) | G74: =IFERROR( INDEX('Project Assignment Check'!$G$1:$ZX$1, MATCH( LARGE( INDEX('ADR Tracking'!$G:$ZX, MATCH($A74, 'ADR Tracking'!$A:$A, 0), ), COLUMN()-4 ), INDEX('ADR Tracking'!$G:$ZX, MATCH($A74, 'ADR Tracking'!$A:$A, 0), ), 0 ) ), "" ) | H74: =IFERROR( INDEX('Project Assignment Check'!$G$1:$ZX$1, MATCH( LARGE( INDEX('ADR Tracking'!$G:$ZX, MATCH($A74, 'ADR Tracking'!$A:$A, 0), ), COLUMN()-4 ), INDEX('ADR Tracking'!$G:$ZX, MATCH($A74, 'ADR Tracking'!$A:$A, 0), ), 0 ) ), "" ) | I74: =IFERROR( INDEX('Project Assignment Check'!$G$1:$ZX$1, MATCH( LARGE( INDEX('ADR Tracking'!$G:$ZX, MATCH($A74, 'ADR Tracking'!$A:$A, 0), ), COLUMN()-4 ), INDEX('ADR Tracking'!$G:$ZX, MATCH($A74, 'ADR Tracking'!$A:$A, 0), ), 0 ) ), "" ) | J74: =IFERROR( INDEX('Project Assignment Check'!$G$1:$ZX$1, MATCH( LARGE( INDEX('ADR Tracking'!$G:$ZX, MATCH($A74, 'ADR Tracking'!$A:$A, 0), ), COLUMN()-4 ), INDEX('ADR Tracking'!$G:$ZX, MATCH($A74, 'ADR Tracking'!$A:$A, 0), ), 0 ) ), "" )
A75: SRP8-156 | B75: Phone Charging | C75: Interior | E75: =IFERROR( INDEX('Project Assignment Check'!$G$1:$ZX$1, MATCH( LARGE( INDEX('ADR Tracking'!$G:$ZX, MATCH($A75, 'ADR Tracking'!$A:$A, 0), ), COLUMN()-4 ), INDEX('ADR Tracking'!$G:$ZX, MATCH($A75, 'ADR Tracking'!$A:$A, 0), ), 0 ) ), "" ) | F75: =IFERROR( INDEX('Project Assignment Check'!$G$1:$ZX$1, MATCH( LARGE( INDEX('ADR Tracking'!$G:$ZX, MATCH($A75, 'ADR Tracking'!$A:$A, 0), ), COLUMN()-4 ), INDEX('ADR Tracking'!$G:$ZX, MATCH($A75, 'ADR Tracking'!$A:$A, 0), ), 0 ) ), "" ) | G75: =IFERROR( INDEX('Project Assignment Check'!$G$1:$ZX$1, MATCH( LARGE( INDEX('ADR Tracking'!$G:$ZX, MATCH($A75, 'ADR Tracking'!$A:$A, 0), ), COLUMN()-4 ), INDEX('ADR Tracking'!$G:$ZX, MATCH($A75, 'ADR Tracking'!$A:$A, 0), ), 0 ) ), "" ) | H75: =IFERROR( INDEX('Project Assignment Check'!$G$1:$ZX$1, MATCH( LARGE( INDEX('ADR Tracking'!$G:$ZX, MATCH($A75, 'ADR Tracking'!$A:$A, 0), ), COLUMN()-4 ), INDEX('ADR Tracking'!$G:$ZX, MATCH($A75, 'ADR Tracking'!$A:$A, 0), ), 0 ) ), "" ) | I75: =IFERROR( INDEX('Project Assignment Check'!$G$1:$ZX$1, MATCH( LARGE( INDEX('ADR Tracking'!$G:$ZX, MATCH($A75, 'ADR Tracking'!$A:$A, 0), ), COLUMN()-4 ), INDEX('ADR Tracking'!$G:$ZX, MATCH($A75, 'ADR Tracking'!$A:$A, 0), ), 0 ) ), "" ) | J75: =IFERROR( INDEX('Project Assignment Check'!$G$1:$ZX$1, MATCH( LARGE( INDEX('ADR Tracking'!$G:$ZX, MATCH($A75, 'ADR Tracking'!$A:$A, 0), ), COLUMN()-4 ), INDEX('ADR Tracking'!$G:$ZX, MATCH($A75, 'ADR Tracking'!$A:$A, 0), ), 0 ) ), "" )
A76: SRP8-167 | B76: Front Structure | C76: Chassis & Bodywork | E76: =IFERROR( INDEX('Project Assignment Check'!$G$1:$ZX$1, MATCH( LARGE( INDEX('ADR Tracking'!$G:$ZX, MATCH($A76, 'ADR Tracking'!$A:$A, 0), ), COLUMN()-4 ), INDEX('ADR Tracking'!$G:$ZX, MATCH($A76, 'ADR Tracking'!$A:$A, 0), ), 0 ) ), "" ) -> ADR-92 | F76: =IFERROR( INDEX('Project Assignment Check'!$G$1:$ZX$1, MATCH( LARGE( INDEX('ADR Tracking'!$G:$ZX, MATCH($A76, 'ADR Tracking'!$A:$A, 0), ), COLUMN()-4 ), INDEX('ADR Tracking'!$G:$ZX, MATCH($A76, 'ADR Tracking'!$A:$A, 0), ), 0 ) ), "" ) -> ADR-43 | G76: =IFERROR( INDEX('Project Assignment Check'!$G$1:$ZX$1, MATCH( LARGE( INDEX('ADR Tracking'!$G:$ZX, MATCH($A76, 'ADR Tracking'!$A:$A, 0), ), COLUMN()-4 ), INDEX('ADR Tracking'!$G:$ZX, MATCH($A76, 'ADR Tracking'!$A:$A, 0), ), 0 ) ), "" ) | H76: =IFERROR( INDEX('Project Assignment Check'!$G$1:$ZX$1, MATCH( LARGE( INDEX('ADR Tracking'!$G:$ZX, MATCH($A76, 'ADR Tracking'!$A:$A, 0), ), COLUMN()-4 ), INDEX('ADR Tracking'!$G:$ZX, MATCH($A76, 'ADR Tracking'!$A:$A, 0), ), 0 ) ), "" ) | I76: =IFERROR( INDEX('Project Assignment Check'!$G$1:$ZX$1, MATCH( LARGE( INDEX('ADR Tracking'!$G:$ZX, MATCH($A76, 'ADR Tracking'!$A:$A, 0), ), COLUMN()-4 ), INDEX('ADR Tracking'!$G:$ZX, MATCH($A76, 'ADR Tracking'!$A:$A, 0), ), 0 ) ), "" ) | J76: =IFERROR( INDEX('Project Assignment Check'!$G$1:$ZX$1, MATCH( LARGE( INDEX('ADR Tracking'!$G:$ZX, MATCH($A76, 'ADR Tracking'!$A:$A, 0), ), COLUMN()-4 ), INDEX('ADR Tracking'!$G:$ZX, MATCH($A76, 'ADR Tracking'!$A:$A, 0), ), 0 ) ), "" )
A77: SRP8-170 | B77: Rear Quarters | C77: Chassis & Bodywork | E77: =IFERROR( INDEX('Project Assignment Check'!$G$1:$ZX$1, MATCH( LARGE( INDEX('ADR Tracking'!$G:$ZX, MATCH($A77, 'ADR Tracking'!$A:$A, 0), ), COLUMN()-4 ), INDEX('ADR Tracking'!$G:$ZX, MATCH($A77, 'ADR Tracking'!$A:$A, 0), ), 0 ) ), "" ) -> ADR-92 | F77: =IFERROR( INDEX('Project Assignment Check'!$G$1:$ZX$1, MATCH( LARGE( INDEX('ADR Tracking'!$G:$ZX, MATCH($A77, 'ADR Tracking'!$A:$A, 0), ), COLUMN()-4 ), INDEX('ADR Tracking'!$G:$ZX, MATCH($A77, 'ADR Tracking'!$A:$A, 0), ), 0 ) ), "" ) -> ADR-43 | G77: =IFERROR( INDEX('Project Assignment Check'!$G$1:$ZX$1, MATCH( LARGE( INDEX('ADR Tracking'!$G:$ZX, MATCH($A77, 'ADR Tracking'!$A:$A, 0), ), COLUMN()-4 ), INDEX('ADR Tracking'!$G:$ZX, MATCH($A77, 'ADR Tracking'!$A:$A, 0), ), 0 ) ), "" ) | H77: =IFERROR( INDEX('Project Assignment Check'!$G$1:$ZX$1, MATCH( LARGE( INDEX('ADR Tracking'!$G:$ZX, MATCH($A77, 'ADR Tracking'!$A:$A, 0), ), COLUMN()-4 ), INDEX('ADR Tracking'!$G:$ZX, MATCH($A77, 'ADR Tracking'!$A:$A, 0), ), 0 ) ), "" ) | I77: =IFERROR( INDEX('Project Assignment Check'!$G$1:$ZX$1, MATCH( LARGE( INDEX('ADR Tracking'!$G:$ZX, MATCH($A77, 'ADR Tracking'!$A:$A, 0), ), COLUMN()-4 ), INDEX('ADR Tracking'!$G:$ZX, MATCH($A77, 'ADR Tracking'!$A:$A, 0), ), 0 ) ), "" ) | J77: =IFERROR( INDEX('Project Assignment Check'!$G$1:$ZX$1, MATCH( LARGE( INDEX('ADR Tracking'!$G:$ZX, MATCH($A77, 'ADR Tracking'!$A:$A, 0), ), COLUMN()-4 ), INDEX('ADR Tracking'!$G:$ZX, MATCH($A77, 'ADR Tracking'!$A:$A, 0), ), 0 ) ), "" )
A78: SRP8-171 | B78: Rear Bumper | C78: Chassis & Bodywork | E78: =IFERROR( INDEX('Project Assignment Check'!$G$1:$ZX$1, MATCH( LARGE( INDEX('ADR Tracking'!$G:$ZX, MATCH($A78, 'ADR Tracking'!$A:$A, 0), ), COLUMN()-4 ), INDEX('ADR Tracking'!$G:$ZX, MATCH($A78, 'ADR Tracking'!$A:$A, 0), ), 0 ) ), "" ) -> ADR-13 | F78: =IFERROR( INDEX('Project Assignment Check'!$G$1:$ZX$1, MATCH( LARGE( INDEX('ADR Tracking'!$G:$ZX, MATCH($A78, 'ADR Tracking'!$A:$A, 0), ), COLUMN()-4 ), INDEX('ADR Tracking'!$G:$ZX, MATCH($A78, 'ADR Tracking'!$A:$A, 0), ), 0 ) ), "" ) -> ADR-47 | G78: =IFERROR( INDEX('Project Assignment Check'!$G$1:$ZX$1, MATCH( LARGE( INDEX('ADR Tracking'!$G:$ZX, MATCH($A78, 'ADR Tracking'!$A:$A, 0), ), COLUMN()-4 ), INDEX('ADR Tracking'!$G:$ZX, MATCH($A78, 'ADR Tracking'!$A:$A, 0), ), 0 ) ), "" ) -> ADR-43 | H78: =IFERROR( INDEX('Project Assignment Check'!$G$1:$ZX$1, MATCH( LARGE( INDEX('ADR Tracking'!$G:$ZX, MATCH($A78, 'ADR Tracking'!$A:$A, 0), ), COLUMN()-4 ), INDEX('ADR Tracking'!$G:$ZX, MATCH($A78, 'ADR Tracking'!$A:$A, 0), ), 0 ) ), "" ) -> ADR-43 | I78: =IFERROR( INDEX('Project Assignment Check'!$G$1:$ZX$1, MATCH( LARGE( INDEX('ADR Tracking'!$G:$ZX, MATCH($A78, 'ADR Tracking'!$A:$A, 0), ), COLUMN()-4 ), INDEX('ADR Tracking'!$G:$ZX, MATCH($A78, 'ADR Tracking'!$A:$A, 0), ), 0 ) ), "" ) | J78: =IFERROR( INDEX('Project Assignment Check'!$G$1:$ZX$1, MATCH( LARGE( INDEX('ADR Tracking'!$G:$ZX, MATCH($A78, 'ADR Tracking'!$A:$A, 0), ), COLUMN()-4 ), INDEX('ADR Tracking'!$G:$ZX, MATCH($A78, 'ADR Tracking'!$A:$A, 0), ), 0 ) ), "" )
A79: SRP8-172 | B79: Rear Support Structure | C79: Chassis & Bodywork | E79: =IFERROR( INDEX('Project Assignment Check'!$G$1:$ZX$1, MATCH( LARGE( INDEX('ADR Tracking'!$G:$ZX, MATCH($A79, 'ADR Tracking'!$A:$A, 0), ), COLUMN()-4 ), INDEX('ADR Tracking'!$G:$ZX, MATCH($A79, 'ADR Tracking'!$A:$A, 0), ), 0 ) ), "" ) -> ADR-61 | F79: =IFERROR( INDEX('Project Assignment Check'!$G$1:$ZX$1, MATCH( LARGE( INDEX('ADR Tracking'!$G:$ZX, MATCH($A79, 'ADR Tracking'!$A:$A, 0), ), COLUMN()-4 ), INDEX('ADR Tracking'!$G:$ZX, MATCH($A79, 'ADR Tracking'!$A:$A, 0), ), 0 ) ), "" ) -> ADR-92 | G79: =IFERROR( INDEX('Project Assignment Check'!$G$1:$ZX$1, MATCH( LARGE( INDEX('ADR Tracking'!$G:$ZX, MATCH($A79, 'ADR Tracking'!$A:$A, 0), ), COLUMN()-4 ), INDEX('ADR Tracking'!$G:$ZX, MATCH($A79, 'ADR Tracking'!$A:$A, 0), ), 0 ) ), "" ) | H79: =IFERROR( INDEX('Project Assignment Check'!$G$1:$ZX$1, MATCH( LARGE( INDEX('ADR Tracking'!$G:$ZX, MATCH($A79, 'ADR Tracking'!$A:$A, 0), ), COLUMN()-4 ), INDEX('ADR Tracking'!$G:$ZX, MATCH($A79, 'ADR Tracking'!$A:$A, 0), ), 0 ) ), "" ) | I79: =IFERROR( INDEX('Project Assignment Check'!$G$1:$ZX$1, MATCH( LARGE( INDEX('ADR Tracking'!$G:$ZX, MATCH($A79, 'ADR Tracking'!$A:$A, 0), ), COLUMN()-4 ), INDEX('ADR Tracking'!$G:$ZX, MATCH($A79, 'ADR Tracking'!$A:$A, 0), ), 0 ) ), "" ) | J79: =IFERROR( INDEX('Project Assignment Check'!$G$1:$ZX$1, MATCH( LARGE( INDEX('ADR Tracking'!$G:$ZX, MATCH($A79, 'ADR Tracking'!$A:$A, 0), ), COLUMN()-4 ), INDEX('ADR Tracking'!$G:$ZX, MATCH($A79, 'ADR Tracking'!$A:$A, 0), ), 0 ) ), "" )
A80: SRP8-173 | B80: Underbody | C80: Chassis & Bodywork | E80: =IFERROR( INDEX('Project Assignment Check'!$G$1:$ZX$1, MATCH( LARGE( INDEX('ADR Tracking'!$G:$ZX, MATCH($A80, 'ADR Tracking'!$A:$A, 0), ), COLUMN()-4 ), INDEX('ADR Tracking'!$G:$ZX, MATCH($A80, 'ADR Tracking'!$A:$A, 0), ), 0 ) ), "" ) -> ADR-43 | F80: =IFERROR( INDEX('Project Assignment Check'!$G$1:$ZX$1, MATCH( LARGE( INDEX('ADR Tracking'!$G:$ZX, MATCH($A80, 'ADR Tracking'!$A:$A, 0), ), COLUMN()-4 ), INDEX('ADR Tracking'!$G:$ZX, MATCH($A80, 'ADR Tracking'!$A:$A, 0), ), 0 ) ), "" ) -> ADR-92 | G80: =IFERROR( INDEX('Project Assignment Check'!$G$1:$ZX$1, MATCH( LARGE( INDEX('ADR Tracking'!$G:$ZX, MATCH($A80, 'ADR Tracking'!$A:$A, 0), ), COLUMN()-4 ), INDEX('ADR Tracking'!$G:$ZX, MATCH($A80, 'ADR Tracking'!$A:$A, 0), ), 0 ) ), "" ) | H80: =IFERROR( INDEX('Project Assignment Check'!$G$1:$ZX$1, MATCH( LARGE( INDEX('ADR Tracking'!$G:$ZX, MATCH($A80, 'ADR Tracking'!$A:$A, 0), ), COLUMN()-4 ), INDEX('ADR Tracking'!$G:$ZX, MATCH($A80, 'ADR Tracking'!$A:$A, 0), ), 0 ) ), "" ) | I80: =IFERROR( INDEX('Project Assignment Check'!$G$1:$ZX$1, MATCH( LARGE( INDEX('ADR Tracking'!$G:$ZX, MATCH($A80, 'ADR Tracking'!$A:$A, 0), ), COLUMN()-4 ), INDEX('ADR Tracking'!$G:$ZX, MATCH($A80, 'ADR Tracking'!$A:$A, 0), ), 0 ) ), "" ) | J80: =IFERROR( INDEX('Project Assignment Check'!$G$1:$ZX$1, MATCH( LARGE( INDEX('ADR Tracking'!$G:$ZX, MATCH($A80, 'ADR Tracking'!$A:$A, 0), ), COLUMN()-4 ), INDEX('ADR Tracking'!$G:$ZX, MATCH($A80, 'ADR Tracking'!$A:$A, 0), ), 0 ) ), "" )
A81: SRP8-174 | B81: Communications Project (ANTENNAS) | C81: Embedded Systems | E81: =IFERROR( INDEX('Project Assignment Check'!$G$1:$ZX$1, MATCH( LARGE( INDEX('ADR Tracking'!$G:$ZX, MATCH($A81, 'ADR Tracking'!$A:$A, 0), ), COLUMN()-4 ), INDEX('ADR Tracking'!$G:$ZX, MATCH($A81, 'ADR Tracking'!$A:$A, 0), ), 0 ) ), "" ) -> ADR-92 | F81: =IFERROR( INDEX('Project Assignment Check'!$G$1:$ZX$1, MATCH( LARGE( INDEX('ADR Tracking'!$G:$ZX, MATCH($A81, 'ADR Tracking'!$A:$A, 0), ), COLUMN()-4 ), INDEX('ADR Tracking'!$G:$ZX, MATCH($A81, 'ADR Tracking'!$A:$A, 0), ), 0 ) ), "" ) | G81: =IFERROR( INDEX('Project Assignment Check'!$G$1:$ZX$1, MATCH( LARGE( INDEX('ADR Tracking'!$G:$ZX, MATCH($A81, 'ADR Tracking'!$A:$A, 0), ), COLUMN()-4 ), INDEX('ADR Tracking'!$G:$ZX, MATCH($A81, 'ADR Tracking'!$A:$A, 0), ), 0 ) ), "" ) | H81: =IFERROR( INDEX('Project Assignment Check'!$G$1:$ZX$1, MATCH( LARGE( INDEX('ADR Tracking'!$G:$ZX, MATCH($A81, 'ADR Tracking'!$A:$A, 0), ), COLUMN()-4 ), INDEX('ADR Tracking'!$G:$ZX, MATCH($A81, 'ADR Tracking'!$A:$A, 0), ), 0 ) ), "" ) | I81: =IFERROR( INDEX('Project Assignment Check'!$G$1:$ZX$1, MATCH( LARGE( INDEX('ADR Tracking'!$G:$ZX, MATCH($A81, 'ADR Tracking'!$A:$A, 0), ), COLUMN()-4 ), INDEX('ADR Tracking'!$G:$ZX, MATCH($A81, 'ADR Tracking'!$A:$A, 0), ), 0 ) ), "" ) | J81: =IFERROR( INDEX('Project Assignment Check'!$G$1:$ZX$1, MATCH( LARGE( INDEX('ADR Tracking'!$G:$ZX, MATCH($A81, 'ADR Tracking'!$A:$A, 0), ), COLUMN()-4 ), INDEX('ADR Tracking'!$G:$ZX, MATCH($A81, 'ADR Tracking'!$A:$A, 0), ), 0 ) ), "" )
A82: SRP8-175 | B82: Vehicle States Project | C82: Embedded Systems | E82: =IFERROR( INDEX('Project Assignment Check'!$G$1:$ZX$1, MATCH( LARGE( INDEX('ADR Tracking'!$G:$ZX, MATCH($A82, 'ADR Tracking'!$A:$A, 0), ), COLUMN()-4 ), INDEX('ADR Tracking'!$G:$ZX, MATCH($A82, 'ADR Tracking'!$A:$A, 0), ), 0 ) ), "" ) -> ADR-42 | F82: =IFERROR( INDEX('Project Assignment Check'!$G$1:$ZX$1, MATCH( LARGE( INDEX('ADR Tracking'!$G:$ZX, MATCH($A82, 'ADR Tracking'!$A:$A, 0), ), COLUMN()-4 ), INDEX('ADR Tracking'!$G:$ZX, MATCH($A82, 'ADR Tracking'!$A:$A, 0), ), 0 ) ), "" ) -> ADR-14 | G82: =IFERROR( INDEX('Project Assignment Check'!$G$1:$ZX$1, MATCH( LARGE( INDEX('ADR Tracking'!$G:$ZX, MATCH($A82, 'ADR Tracking'!$A:$A, 0), ), COLUMN()-4 ), INDEX('ADR Tracking'!$G:$ZX, MATCH($A82, 'ADR Tracking'!$A:$A, 0), ), 0 ) ), "" ) -> ADR-14 | H82: =IFERROR( INDEX('Project Assignment Check'!$G$1:$ZX$1, MATCH( LARGE( INDEX('ADR Tracking'!$G:$ZX, MATCH($A82, 'ADR Tracking'!$A:$A, 0), ), COLUMN()-4 ), INDEX('ADR Tracking'!$G:$ZX, MATCH($A82, 'ADR Tracking'!$A:$A, 0), ), 0 ) ), "" ) -> ADR-14 | I82: =IFERROR( INDEX('Project Assignment Check'!$G$1:$ZX$1, MATCH( LARGE( INDEX('ADR Tracking'!$G:$ZX, MATCH($A82, 'ADR Tracking'!$A:$A, 0), ), COLUMN()-4 ), INDEX('ADR Tracking'!$G:$ZX, MATCH($A82, 'ADR Tracking'!$A:$A, 0), ), 0 ) ), "" ) -> ADR-90 | J82: =IFERROR( INDEX('Project Assignment Check'!$G$1:$ZX$1, MATCH( LARGE( INDEX('ADR Tracking'!$G:$ZX, MATCH($A82, 'ADR Tracking'!$A:$A, 0), ), COLUMN()-4 ), INDEX('ADR Tracking'!$G:$ZX, MATCH($A82, 'ADR Tracking'!$A:$A, 0), ), 0 ) ), "" ) -> ADR-90
A83: SRP8-176 | B83: Rear Crash Structures | C83: Chassis & Bodywork | E83: =IFERROR( INDEX('Project Assignment Check'!$G$1:$ZX$1, MATCH( LARGE( INDEX('ADR Tracking'!$G:$ZX, MATCH($A83, 'ADR Tracking'!$A:$A, 0), ), COLUMN()-4 ), INDEX('ADR Tracking'!$G:$ZX, MATCH($A83, 'ADR Tracking'!$A:$A, 0), ), 0 ) ), "" ) | F83: =IFERROR( INDEX('Project Assignment Check'!$G$1:$ZX$1, MATCH( LARGE( INDEX('ADR Tracking'!$G:$ZX, MATCH($A83, 'ADR Tracking'!$A:$A, 0), ), COLUMN()-4 ), INDEX('ADR Tracking'!$G:$ZX, MATCH($A83, 'ADR Tracking'!$A:$A, 0), ), 0 ) ), "" ) | G83: =IFERROR( INDEX('Project Assignment Check'!$G$1:$ZX$1, MATCH( LARGE( INDEX('ADR Tracking'!$G:$ZX, MATCH($A83, 'ADR Tracking'!$A:$A, 0), ), COLUMN()-4 ), INDEX('ADR Tracking'!$G:$ZX, MATCH($A83, 'ADR Tracking'!$A:$A, 0), ), 0 ) ), "" ) | H83: =IFERROR( INDEX('Project Assignment Check'!$G$1:$ZX$1, MATCH( LARGE( INDEX('ADR Tracking'!$G:$ZX, MATCH($A83, 'ADR Tracking'!$A:$A, 0), ), COLUMN()-4 ), INDEX('ADR Tracking'!$G:$ZX, MATCH($A83, 'ADR Tracking'!$A:$A, 0), ), 0 ) ), "" ) | I83: =IFERROR( INDEX('Project Assignment Check'!$G$1:$ZX$1, MATCH( LARGE( INDEX('ADR Tracking'!$G:$ZX, MATCH($A83, 'ADR Tracking'!$A:$A, 0), ), COLUMN()-4 ), INDEX('ADR Tracking'!$G:$ZX, MATCH($A83, 'ADR Tracking'!$A:$A, 0), ), 0 ) ), "" ) | J83: =IFERROR( INDEX('Project Assignment Check'!$G$1:$ZX$1, MATCH( LARGE( INDEX('ADR Tracking'!$G:$ZX, MATCH($A83, 'ADR Tracking'!$A:$A, 0), ), COLUMN()-4 ), INDEX('ADR Tracking'!$G:$ZX, MATCH($A83, 'ADR Tracking'!$A:$A, 0), ), 0 ) ), "" )
A84: SRP8-179 | B84: Hydrogen Airflow and Venting | C84: Alternative Energies | E84: =IFERROR( INDEX('Project Assignment Check'!$G$1:$ZX$1, MATCH( LARGE( INDEX('ADR Tracking'!$G:$ZX, MATCH($A84, 'ADR Tracking'!$A:$A, 0), ), COLUMN()-4 ), INDEX('ADR Tracking'!$G:$ZX, MATCH($A84, 'ADR Tracking'!$A:$A, 0), ), 0 ) ), "" ) | F84: =IFERROR( INDEX('Project Assignment Check'!$G$1:$ZX$1, MATCH( LARGE( INDEX('ADR Tracking'!$G:$ZX, MATCH($A84, 'ADR Tracking'!$A:$A, 0), ), COLUMN()-4 ), INDEX('ADR Tracking'!$G:$ZX, MATCH($A84, 'ADR Tracking'!$A:$A, 0), ), 0 ) ), "" ) | G84: =IFERROR( INDEX('Project Assignment Check'!$G$1:$ZX$1, MATCH( LARGE( INDEX('ADR Tracking'!$G:$ZX, MATCH($A84, 'ADR Tracking'!$A:$A, 0), ), COLUMN()-4 ), INDEX('ADR Tracking'!$G:$ZX, MATCH($A84, 'ADR Tracking'!$A:$A, 0), ), 0 ) ), "" ) | H84: =IFERROR( INDEX('Project Assignment Check'!$G$1:$ZX$1, MATCH( LARGE( INDEX('ADR Tracking'!$G:$ZX, MATCH($A84, 'ADR Tracking'!$A:$A, 0), ), COLUMN()-4 ), INDEX('ADR Tracking'!$G:$ZX, MATCH($A84, 'ADR Tracking'!$A:$A, 0), ), 0 ) ), "" ) | I84: =IFERROR( INDEX('Project Assignment Check'!$G$1:$ZX$1, MATCH( LARGE( INDEX('ADR Tracking'!$G:$ZX, MATCH($A84, 'ADR Tracking'!$A:$A, 0), ), COLUMN()-4 ), INDEX('ADR Tracking'!$G:$ZX, MATCH($A84, 'ADR Tracking'!$A:$A, 0), ), 0 ) ), "" ) | J84: =IFERROR( INDEX('Project Assignment Check'!$G$1:$ZX$1, MATCH( LARGE( INDEX('ADR Tracking'!$G:$ZX, MATCH($A84, 'ADR Tracking'!$A:$A, 0), ), COLUMN()-4 ), INDEX('ADR Tracking'!$G:$ZX, MATCH($A84, 'ADR Tracking'!$A:$A, 0), ), 0 ) ), "" )
A85: SRP8-182 | B85: Hydrogen Power Electronics System | C85: Energy Systems | E85: =IFERROR( INDEX('Project Assignment Check'!$G$1:$ZX$1, MATCH( LARGE( INDEX('ADR Tracking'!$G:$ZX, MATCH($A85, 'ADR Tracking'!$A:$A, 0), ), COLUMN()-4 ), INDEX('ADR Tracking'!$G:$ZX, MATCH($A85, 'ADR Tracking'!$A:$A, 0), ), 0 ) ), "" ) | F85: =IFERROR( INDEX('Project Assignment Check'!$G$1:$ZX$1, MATCH( LARGE( INDEX('ADR Tracking'!$G:$ZX, MATCH($A85, 'ADR Tracking'!$A:$A, 0), ), COLUMN()-4 ), INDEX('ADR Tracking'!$G:$ZX, MATCH($A85, 'ADR Tracking'!$A:$A, 0), ), 0 ) ), "" ) | G85: =IFERROR( INDEX('Project Assignment Check'!$G$1:$ZX$1, MATCH( LARGE( INDEX('ADR Tracking'!$G:$ZX, MATCH($A85, 'ADR Tracking'!$A:$A, 0), ), COLUMN()-4 ), INDEX('ADR Tracking'!$G:$ZX, MATCH($A85, 'ADR Tracking'!$A:$A, 0), ), 0 ) ), "" ) | H85: =IFERROR( INDEX('Project Assignment Check'!$G$1:$ZX$1, MATCH( LARGE( INDEX('ADR Tracking'!$G:$ZX, MATCH($A85, 'ADR Tracking'!$A:$A, 0), ), COLUMN()-4 ), INDEX('ADR Tracking'!$G:$ZX, MATCH($A85, 'ADR Tracking'!$A:$A, 0), ), 0 ) ), "" ) | I85: =IFERROR( INDEX('Project Assignment Check'!$G$1:$ZX$1, MATCH( LARGE( INDEX('ADR Tracking'!$G:$ZX, MATCH($A85, 'ADR Tracking'!$A:$A, 0), ), COLUMN()-4 ), INDEX('ADR Tracking'!$G:$ZX, MATCH($A85, 'ADR Tracking'!$A:$A, 0), ), 0 ) ), "" ) | J85: =IFERROR( INDEX('Project Assignment Check'!$G$1:$ZX$1, MATCH( LARGE( INDEX('ADR Tracking'!$G:$ZX, MATCH($A85, 'ADR Tracking'!$A:$A, 0), ), COLUMN()-4 ), INDEX('ADR Tracking'!$G:$ZX, MATCH($A85, 'ADR Tracking'!$A:$A, 0), ), 0 ) ), "" )
... A92: SRP8-192 | B92: Interior Floor Lining | C92: Interior | E92: =IFERROR( INDEX('Project Assignment Check'!$G$1:$ZX$1, MATCH( LARGE( INDEX('ADR Tracking'!$G:$ZX, MATCH($A92, 'ADR Tracking'!$A:$A, 0), ), COLUMN()-4 ), INDEX('ADR Tracking'!$G:$ZX, MATCH($A92, 'ADR Tracking'!$A:$A, 0), ), 0 ) ), "" ) | F92: =IFERROR( INDEX('Project Assignment Check'!$G$1:$ZX$1, MATCH( LARGE( INDEX('ADR Tracking'!$G:$ZX, MATCH($A92, 'ADR Tracking'!$A:$A, 0), ), COLUMN()-4 ), INDEX('ADR Tracking'!$G:$ZX, MATCH($A92, 'ADR Tracking'!$A:$A, 0), ), 0 ) ), "" ) | G92: =IFERROR( INDEX('Project Assignment Check'!$G$1:$ZX$1, MATCH( LARGE( INDEX('ADR Tracking'!$G:$ZX, MATCH($A92, 'ADR Tracking'!$A:$A, 0), ), COLUMN()-4 ), INDEX('ADR Tracking'!$G:$ZX, MATCH($A92, 'ADR Tracking'!$A:$A, 0), ), 0 ) ), "" ) | H92: =IFERROR( INDEX('Project Assignment Check'!$G$1:$ZX$1, MATCH( LARGE( INDEX('ADR Tracking'!$G:$ZX, MATCH($A92, 'ADR Tracking'!$A:$A, 0), ), COLUMN()-4 ), INDEX('ADR Tracking'!$G:$ZX, MATCH($A92, 'ADR Tracking'!$A:$A, 0), ), 0 ) ), "" ) | I92: =IFERROR( INDEX('Project Assignment Check'!$G$1:$ZX$1, MATCH( LARGE( INDEX('ADR Tracking'!$G:$ZX, MATCH($A92, 'ADR Tracking'!$A:$A, 0), ), COLUMN()-4 ), INDEX('ADR Tracking'!$G:$ZX, MATCH($A92, 'ADR Tracking'!$A:$A, 0), ), 0 ) ), "" ) | J92: =IFERROR( INDEX('Project Assignment Check'!$G$1:$ZX$1, MATCH( LARGE( INDEX('ADR Tracking'!$G:$ZX, MATCH($A92, 'ADR Tracking'!$A:$A, 0), ), COLUMN()-4 ), INDEX('ADR Tracking'!$G:$ZX, MATCH($A92, 'ADR Tracking'!$A:$A, 0), ), 0 ) ), "" )

Sheet MASTER (Assignment)
A1: Project ID | B1: Project Name | C1: Primary Department | D1: Secondary Department | E1: 1st ADR | F1: 2nd ADR | G1: 3rd ADR | H1: 4th ADR | I1: 5th ADR | J1: 6th ADR
A2: SRP8-001 | B2: Doors | C2: Chassis & Bodywork | E2: =IF(IFERROR( INDEX('Project Assignment Check'!$G$1:$ZX$1, MATCH( LARGE( INDEX('Project Assignment Check'!$G:$ZX, MATCH($A2, 'Project Assignment Check'!$A:$A, 0), ), COLUMN()-4 ), INDEX('Project Assignment Check'!$G:$ZX, MATCH($A2, 'Project Assignment Check'!$A:$A, 0), ), 0 ) ), "" ) = 0,"", IFERROR( INDEX('Project Assignment Check'!$G$1:$ZX$1, MATCH( LARGE( INDEX('Project Assignment Check'!$G:$ZX, MATCH($A2, 'Project Assignment Check'!$A:$A, 0), ), COLUMN()-4 ), INDEX('Project Assignment Check'!$G:$ZX, MATCH($A2, 'Project Assignment Check'!$A:$A, 0), ), 0 ) ), "" )) -> ADR-02 | F2: =IF(IFERROR( INDEX('Project Assignment Check'!$G$1:$ZX$1, MATCH( LARGE( INDEX('Project Assignment Check'!$G:$ZX, MATCH($A2, 'Project Assignment Check'!$A:$A, 0), ), COLUMN()-4 ), INDEX('Project Assignment Check'!$G:$ZX, MATCH($A2, 'Project Assignment Check'!$A:$A, 0), ), 0 ) ), "" ) = 0,"", IFERROR( INDEX('Project Assignment Check'!$G$1:$ZX$1, MATCH( LARGE( INDEX('Project Assignment Check'!$G:$ZX, MATCH($A2, 'Project Assignment Check'!$A:$A, 0), ), COLUMN()-4 ), INDEX('Project Assignment Check'!$G:$ZX, MATCH($A2, 'Project Assignment Check'!$A:$A, 0), ), 0 ) ), "" )) -> ADR-02 | G2: =IF(IFERROR( INDEX('Project Assignment Check'!$G$1:$ZX$1, MATCH( LARGE( INDEX('Project Assignment Check'!$G:$ZX, MATCH($A2, 'Project Assignment Check'!$A:$A, 0), ), COLUMN()-4 ), INDEX('Project Assignment Check'!$G:$ZX, MATCH($A2, 'Project Assignment Check'!$A:$A, 0), ), 0 ) ), "" ) = 0,"", IFERROR( INDEX('Project Assignment Check'!$G$1:$ZX$1, MATCH( LARGE( INDEX('Project Assignment Check'!$G:$ZX, MATCH($A2, 'Project Assignment Check'!$A:$A, 0), ), COLUMN()-4 ), INDEX('Project Assignment Check'!$G:$ZX, MATCH($A2, 'Project Assignment Check'!$A:$A, 0), ), 0 ) ), "" )) -> ADR-02 | H2: =IF(IFERROR( INDEX('Project Assignment Check'!$G$1:$ZX$1, MATCH( LARGE( INDEX('Project Assignment Check'!$G:$ZX, MATCH($A2, 'Project Assignment Check'!$A:$A, 0), ), COLUMN()-4 ), INDEX('Project Assignment Check'!$G:$ZX, MATCH($A2, 'Project Assignment Check'!$A:$A, 0), ), 0 ) ), "" ) = 0,"", IFERROR( INDEX('Project Assignment Check'!$G$1:$ZX$1, MATCH( LARGE( INDEX('Project Assignment Check'!$G:$ZX, MATCH($A2, 'Project Assignment Check'!$A:$A, 0), ), COLUMN()-4 ), INDEX('Project Assignment Check'!$G:$ZX, MATCH($A2, 'Project Assignment Check'!$A:$A, 0), ), 0 ) ), "" )) -> ADR-02 | I2: =IFERROR( INDEX('Project Assignment Check'!$G$1:$ZX$1, MATCH( LARGE( INDEX('Project Assignment Check'!$G:$ZX, MATCH($A2, 'Project Assignment Check'!$A:$A, 0), ), COLUMN()-4 ), INDEX('Project Assignment Check'!$G:$ZX, MATCH($A2, 'Project Assignment Check'!$A:$A, 0), ), 0 ) ), "" ) | J2: =IFERROR( INDEX('Project Assignment Check'!$G$1:$ZX$1, MATCH( LARGE( INDEX('Project Assignment Check'!$G:$ZX, MATCH($A2, 'Project Assignment Check'!$A:$A, 0), ), COLUMN()-4 ), INDEX('Project Assignment Check'!$G:$ZX, MATCH($A2, 'Project Assignment Check'!$A:$A, 0), ), 0 ) ), "" )
A3: SRP8-002 | B3: Door Handles | C3: Chassis & Bodywork | E3: =IF(IFERROR( INDEX('Project Assignment Check'!$G$1:$ZX$1, MATCH( LARGE( INDEX('Project Assignment Check'!$G:$ZX, MATCH($A3, 'Project Assignment Check'!$A:$A, 0), ), COLUMN()-4 ), INDEX('Project Assignment Check'!$G:$ZX, MATCH($A3, 'Project Assignment Check'!$A:$A, 0), ), 0 ) ), "" ) = 0,"", IFERROR( INDEX('Project Assignment Check'!$G$1:$ZX$1, MATCH( LARGE( INDEX('Project Assignment Check'!$G:$ZX, MATCH($A3, 'Project Assignment Check'!$A:$A, 0), ), COLUMN()-4 ), INDEX('Project Assignment Check'!$G:$ZX, MATCH($A3, 'Project Assignment Check'!$A:$A, 0), ), 0 ) ), "" )) -> ADR-92 | F3: =IFERROR( INDEX('Project Assignment Check'!$G$1:$ZX$1, MATCH( LARGE( INDEX('Project Assignment Check'!$G:$ZX, MATCH($A3, 'Project Assignment Check'!$A:$A, 0), ), COLUMN()-4 ), INDEX('Project Assignment Check'!$G:$ZX, MATCH($A3, 'Project Assignment Check'!$A:$A, 0), ), 0 ) ), "" ) | G3: =IFERROR( INDEX('Project Assignment Check'!$G$1:$ZX$1, MATCH( LARGE( INDEX('Project Assignment Check'!$G:$ZX, MATCH($A3, 'Project Assignment Check'!$A:$A, 0), ), COLUMN()-4 ), INDEX('Project Assignment Check'!$G:$ZX, MATCH($A3, 'Project Assignment Check'!$A:$A, 0), ), 0 ) ), "" ) | H3: =IFERROR( INDEX('Project Assignment Check'!$G$1:$ZX$1, MATCH( LARGE( INDEX('Project Assignment Check'!$G:$ZX, MATCH($A3, 'Project Assignment Check'!$A:$A, 0), ), COLUMN()-4 ), INDEX('Project Assignment Check'!$G:$ZX, MATCH($A3, 'Project Assignment Check'!$A:$A, 0), ), 0 ) ), "" ) | I3: =IFERROR( INDEX('Project Assignment Check'!$G$1:$ZX$1, MATCH( LARGE( INDEX('Project Assignment Check'!$G:$ZX, MATCH($A3, 'Project Assignment Check'!$A:$A, 0), ), COLUMN()-4 ), INDEX('Project Assignment Check'!$G:$ZX, MATCH($A3, 'Project Assignment Check'!$A:$A, 0), ), 0 ) ), "" ) | J3: =IFERROR( INDEX('Project Assignment Check'!$G$1:$ZX$1, MATCH( LARGE( INDEX('Project Assignment Check'!$G:$ZX, MATCH($A3, 'Project Assignment Check'!$A:$A, 0), ), COLUMN()-4 ), INDEX('Project Assignment Check'!$G:$ZX, MATCH($A3, 'Project Assignment Check'!$A:$A, 0), ), 0 ) ), "" )
A4: SRP8-003 | B4: Windscreen | C4: Chassis & Bodywork | E4: =IF(IFERROR( INDEX('Project Assignment Check'!$G$1:$ZX$1, MATCH( LARGE( INDEX('Project Assignment Check'!$G:$ZX, MATCH($A4, 'Project Assignment Check'!$A:$A, 0), ), COLUMN()-4 ), INDEX('Project Assignment Check'!$G:$ZX, MATCH($A4, 'Project Assignment Check'!$A:$A, 0), ), 0 ) ), "" ) = 0,"", IFERROR( INDEX('Project Assignment Check'!$G$1:$ZX$1, MATCH( LARGE( INDEX('Project Assignment Check'!$G:$ZX, MATCH($A4, 'Project Assignment Check'!$A:$A, 0), ), COLUMN()-4 ), INDEX('Project Assignment Check'!$G:$ZX, MATCH($A4, 'Project Assignment Check'!$A:$A, 0), ), 0 ) ), "" )) -> ADR-93 | F4: =IFERROR( INDEX('Project Assignment Check'!$G$1:$ZX$1, MATCH( LARGE( INDEX('Project Assignment Check'!$G:$ZX, MATCH($A4, 'Project Assignment Check'!$A:$A, 0), ), COLUMN()-4 ), INDEX('Project Assignment Check'!$G:$ZX, MATCH($A4, 'Project Assignment Check'!$A:$A, 0), ), 0 ) ), "" ) -> ADR-08 | G4: =IFERROR( INDEX('Project Assignment Check'!$G$1:$ZX$1, MATCH( LARGE( INDEX('Project Assignment Check'!$G:$ZX, MATCH($A4, 'Project Assignment Check'!$A:$A, 0), ), COLUMN()-4 ), INDEX('Project Assignment Check'!$G:$ZX, MATCH($A4, 'Project Assignment Check'!$A:$A, 0), ), 0 ) ), "" ) -> ADR-92 | H4: =IFERROR( INDEX('Project Assignment Check'!$G$1:$ZX$1, MATCH( LARGE( INDEX('Project Assignment Check'!$G:$ZX, MATCH($A4, 'Project Assignment Check'!$A:$A, 0), ), COLUMN()-4 ), INDEX('Project Assignment Check'!$G:$ZX, MATCH($A4, 'Project Assignment Check'!$A:$A, 0), ), 0 ) ), "" ) | I4: =IFERROR( INDEX('Project Assignment Check'!$G$1:$ZX$1, MATCH( LARGE( INDEX('Project Assignment Check'!$G:$ZX, MATCH($A4, 'Project Assignment Check'!$A:$A, 0), ), COLUMN()-4 ), INDEX('Project Assignment Check'!$G:$ZX, MATCH($A4, 'Project Assignment Check'!$A:$A, 0), ), 0 ) ), "" ) | J4: =IFERROR( INDEX('Project Assignment Check'!$G$1:$ZX$1, MATCH( LARGE( INDEX('Project Assignment Check'!$G:$ZX, MATCH($A4, 'Project Assignment Check'!$A:$A, 0), ), COLUMN()-4 ), INDEX('Project Assignment Check'!$G:$ZX, MATCH($A4, 'Project Assignment Check'!$A:$A, 0), ), 0 ) ), "" )
A5: SRP8-004 | B5: Boot | C5: Chassis & Bodywork | E5: =IF(IFERROR( INDEX('Project Assignment Check'!$G$1:$ZX$1, MATCH( LARGE( INDEX('Project Assignment Check'!$G:$ZX, MATCH($A5, 'Project Assignment Check'!$A:$A, 0), ), COLUMN()-4 ), INDEX('Project Assignment Check'!$G:$ZX, MATCH($A5, 'Project Assignment Check'!$A:$A, 0), ), 0 ) ), "" ) = 0,"", IFERROR( INDEX('Project Assignment Check'!$G$1:$ZX$1, MATCH( LARGE( INDEX('Project Assignment Check'!$G:$ZX, MATCH($A5, 'Project Assignment Check'!$A:$A, 0), ), COLUMN()-4 ), INDEX('Project Assignment Check'!$G:$ZX, MATCH($A5, 'Project Assignment Check'!$A:$A, 0), ), 0 ) ), "" )) -> ADR-43 | F5: =IFERROR( INDEX('Project Assignment Check'!$G$1:$ZX$1, MATCH( LARGE( INDEX('Project Assignment Check'!$G:$ZX, MATCH($A5, 'Project Assignment Check'!$A:$A, 0), ), COLUMN()-4 ), INDEX('Project Assignment Check'!$G:$ZX, MATCH($A5, 'Project Assignment Check'!$A:$A, 0), ), 0 ) ), "" ) -> ADR-92 | G5: =IFERROR( INDEX('Project Assignment Check'!$G$1:$ZX$1, MATCH( LARGE( INDEX('Project Assignment Check'!$G:$ZX, MATCH($A5, 'Project Assignment Check'!$A:$A, 0), ), COLUMN()-4 ), INDEX('Project Assignment Check'!$G:$ZX, MATCH($A5, 'Project Assignment Check'!$A:$A, 0), ), 0 ) ), "" ) | H5: =IFERROR( INDEX('Project Assignment Check'!$G$1:$ZX$1, MATCH( LARGE( INDEX('Project Assignment Check'!$G:$ZX, MATCH($A5, 'Project Assignment Check'!$A:$A, 0), ), COLUMN()-4 ), INDEX('Project Assignment Check'!$G:$ZX, MATCH($A5, 'Project Assignment Check'!$A:$A, 0), ), 0 ) ), "" ) | I5: =IFERROR( INDEX('Project Assignment Check'!$G$1:$ZX$1, MATCH( LARGE( INDEX('Project Assignment Check'!$G:$ZX, MATCH($A5, 'Project Assignment Check'!$A:$A, 0), ), COLUMN()-4 ), INDEX('Project Assignment Check'!$G:$ZX, MATCH($A5, 'Project Assignment Check'!$A:$A, 0), ), 0 ) ), "" ) | J5: =IFERROR( INDEX('Project Assignment Check'!$G$1:$ZX$1, MATCH( LARGE( INDEX('Project Assignment Check'!$G:$ZX, MATCH($A5, 'Project Assignment Check'!$A:$A, 0), ), COLUMN()-4 ), INDEX('Project Assignment Check'!$G:$ZX, MATCH($A5, 'Project Assignment Check'!$A:$A, 0), ), 0 ) ), "" )
A6: SRP8-005 | B6: Bonnet | C6: Chassis & Bodywork | E6: =IF(IFERROR( INDEX('Project Assignment Check'!$G$1:$ZX$1, MATCH( LARGE( INDEX('Project Assignment Check'!$G:$ZX, MATCH($A6, 'Project Assignment Check'!$A:$A, 0), ), COLUMN()-4 ), INDEX('Project Assignment Check'!$G:$ZX, MATCH($A6, 'Project Assignment Check'!$A:$A, 0), ), 0 ) ), "" ) = 0,"", IFERROR( INDEX('Project Assignment Check'!$G$1:$ZX$1, MATCH( LARGE( INDEX('Project Assignment Check'!$G:$ZX, MATCH($A6, 'Project Assignment Check'!$A:$A, 0), ), COLUMN()-4 ), INDEX('Project Assignment Check'!$G:$ZX, MATCH($A6, 'Project Assignment Check'!$A:$A, 0), ), 0 ) ), "" )) -> ADR-42 | F6: =IFERROR( INDEX('Project Assignment Check'!$G$1:$ZX$1, MATCH( LARGE( INDEX('Project Assignment Check'!$G:$ZX, MATCH($A6, 'Project Assignment Check'!$A:$A, 0), ), COLUMN()-4 ), INDEX('Project Assignment Check'!$G:$ZX, MATCH($A6, 'Project Assignment Check'!$A:$A, 0), ), 0 ) ), "" ) -> ADR-42 | G6: =IFERROR( INDEX('Project Assignment Check'!$G$1:$ZX$1, MATCH( LARGE( INDEX('Project Assignment Check'!$G:$ZX, MATCH($A6, 'Project Assignment Check'!$A:$A, 0), ), COLUMN()-4 ), INDEX('Project Assignment Check'!$G:$ZX, MATCH($A6, 'Project Assignment Check'!$A:$A, 0), ), 0 ) ), "" ) | H6: =IFERROR( INDEX('Project Assignment Check'!$G$1:$ZX$1, MATCH( LARGE( INDEX('Project Assignment Check'!$G:$ZX, MATCH($A6, 'Project Assignment Check'!$A:$A, 0), ), COLUMN()-4 ), INDEX('Project Assignment Check'!$G:$ZX, MATCH($A6, 'Project Assignment Check'!$A:$A, 0), ), 0 ) ), "" ) | I6: =IFERROR( INDEX('Project Assignment Check'!$G$1:$ZX$1, MATCH( LARGE( INDEX('Project Assignment Check'!$G:$ZX, MATCH($A6, 'Project Assignment Check'!$A:$A, 0), ), COLUMN()-4 ), INDEX('Project Assignment Check'!$G:$ZX, MATCH($A6, 'Project Assignment Check'!$A:$A, 0), ), 0 ) ), "" ) | J6: =IFERROR( INDEX('Project Assignment Check'!$G$1:$ZX$1, MATCH( LARGE( INDEX('Project Assignment Check'!$G:$ZX, MATCH($A6, 'Project Assignment Check'!$A:$A, 0), ), COLUMN()-4 ), INDEX('Project Assignment Check'!$G:$ZX, MATCH($A6, 'Project Assignment Check'!$A:$A, 0), ), 0 ) ), "" )
A7: SRP8-006 | B7: Exterior Design | C7: Chassis & Bodywork | E7: =IF(IFERROR( INDEX('Project Assignment Check'!$G$1:$ZX$1, MATCH( LARGE( INDEX('Project Assignment Check'!$G:$ZX, MATCH($A7, 'Project Assignment Check'!$A:$A, 0), ), COLUMN()-4 ), INDEX('Project Assignment Check'!$G:$ZX, MATCH($A7, 'Project Assignment Check'!$A:$A, 0), ), 0 ) ), "" ) = 0,"", IFERROR( INDEX('Project Assignment Check'!$G$1:$ZX$1, MATCH( LARGE( INDEX('Project Assignment Check'!$G:$ZX, MATCH($A7, 'Project Assignment Check'!$A:$A, 0), ), COLUMN()-4 ), INDEX('Project Assignment Check'!$G:$ZX, MATCH($A7, 'Project Assignment Check'!$A:$A, 0), ), 0 ) ), "" )) | F7: =IFERROR( INDEX('Project Assignment Check'!$G$1:$ZX$1, MATCH( LARGE( INDEX('Project Assignment Check'!$G:$ZX, MATCH($A7, 'Project Assignment Check'!$A:$A, 0), ), COLUMN()-4 ), INDEX('Project Assignment Check'!$G:$ZX, MATCH($A7, 'Project Assignment Check'!$A:$A, 0), ), 0 ) ), "" ) | G7: =IFERROR( INDEX('Project Assignment Check'!$G$1:$ZX$1, MATCH( LARGE( INDEX('Project Assignment Check'!$G:$ZX, MATCH($A7, 'Project Assignment Check'!$A:$A, 0), ), COLUMN()-4 ), INDEX('Project Assignment Check'!$G:$ZX, MATCH($A7, 'Project Assignment Check'!$A:$A, 0), ), 0 ) ), "" ) | H7: =IFERROR( INDEX('Project Assignment Check'!$G$1:$ZX$1, MATCH( LARGE( INDEX('Project Assignment Check'!$G:$ZX, MATCH($A7, 'Project Assignment Check'!$A:$A, 0), ), COLUMN()-4 ), INDEX('Project Assignment Check'!$G:$ZX, MATCH($A7, 'Project Assignment Check'!$A:$A, 0), ), 0 ) ), "" ) | I7: =IFERROR( INDEX('Project Assignment Check'!$G$1:$ZX$1, MATCH( LARGE( INDEX('Project Assignment Check'!$G:$ZX, MATCH($A7, 'Project Assignment Check'!$A:$A, 0), ), COLUMN()-4 ), INDEX('Project Assignment Check'!$G:$ZX, MATCH($A7, 'Project Assignment Check'!$A:$A, 0), ), 0 ) ), "" ) | J7: =IFERROR( INDEX('Project Assignment Check'!$G$1:$ZX$1, MATCH( LARGE( INDEX('Project Assignment Check'!$G:$ZX, MATCH($A7, 'Project Assignment Check'!$A:$A, 0), ), COLUMN()-4 ), INDEX('Project Assignment Check'!$G:$ZX, MATCH($A7, 'Project Assignment Check'!$A:$A, 0), ), 0 ) ), "" )
A8: SRP8-007 | B8: Front Wheel Covers | E8: =IF(IFERROR( INDEX('Project Assignment Check'!$G$1:$ZX$1, MATCH( LARGE( INDEX('Project Assignment Check'!$G:$ZX, MATCH($A8, 'Project Assignment Check'!$A:$A, 0), ), COLUMN()-4 ), INDEX('Project Assignment Check'!$G:$ZX, MATCH($A8, 'Project Assignment Check'!$A:$A, 0), ), 0 ) ), "" ) = 0,"", IFERROR( INDEX('Project Assignment Check'!$G$1:$ZX$1, MATCH( LARGE( INDEX('Project Assignment Check'!$G:$ZX, MATCH($A8, 'Project Assignment Check'!$A:$A, 0), ), COLUMN()-4 ), INDEX('Project Assignment Check'!$G:$ZX, MATCH($A8, 'Project Assignment Check'!$A:$A, 0), ), 0 ) ), "" )) | F8: =IFERROR( INDEX('Project Assignment Check'!$G$1:$ZX$1, MATCH( LARGE( INDEX('Project Assignment Check'!$G:$ZX, MATCH($A8, 'Project Assignment Check'!$A:$A, 0), ), COLUMN()-4 ), INDEX('Project Assignment Check'!$G:$ZX, MATCH($A8, 'Project Assignment Check'!$A:$A, 0), ), 0 ) ), "" ) | G8: =IFERROR( INDEX('Project Assignment Check'!$G$1:$ZX$1, MATCH( LARGE( INDEX('Project Assignment Check'!$G:$ZX, MATCH($A8, 'Project Assignment Check'!$A:$A, 0), ), COLUMN()-4 ), INDEX('Project Assignment Check'!$G:$ZX, MATCH($A8, 'Project Assignment Check'!$A:$A, 0), ), 0 ) ), "" ) | H8: =IFERROR( INDEX('Project Assignment Check'!$G$1:$ZX$1, MATCH( LARGE( INDEX('Project Assignment Check'!$G:$ZX, MATCH($A8, 'Project Assignment Check'!$A:$A, 0), ), COLUMN()-4 ), INDEX('Project Assignment Check'!$G:$ZX, MATCH($A8, 'Project Assignment Check'!$A:$A, 0), ), 0 ) ), "" ) | I8: =IFERROR( INDEX('Project Assignment Check'!$G$1:$ZX$1, MATCH( LARGE( INDEX('Project Assignment Check'!$G:$ZX, MATCH($A8, 'Project Assignment Check'!$A:$A, 0), ), COLUMN()-4 ), INDEX('Project Assignment Check'!$G:$ZX, MATCH($A8, 'Project Assignment Check'!$A:$A, 0), ), 0 ) ), "" ) | J8: =IFERROR( INDEX('Project Assignment Check'!$G$1:$ZX$1, MATCH( LARGE( INDEX('Project Assignment Check'!$G:$ZX, MATCH($A8, 'Project Assignment Check'!$A:$A, 0), ), COLUMN()-4 ), INDEX('Project Assignment Check'!$G:$ZX, MATCH($A8, 'Project Assignment Check'!$A:$A, 0), ), 0 ) ), "" )
A9: SRP8-008 | B9: Rear Wheel Covers | E9: =IF(IFERROR( INDEX('Project Assignment Check'!$G$1:$ZX$1, MATCH( LARGE( INDEX('Project Assignment Check'!$G:$ZX, MATCH($A9, 'Project Assignment Check'!$A:$A, 0), ), COLUMN()-4 ), INDEX('Project Assignment Check'!$G:$ZX, MATCH($A9, 'Project Assignment Check'!$A:$A, 0), ), 0 ) ), "" ) = 0,"", IFERROR( INDEX('Project Assignment Check'!$G$1:$ZX$1, MATCH( LARGE( INDEX('Project Assignment Check'!$G:$ZX, MATCH($A9, 'Project Assignment Check'!$A:$A, 0), ), COLUMN()-4 ), INDEX('Project Assignment Check'!$G:$ZX, MATCH($A9, 'Project Assignment Check'!$A:$A, 0), ), 0 ) ), "" )) | F9: =IFERROR( INDEX('Project Assignment Check'!$G$1:$ZX$1, MATCH( LARGE( INDEX('Project Assignment Check'!$G:$ZX, MATCH($A9, 'Project Assignment Check'!$A:$A, 0), ), COLUMN()-4 ), INDEX('Project Assignment Check'!$G:$ZX, MATCH($A9, 'Project Assignment Check'!$A:$A, 0), ), 0 ) ), "" ) | G9: =IFERROR( INDEX('Project Assignment Check'!$G$1:$ZX$1, MATCH( LARGE( INDEX('Project Assignment Check'!$G:$ZX, MATCH($A9, 'Project Assignment Check'!$A:$A, 0), ), COLUMN()-4 ), INDEX('Project Assignment Check'!$G:$ZX, MATCH($A9, 'Project Assignment Check'!$A:$A, 0), ), 0 ) ), "" ) | H9: =IFERROR( INDEX('Project Assignment Check'!$G$1:$ZX$1, MATCH( LARGE( INDEX('Project Assignment Check'!$G:$ZX, MATCH($A9, 'Project Assignment Check'!$A:$A, 0), ), COLUMN()-4 ), INDEX('Project Assignment Check'!$G:$ZX, MATCH($A9, 'Project Assignment Check'!$A:$A, 0), ), 0 ) ), "" ) | I9: =IFERROR( INDEX('Project Assignment Check'!$G$1:$ZX$1, MATCH( LARGE( INDEX('Project Assignment Check'!$G:$ZX, MATCH($A9, 'Project Assignment Check'!$A:$A, 0), ), COLUMN()-4 ), INDEX('Project Assignment Check'!$G:$ZX, MATCH($A9, 'Project Assignment Check'!$A:$A, 0), ), 0 ) ), "" ) | J9: =IFERROR( INDEX('Project Assignment Check'!$G$1:$ZX$1, MATCH( LARGE( INDEX('Project Assignment Check'!$G:$ZX, MATCH($A9, 'Project Assignment Check'!$A:$A, 0), ), COLUMN()-4 ), INDEX('Project Assignment Check'!$G:$ZX, MATCH($A9, 'Project Assignment Check'!$A:$A, 0), ), 0 ) ), "" )
A10: SRP8-009 | B10: Chassis | E10: =IF(IFERROR( INDEX('Project Assignment Check'!$G$1:$ZX$1, MATCH( LARGE( INDEX('Project Assignment Check'!$G:$ZX, MATCH($A10, 'Project Assignment Check'!$A:$A, 0), ), COLUMN()-4 ), INDEX('Project Assignment Check'!$G:$ZX, MATCH($A10, 'Project Assignment Check'!$A:$A, 0), ), 0 ) ), "" ) = 0,"", IFERROR( INDEX('Project Assignment Check'!$G$1:$ZX$1, MATCH( LARGE( INDEX('Project Assignment Check'!$G:$ZX, MATCH($A10, 'Project Assignment Check'!$A:$A, 0), ), COLUMN()-4 ), INDEX('Project Assignment Check'!$G:$ZX, MATCH($A10, 'Project Assignment Check'!$A:$A, 0), ), 0 ) ), "" )) | F10: =IFERROR( INDEX('Project Assignment Check'!$G$1:$ZX$1, MATCH( LARGE( INDEX('Project Assignment Check'!$G:$ZX, MATCH($A10, 'Project Assignment Check'!$A:$A, 0), ), COLUMN()-4 ), INDEX('Project Assignment Check'!$G:$ZX, MATCH($A10, 'Project Assignment Check'!$A:$A, 0), ), 0 ) ), "" ) | G10: =IFERROR( INDEX('Project Assignment Check'!$G$1:$ZX$1, MATCH( LARGE( INDEX('Project Assignment Check'!$G:$ZX, MATCH($A10, 'Project Assignment Check'!$A:$A, 0), ), COLUMN()-4 ), INDEX('Project Assignment Check'!$G:$ZX, MATCH($A10, 'Project Assignment Check'!$A:$A, 0), ), 0 ) ), "" ) | H10: =IFERROR( INDEX('Project Assignment Check'!$G$1:$ZX$1, MATCH( LARGE( INDEX('Project Assignment Check'!$G:$ZX, MATCH($A10, 'Project Assignment Check'!$A:$A, 0), ), COLUMN()-4 ), INDEX('Project Assignment Check'!$G:$ZX, MATCH($A10, 'Project Assignment Check'!$A:$A, 0), ), 0 ) ), "" ) | I10: =IFERROR( INDEX('Project Assignment Check'!$G$1:$ZX$1, MATCH( LARGE( INDEX('Project Assignment Check'!$G:$ZX, MATCH($A10, 'Project Assignment Check'!$A:$A, 0), ), COLUMN()-4 ), INDEX('Project Assignment Check'!$G:$ZX, MATCH($A10, 'Project Assignment Check'!$A:$A, 0), ), 0 ) ), "" ) | J10: =IFERROR( INDEX('Project Assignment Check'!$G$1:$ZX$1, MATCH( LARGE( INDEX('Project Assignment Check'!$G:$ZX, MATCH($A10, 'Project Assignment Check'!$A:$A, 0), ), COLUMN()-4 ), INDEX('Project Assignment Check'!$G:$ZX, MATCH($A10, 'Project Assignment Check'!$A:$A, 0), ), 0 ) ), "" )
A11: SRP8-010 | B11: Ventilation | C11: Chassis & Bodywork | D11: Energy Systems | E11: =IF(IFERROR( INDEX('Project Assignment Check'!$G$1:$ZX$1, MATCH( LARGE( INDEX('Project Assignment Check'!$G:$ZX, MATCH($A11, 'Project Assignment Check'!$A:$A, 0), ), COLUMN()-4 ), INDEX('Project Assignment Check'!$G:$ZX, MATCH($A11, 'Project Assignment Check'!$A:$A, 0), ), 0 ) ), "" ) = 0,"", IFERROR( INDEX('Project Assignment Check'!$G$1:$ZX$1, MATCH( LARGE( INDEX('Project Assignment Check'!$G:$ZX, MATCH($A11, 'Project Assignment Check'!$A:$A, 0), ), COLUMN()-4 ), INDEX('Project Assignment Check'!$G:$ZX, MATCH($A11, 'Project Assignment Check'!$A:$A, 0), ), 0 ) ), "" )) | F11: =IFERROR( INDEX('Project Assignment Check'!$G$1:$ZX$1, MATCH( LARGE( INDEX('Project Assignment Check'!$G:$ZX, MATCH($A11, 'Project Assignment Check'!$A:$A, 0), ), COLUMN()-4 ), INDEX('Project Assignment Check'!$G:$ZX, MATCH($A11, 'Project Assignment Check'!$A:$A, 0), ), 0 ) ), "" ) | G11: =IFERROR( INDEX('Project Assignment Check'!$G$1:$ZX$1, MATCH( LARGE( INDEX('Project Assignment Check'!$G:$ZX, MATCH($A11, 'Project Assignment Check'!$A:$A, 0), ), COLUMN()-4 ), INDEX('Project Assignment Check'!$G:$ZX, MATCH($A11, 'Project Assignment Check'!$A:$A, 0), ), 0 ) ), "" ) | H11: =IFERROR( INDEX('Project Assignment Check'!$G$1:$ZX$1, MATCH( LARGE( INDEX('Project Assignment Check'!$G:$ZX, MATCH($A11, 'Project Assignment Check'!$A:$A, 0), ), COLUMN()-4 ), INDEX('Project Assignment Check'!$G:$ZX, MATCH($A11, 'Project Assignment Check'!$A:$A, 0), ), 0 ) ), "" ) | I11: =IFERROR( INDEX('Project Assignment Check'!$G$1:$ZX$1, MATCH( LARGE( INDEX('Project Assignment Check'!$G:$ZX, MATCH($A11, 'Project Assignment Check'!$A:$A, 0), ), COLUMN()-4 ), INDEX('Project Assignment Check'!$G:$ZX, MATCH($A11, 'Project Assignment Check'!$A:$A, 0), ), 0 ) ), "" ) | J11: =IFERROR( INDEX('Project Assignment Check'!$G$1:$ZX$1, MATCH( LARGE( INDEX('Project Assignment Check'!$G:$ZX, MATCH($A11, 'Project Assignment Check'!$A:$A, 0), ), COLUMN()-4 ), INDEX('Project Assignment Check'!$G:$ZX, MATCH($A11, 'Project Assignment Check'!$A:$A, 0), ), 0 ) ), "" )
A12: SRP8-011 | B12: Tailights | C12: Embedded Systems | D12: Chassis & Bodywork | E12: =IF(IFERROR( INDEX('Project Assignment Check'!$G$1:$ZX$1, MATCH( LARGE( INDEX('Project Assignment Check'!$G:$ZX, MATCH($A12, 'Project Assignment Check'!$A:$A, 0), ), COLUMN()-4 ), INDEX('Project Assignment Check'!$G:$ZX, MATCH($A12, 'Project Assignment Check'!$A:$A, 0), ), 0 ) ), "" ) = 0,"", IFERROR( INDEX('Project Assignment Check'!$G$1:$ZX$1, MATCH( LARGE( INDEX('Project Assignment Check'!$G:$ZX, MATCH($A12, 'Project Assignment Check'!$A:$A, 0), ), COLUMN()-4 ), INDEX('Project Assignment Check'!$G:$ZX, MATCH($A12, 'Project Assignment Check'!$A:$A, 0), ), 0 ) ), "" )) -> ADR-01 | F12: =IFERROR( INDEX('Project Assignment Check'!$G$1:$ZX$1, MATCH( LARGE( INDEX('Project Assignment Check'!$G:$ZX, MATCH($A12, 'Project Assignment Check'!$A:$A, 0), ), COLUMN()-4 ), INDEX('Project Assignment Check'!$G:$ZX, MATCH($A12, 'Project Assignment Check'!$A:$A, 0), ), 0 ) ), "" ) -> ADR-01 | G12: =IFERROR( INDEX('Project Assignment Check'!$G$1:$ZX$1, MATCH( LARGE( INDEX('Project Assignment Check'!$G:$ZX, MATCH($A12, 'Project Assignment Check'!$A:$A, 0), ), COLUMN()-4 ), INDEX('Project Assignment Check'!$G:$ZX, MATCH($A12, 'Project Assignment Check'!$A:$A, 0), ), 0 ) ), "" ) -> ADR-01 | H12: =IFERROR( INDEX('Project Assignment Check'!$G$1:$ZX$1, MATCH( LARGE( INDEX('Project Assignment Check'!$G:$ZX, MATCH($A12, 'Project Assignment Check'!$A:$A, 0), ), COLUMN()-4 ), INDEX('Project Assignment Check'!$G:$ZX, MATCH($A12, 'Project Assignment Check'!$A:$A, 0), ), 0 ) ), "" ) -> ADR-01 | I12: =IFERROR( INDEX('Project Assignment Check'!$G$1:$ZX$1, MATCH( LARGE( INDEX('Project Assignment Check'!$G:$ZX, MATCH($A12, 'Project Assignment Check'!$A:$A, 0), ), COLUMN()-4 ), INDEX('Project Assignment Check'!$G:$ZX, MATCH($A12, 'Project Assignment Check'!$A:$A, 0), ), 0 ) ), "" ) | J12: =IFERROR( INDEX('Project Assignment Check'!$G$1:$ZX$1, MATCH( LARGE( INDEX('Project Assignment Check'!$G:$ZX, MATCH($A12, 'Project Assignment Check'!$A:$A, 0), ), COLUMN()-4 ), INDEX('Project Assignment Check'!$G:$ZX, MATCH($A12, 'Project Assignment Check'!$A:$A, 0), ), 0 ) ), "" )
A13: SRP8-012 | B13: Headlights | C13: Embedded Systems | D13: Chassis & Bodywork | E13: =IF(IFERROR( INDEX('Project Assignment Check'!$G$1:$ZX$1, MATCH( LARGE( INDEX('Project Assignment Check'!$G:$ZX, MATCH($A13, 'Project Assignment Check'!$A:$A, 0), ), COLUMN()-4 ), INDEX('Project Assignment Check'!$G:$ZX, MATCH($A13, 'Project Assignment Check'!$A:$A, 0), ), 0 ) ), "" ) = 0,"", IFERROR( INDEX('Project Assignment Check'!$G$1:$ZX$1, MATCH( LARGE( INDEX('Project Assignment Check'!$G:$ZX, MATCH($A13, 'Project Assignment Check'!$A:$A, 0), ), COLUMN()-4 ), INDEX('Project Assignment Check'!$G:$ZX, MATCH($A13, 'Project Assignment Check'!$A:$A, 0), ), 0 ) ), "" )) -> ADR-46 | F13: =IFERROR( INDEX('Project Assignment Check'!$G$1:$ZX$1, MATCH( LARGE( INDEX('Project Assignment Check'!$G:$ZX, MATCH($A13, 'Project Assignment Check'!$A:$A, 0), ), COLUMN()-4 ), INDEX('Project Assignment Check'!$G:$ZX, MATCH($A13, 'Project Assignment Check'!$A:$A, 0), ), 0 ) ), "" ) -> ADR-92 | G13: =IFERROR( INDEX('Project Assignment Check'!$G$1:$ZX$1, MATCH( LARGE( INDEX('Project Assignment Check'!$G:$ZX, MATCH($A13, 'Project Assignment Check'!$A:$A, 0), ), COLUMN()-4 ), INDEX('Project Assignment Check'!$G:$ZX, MATCH($A13, 'Project Assignment Check'!$A:$A, 0), ), 0 ) ), "" ) -> ADR-76 | H13: =IFERROR( INDEX('Project Assignment Check'!$G$1:$ZX$1, MATCH( LARGE( INDEX('Project Assignment Check'!$G:$ZX, MATCH($A13, 'Project Assignment Check'!$A:$A, 0), ), COLUMN()-4 ), INDEX('Project Assignment Check'!$G:$ZX, MATCH($A13, 'Project Assignment Check'!$A:$A, 0), ), 0 ) ), "" ) -> ADR-06 | I13: =IFERROR( INDEX('Project Assignment Check'!$G$1:$ZX$1, MATCH( LARGE( INDEX('Project Assignment Check'!$G:$ZX, MATCH($A13, 'Project Assignment Check'!$A:$A, 0), ), COLUMN()-4 ), INDEX('Project Assignment Check'!$G:$ZX, MATCH($A13, 'Project Assignment Check'!$A:$A, 0), ), 0 ) ), "" ) -> ADR-06 | J13: =IFERROR( INDEX('Project Assignment Check'!$G$1:$ZX$1, MATCH( LARGE( INDEX('Project Assignment Check'!$G:$ZX, MATCH($A13, 'Project Assignment Check'!$A:$A, 0), ), COLUMN()-4 ), INDEX('Project Assignment Check'!$G:$ZX, MATCH($A13, 'Project Assignment Check'!$A:$A, 0), ), 0 ) ), "" )
A14: SRP8-013 | B14: Indicators | C14: Embedded Systems | D14: Chassis & Bodywork | E14: =IF(IFERROR( INDEX('Project Assignment Check'!$G$1:$ZX$1, MATCH( LARGE( INDEX('Project Assignment Check'!$G:$ZX, MATCH($A14, 'Project Assignment Check'!$A:$A, 0), ), COLUMN()-4 ), INDEX('Project Assignment Check'!$G:$ZX, MATCH($A14, 'Project Assignment Check'!$A:$A, 0), ), 0 ) ), "" ) = 0,"", IFERROR( INDEX('Project Assignment Check'!$G$1:$ZX$1, MATCH( LARGE( INDEX('Project Assignment Check'!$G:$ZX, MATCH($A14, 'Project Assignment Check'!$A:$A, 0), ), COLUMN()-4 ), INDEX('Project Assignment Check'!$G:$ZX, MATCH($A14, 'Project Assignment Check'!$A:$A, 0), ), 0 ) ), "" )) -> ADR-13 | F14: =IFERROR( INDEX('Project Assignment Check'!$G$1:$ZX$1, MATCH( LARGE( INDEX('Project Assignment Check'!$G:$ZX, MATCH($A14, 'Project Assignment Check'!$A:$A, 0), ), COLUMN()-4 ), INDEX('Project Assignment Check'!$G:$ZX, MATCH($A14, 'Project Assignment Check'!$A:$A, 0), ), 0 ) ), "" ) -> ADR-06 | G14: =IFERROR( INDEX('Project Assignment Check'!$G$1:$ZX$1, MATCH( LARGE( INDEX('Project Assignment Check'!$G:$ZX, MATCH($A14, 'Project Assignment Check'!$A:$A, 0), ), COLUMN()-4 ), INDEX('Project Assignment Check'!$G:$ZX, MATCH($A14, 'Project Assignment Check'!$A:$A, 0), ), 0 ) ), "" ) | H14: =IFERROR( INDEX('Project Assignment Check'!$G$1:$ZX$1, MATCH( LARGE( INDEX('Project Assignment Check'!$G:$ZX, MATCH($A14, 'Project Assignment Check'!$A:$A, 0), ), COLUMN()-4 ), INDEX('Project Assignment Check'!$G:$ZX, MATCH($A14, 'Project Assignment Check'!$A:$A, 0), ), 0 ) ), "" ) | I14: =IFERROR( INDEX('Project Assignment Check'!$G$1:$ZX$1, MATCH( LARGE( INDEX('Project Assignment Check'!$G:$ZX, MATCH($A14, 'Project Assignment Check'!$A:$A, 0), ), COLUMN()-4 ), INDEX('Project Assignment Check'!$G:$ZX, MATCH($A14, 'Project Assignment Check'!$A:$A, 0), ), 0 ) ), "" ) | J14: =IFERROR( INDEX('Project Assignment Check'!$G$1:$ZX$1, MATCH( LARGE( INDEX('Project Assignment Check'!$G:$ZX, MATCH($A14, 'Project Assignment Check'!$A:$A, 0), ), COLUMN()-4 ), INDEX('Project Assignment Check'!$G:$ZX, MATCH($A14, 'Project Assignment Check'!$A:$A, 0), ), 0 ) ), "" )
A15: SRP8-014 | B15: Regen Braking | C15: Embedded Systems | E15: =IF(IFERROR( INDEX('Project Assignment Check'!$G$1:$ZX$1, MATCH( LARGE( INDEX('Project Assignment Check'!$G:$ZX, MATCH($A15, 'Project Assignment Check'!$A:$A, 0), ), COLUMN()-4 ), INDEX('Project Assignment Check'!$G:$ZX, MATCH($A15, 'Project Assignment Check'!$A:$A, 0), ), 0 ) ), "" ) = 0,"", IFERROR( INDEX('Project Assignment Check'!$G$1:$ZX$1, MATCH( LARGE( INDEX('Project Assignment Check'!$G:$ZX, MATCH($A15, 'Project Assignment Check'!$A:$A, 0), ), COLUMN()-4 ), INDEX('Project Assignment Check'!$G:$ZX, MATCH($A15, 'Project Assignment Check'!$A:$A, 0), ), 0 ) ), "" )) -> ADR-31 | F15: =IFERROR( INDEX('Project Assignment Check'!$G$1:$ZX$1, MATCH( LARGE( INDEX('Project Assignment Check'!$G:$ZX, MATCH($A15, 'Project Assignment Check'!$A:$A, 0), ), COLUMN()-4 ), INDEX('Project Assignment Check'!$G:$ZX, MATCH($A15, 'Project Assignment Check'!$A:$A, 0), ), 0 ) ), "" ) | G15: =IFERROR( INDEX('Project Assignment Check'!$G$1:$ZX$1, MATCH( LARGE( INDEX('Project Assignment Check'!$G:$ZX, MATCH($A15, 'Project Assignment Check'!$A:$A, 0), ), COLUMN()-4 ), INDEX('Project Assignment Check'!$G:$ZX, MATCH($A15, 'Project Assignment Check'!$A:$A, 0), ), 0 ) ), "" ) | H15: =IFERROR( INDEX('Project Assignment Check'!$G$1:$ZX$1, MATCH( LARGE( INDEX('Project Assignment Check'!$G:$ZX, MATCH($A15, 'Project Assignment Check'!$A:$A, 0), ), COLUMN()-4 ), INDEX('Project Assignment Check'!$G:$ZX, MATCH($A15, 'Project Assignment Check'!$A:$A, 0), ), 0 ) ), "" ) | I15: =IFERROR( INDEX('Project Assignment Check'!$G$1:$ZX$1, MATCH( LARGE( INDEX('Project Assignment Check'!$G:$ZX, MATCH($A15, 'Project Assignment Check'!$A:$A, 0), ), COLUMN()-4 ), INDEX('Project Assignment Check'!$G:$ZX, MATCH($A15, 'Project Assignment Check'!$A:$A, 0), ), 0 ) ), "" ) | J15: =IFERROR( INDEX('Project Assignment Check'!$G$1:$ZX$1, MATCH( LARGE( INDEX('Project Assignment Check'!$G:$ZX, MATCH($A15, 'Project Assignment Check'!$A:$A, 0), ), COLUMN()-4 ), INDEX('Project Assignment Check'!$G:$ZX, MATCH($A15, 'Project Assignment Check'!$A:$A, 0), ), 0 ) ), "" )
A16: SRP8-015 | B16: Cruise Control | C16: Embedded Systems | E16: =IF(IFERROR( INDEX('Project Assignment Check'!$G$1:$ZX$1, MATCH( LARGE( INDEX('Project Assignment Check'!$G:$ZX, MATCH($A16, 'Project Assignment Check'!$A:$A, 0), ), COLUMN()-4 ), INDEX('Project Assignment Check'!$G:$ZX, MATCH($A16, 'Project Assignment Check'!$A:$A, 0), ), 0 ) ), "" ) = 0,"", IFERROR( INDEX('Project Assignment Check'!$G$1:$ZX$1, MATCH( LARGE( INDEX('Project Assignment Check'!$G:$ZX, MATCH($A16, 'Project Assignment Check'!$A:$A, 0), ), COLUMN()-4 ), INDEX('Project Assignment Check'!$G:$ZX, MATCH($A16, 'Project Assignment Check'!$A:$A, 0), ), 0 ) ), "" )) | F16: =IFERROR( INDEX('Project Assignment Check'!$G$1:$ZX$1, MATCH( LARGE( INDEX('Project Assignment Check'!$G:$ZX, MATCH($A16, 'Project Assignment Check'!$A:$A, 0), ), COLUMN()-4 ), INDEX('Project Assignment Check'!$G:$ZX, MATCH($A16, 'Project Assignment Check'!$A:$A, 0), ), 0 ) ), "" ) | G16: =IFERROR( INDEX('Project Assignment Check'!$G$1:$ZX$1, MATCH( LARGE( INDEX('Project Assignment Check'!$G:$ZX, MATCH($A16, 'Project Assignment Check'!$A:$A, 0), ), COLUMN()-4 ), INDEX('Project Assignment Check'!$G:$ZX, MATCH($A16, 'Project Assignment Check'!$A:$A, 0), ), 0 ) ), "" ) | H16: =IFERROR( INDEX('Project Assignment Check'!$G$1:$ZX$1, MATCH( LARGE( INDEX('Project Assignment Check'!$G:$ZX, MATCH($A16, 'Project Assignment Check'!$A:$A, 0), ), COLUMN()-4 ), INDEX('Project Assignment Check'!$G:$ZX, MATCH($A16, 'Project Assignment Check'!$A:$A, 0), ), 0 ) ), "" ) | I16: =IFERROR( INDEX('Project Assignment Check'!$G$1:$ZX$1, MATCH( LARGE( INDEX('Project Assignment Check'!$G:$ZX, MATCH($A16, 'Project Assignment Check'!$A:$A, 0), ), COLUMN()-4 ), INDEX('Project Assignment Check'!$G:$ZX, MATCH($A16, 'Project Assignment Check'!$A:$A, 0), ), 0 ) ), "" ) | J16: =IFERROR( INDEX('Project Assignment Check'!$G$1:$ZX$1, MATCH( LARGE( INDEX('Project Assignment Check'!$G:$ZX, MATCH($A16, 'Project Assignment Check'!$A:$A, 0), ), COLUMN()-4 ), INDEX('Project Assignment Check'!$G:$ZX, MATCH($A16, 'Project Assignment Check'!$A:$A, 0), ), 0 ) ), "" )
A17: SRP8-016 | B17: Battery | C17: Energy Systems | D17: Chassis & Bodywork | E17: =IF(IFERROR( INDEX('Project Assignment Check'!$G$1:$ZX$1, MATCH( LARGE( INDEX('Project Assignment Check'!$G:$ZX, MATCH($A17, 'Project Assignment Check'!$A:$A, 0), ), COLUMN()-4 ), INDEX('Project Assignment Check'!$G:$ZX, MATCH($A17, 'Project Assignment Check'!$A:$A, 0), ), 0 ) ), "" ) = 0,"", IFERROR( INDEX('Project Assignment Check'!$G$1:$ZX$1, MATCH( LARGE( INDEX('Project Assignment Check'!$G:$ZX, MATCH($A17, 'Project Assignment Check'!$A:$A, 0), ), COLUMN()-4 ), INDEX('Project Assignment Check'!$G:$ZX, MATCH($A17, 'Project Assignment Check'!$A:$A, 0), ), 0 ) ), "" )) -> ADR-109 | F17: =IFERROR( INDEX('Project Assignment Check'!$G$1:$ZX$1, MATCH( LARGE( INDEX('Project Assignment Check'!$G:$ZX, MATCH($A17, 'Project Assignment Check'!$A:$A, 0), ), COLUMN()-4 ), INDEX('Project Assignment Check'!$G:$ZX, MATCH($A17, 'Project Assignment Check'!$A:$A, 0), ), 0 ) ), "" ) | G17: =IFERROR( INDEX('Project Assignment Check'!$G$1:$ZX$1, MATCH( LARGE( INDEX('Project Assignment Check'!$G:$ZX, MATCH($A17, 'Project Assignment Check'!$A:$A, 0), ), COLUMN()-4 ), INDEX('Project Assignment Check'!$G:$ZX, MATCH($A17, 'Project Assignment Check'!$A:$A, 0), ), 0 ) ), "" ) | H17: =IFERROR( INDEX('Project Assignment Check'!$G$1:$ZX$1, MATCH( LARGE( INDEX('Project Assignment Check'!$G:$ZX, MATCH($A17, 'Project Assignment Check'!$A:$A, 0), ), COLUMN()-4 ), INDEX('Project Assignment Check'!$G:$ZX, MATCH($A17, 'Project Assignment Check'!$A:$A, 0), ), 0 ) ), "" ) | I17: =IFERROR( INDEX('Project Assignment Check'!$G$1:$ZX$1, MATCH( LARGE( INDEX('Project Assignment Check'!$G:$ZX, MATCH($A17, 'Project Assignment Check'!$A:$A, 0), ), COLUMN()-4 ), INDEX('Project Assignment Check'!$G:$ZX, MATCH($A17, 'Project Assignment Check'!$A:$A, 0), ), 0 ) ), "" ) | J17: =IFERROR( INDEX('Project Assignment Check'!$G$1:$ZX$1, MATCH( LARGE( INDEX('Project Assignment Check'!$G:$ZX, MATCH($A17, 'Project Assignment Check'!$A:$A, 0), ), COLUMN()-4 ), INDEX('Project Assignment Check'!$G:$ZX, MATCH($A17, 'Project Assignment Check'!$A:$A, 0), ), 0 ) ), "" )
A18: SRP8-017 | B18: Auxillary Power Distribution | C18: Energy Systems | D18: Energy Systems | E18: =IF(IFERROR( INDEX('Project Assignment Check'!$G$1:$ZX$1, MATCH( LARGE( INDEX('Project Assignment Check'!$G:$ZX, MATCH($A18, 'Project Assignment Check'!$A:$A, 0), ), COLUMN()-4 ), INDEX('Project Assignment Check'!$G:$ZX, MATCH($A18, 'Project Assignment Check'!$A:$A, 0), ), 0 ) ), "" ) = 0,"", IFERROR( INDEX('Project Assignment Check'!$G$1:$ZX$1, MATCH( LARGE( INDEX('Project Assignment Check'!$G:$ZX, MATCH($A18, 'Project Assignment Check'!$A:$A, 0), ), COLUMN()-4 ), INDEX('Project Assignment Check'!$G:$ZX, MATCH($A18, 'Project Assignment Check'!$A:$A, 0), ), 0 ) ), "" )) | F18: =IFERROR( INDEX('Project Assignment Check'!$G$1:$ZX$1, MATCH( LARGE( INDEX('Project Assignment Check'!$G:$ZX, MATCH($A18, 'Project Assignment Check'!$A:$A, 0), ), COLUMN()-4 ), INDEX('Project Assignment Check'!$G:$ZX, MATCH($A18, 'Project Assignment Check'!$A:$A, 0), ), 0 ) ), "" ) | G18: =IFERROR( INDEX('Project Assignment Check'!$G$1:$ZX$1, MATCH( LARGE( INDEX('Project Assignment Check'!$G:$ZX, MATCH($A18, 'Project Assignment Check'!$A:$A, 0), ), COLUMN()-4 ), INDEX('Project Assignment Check'!$G:$ZX, MATCH($A18, 'Project Assignment Check'!$A:$A, 0), ), 0 ) ), "" ) | H18: =IFERROR( INDEX('Project Assignment Check'!$G$1:$ZX$1, MATCH( LARGE( INDEX('Project Assignment Check'!$G:$ZX, MATCH($A18, 'Project Assignment Check'!$A:$A, 0), ), COLUMN()-4 ), INDEX('Project Assignment Check'!$G:$ZX, MATCH($A18, 'Project Assignment Check'!$A:$A, 0), ), 0 ) ), "" ) | I18: =IFERROR( INDEX('Project Assignment Check'!$G$1:$ZX$1, MATCH( LARGE( INDEX('Project Assignment Check'!$G:$ZX, MATCH($A18, 'Project Assignment Check'!$A:$A, 0), ), COLUMN()-4 ), INDEX('Project Assignment Check'!$G:$ZX, MATCH($A18, 'Project Assignment Check'!$A:$A, 0), ), 0 ) ), "" ) | J18: =IFERROR( INDEX('Project Assignment Check'!$G$1:$ZX$1, MATCH( LARGE( INDEX('Project Assignment Check'!$G:$ZX, MATCH($A18, 'Project Assignment Check'!$A:$A, 0), ), COLUMN()-4 ), INDEX('Project Assignment Check'!$G:$ZX, MATCH($A18, 'Project Assignment Check'!$A:$A, 0), ), 0 ) ), "" )
A19: SRP8-018 | B19: Energy Control | C19: Energy Systems | E19: =IF(IFERROR( INDEX('Project Assignment Check'!$G$1:$ZX$1, MATCH( LARGE( INDEX('Project Assignment Check'!$G:$ZX, MATCH($A19, 'Project Assignment Check'!$A:$A, 0), ), COLUMN()-4 ), INDEX('Project Assignment Check'!$G:$ZX, MATCH($A19, 'Project Assignment Check'!$A:$A, 0), ), 0 ) ), "" ) = 0,"", IFERROR( INDEX('Project Assignment Check'!$G$1:$ZX$1, MATCH( LARGE( INDEX('Project Assignment Check'!$G:$ZX, MATCH($A19, 'Project Assignment Check'!$A:$A, 0), ), COLUMN()-4 ), INDEX('Project Assignment Check'!$G:$ZX, MATCH($A19, 'Project Assignment Check'!$A:$A, 0), ), 0 ) ), "" )) -> ADR-90 | F19: =IFERROR( INDEX('Project Assignment Check'!$G$1:$ZX$1, MATCH( LARGE( INDEX('Project Assignment Check'!$G:$ZX, MATCH($A19, 'Project Assignment Check'!$A:$A, 0), ), COLUMN()-4 ), INDEX('Project Assignment Check'!$G:$ZX, MATCH($A19, 'Project Assignment Check'!$A:$A, 0), ), 0 ) ), "" ) -> ADR-90 | G19: =IFERROR( INDEX('Project Assignment Check'!$G$1:$ZX$1, MATCH( LARGE( INDEX('Project Assignment Check'!$G:$ZX, MATCH($A19, 'Project Assignment Check'!$A:$A, 0), ), COLUMN()-4 ), INDEX('Project Assignment Check'!$G:$ZX, MATCH($A19, 'Project Assignment Check'!$A:$A, 0), ), 0 ) ), "" ) | H19: =IFERROR( INDEX('Project Assignment Check'!$G$1:$ZX$1, MATCH( LARGE( INDEX('Project Assignment Check'!$G:$ZX, MATCH($A19, 'Project Assignment Check'!$A:$A, 0), ), COLUMN()-4 ), INDEX('Project Assignment Check'!$G:$ZX, MATCH($A19, 'Project Assignment Check'!$A:$A, 0), ), 0 ) ), "" ) | I19: =IFERROR( INDEX('Project Assignment Check'!$G$1:$ZX$1, MATCH( LARGE( INDEX('Project Assignment Check'!$G:$ZX, MATCH($A19, 'Project Assignment Check'!$A:$A, 0), ), COLUMN()-4 ), INDEX('Project Assignment Check'!$G:$ZX, MATCH($A19, 'Project Assignment Check'!$A:$A, 0), ), 0 ) ), "" ) | J19: =IFERROR( INDEX('Project Assignment Check'!$G$1:$ZX$1, MATCH( LARGE( INDEX('Project Assignment Check'!$G:$ZX, MATCH($A19, 'Project Assignment Check'!$A:$A, 0), ), COLUMN()-4 ), INDEX('Project Assignment Check'!$G:$ZX, MATCH($A19, 'Project Assignment Check'!$A:$A, 0), ), 0 ) ), "" )
A20: SRP8-019 | B20: MPPTs | C20: Energy Systems | E20: =IF(IFERROR( INDEX('Project Assignment Check'!$G$1:$ZX$1, MATCH( LARGE( INDEX('Project Assignment Check'!$G:$ZX, MATCH($A20, 'Project Assignment Check'!$A:$A, 0), ), COLUMN()-4 ), INDEX('Project Assignment Check'!$G:$ZX, MATCH($A20, 'Project Assignment Check'!$A:$A, 0), ), 0 ) ), "" ) = 0,"", IFERROR( INDEX('Project Assignment Check'!$G$1:$ZX$1, MATCH( LARGE( INDEX('Project Assignment Check'!$G:$ZX, MATCH($A20, 'Project Assignment Check'!$A:$A, 0), ), COLUMN()-4 ), INDEX('Project Assignment Check'!$G:$ZX, MATCH($A20, 'Project Assignment Check'!$A:$A, 0), ), 0 ) ), "" )) | F20: =IFERROR( INDEX('Project Assignment Check'!$G$1:$ZX$1, MATCH( LARGE( INDEX('Project Assignment Check'!$G:$ZX, MATCH($A20, 'Project Assignment Check'!$A:$A, 0), ), COLUMN()-4 ), INDEX('Project Assignment Check'!$G:$ZX, MATCH($A20, 'Project Assignment Check'!$A:$A, 0), ), 0 ) ), "" ) | G20: =IFERROR( INDEX('Project Assignment Check'!$G$1:$ZX$1, MATCH( LARGE( INDEX('Project Assignment Check'!$G:$ZX, MATCH($A20, 'Project Assignment Check'!$A:$A, 0), ), COLUMN()-4 ), INDEX('Project Assignment Check'!$G:$ZX, MATCH($A20, 'Project Assignment Check'!$A:$A, 0), ), 0 ) ), "" ) | H20: =IFERROR( INDEX('Project Assignment Check'!$G$1:$ZX$1, MATCH( LARGE( INDEX('Project Assignment Check'!$G:$ZX, MATCH($A20, 'Project Assignment Check'!$A:$A, 0), ), COLUMN()-4 ), INDEX('Project Assignment Check'!$G:$ZX, MATCH($A20, 'Project Assignment Check'!$A:$A, 0), ), 0 ) ), "" ) | I20: =IFERROR( INDEX('Project Assignment Check'!$G$1:$ZX$1, MATCH( LARGE( INDEX('Project Assignment Check'!$G:$ZX, MATCH($A20, 'Project Assignment Check'!$A:$A, 0), ), COLUMN()-4 ), INDEX('Project Assignment Check'!$G:$ZX, MATCH($A20, 'Project Assignment Check'!$A:$A, 0), ), 0 ) ), "" ) | J20: =IFERROR( INDEX('Project Assignment Check'!$G$1:$ZX$1, MATCH( LARGE( INDEX('Project Assignment Check'!$G:$ZX, MATCH($A20, 'Project Assignment Check'!$A:$A, 0), ), COLUMN()-4 ), INDEX('Project Assignment Check'!$G:$ZX, MATCH($A20, 'Project Assignment Check'!$A:$A, 0), ), 0 ) ), "" )
A21: SRP8-020 | B21: Solar Array | C21: Energy Systems | D21: Chassis & Bodywork | E21: =IF(IFERROR( INDEX('Project Assignment Check'!$G$1:$ZX$1, MATCH( LARGE( INDEX('Project Assignment Check'!$G:$ZX, MATCH($A21, 'Project Assignment Check'!$A:$A, 0), ), COLUMN()-4 ), INDEX('Project Assignment Check'!$G:$ZX, MATCH($A21, 'Project Assignment Check'!$A:$A, 0), ), 0 ) ), "" ) = 0,"", IFERROR( INDEX('Project Assignment Check'!$G$1:$ZX$1, MATCH( LARGE( INDEX('Project Assignment Check'!$G:$ZX, MATCH($A21, 'Project Assignment Check'!$A:$A, 0), ), COLUMN()-4 ), INDEX('Project Assignment Check'!$G:$ZX, MATCH($A21, 'Project Assignment Check'!$A:$A, 0), ), 0 ) ), "" )) | F21: =IFERROR( INDEX('Project Assignment Check'!$G$1:$ZX$1, MATCH( LARGE( INDEX('Project Assignment Check'!$G:$ZX, MATCH($A21, 'Project Assignment Check'!$A:$A, 0), ), COLUMN()-4 ), INDEX('Project Assignment Check'!$G:$ZX, MATCH($A21, 'Project Assignment Check'!$A:$A, 0), ), 0 ) ), "" ) | G21: =IFERROR( INDEX('Project Assignment Check'!$G$1:$ZX$1, MATCH( LARGE( INDEX('Project Assignment Check'!$G:$ZX, MATCH($A21, 'Project Assignment Check'!$A:$A, 0), ), COLUMN()-4 ), INDEX('Project Assignment Check'!$G:$ZX, MATCH($A21, 'Project Assignment Check'!$A:$A, 0), ), 0 ) ), "" ) | H21: =IFERROR( INDEX('Project Assignment Check'!$G$1:$ZX$1, MATCH( LARGE( INDEX('Project Assignment Check'!$G:$ZX, MATCH($A21, 'Project Assignment Check'!$A:$A, 0), ), COLUMN()-4 ), INDEX('Project Assignment Check'!$G:$ZX, MATCH($A21, 'Project Assignment Check'!$A:$A, 0), ), 0 ) ), "" ) | I21: =IFERROR( INDEX('Project Assignment Check'!$G$1:$ZX$1, MATCH( LARGE( INDEX('Project Assignment Check'!$G:$ZX, MATCH($A21, 'Project Assignment Check'!$A:$A, 0), ), COLUMN()-4 ), INDEX('Project Assignment Check'!$G:$ZX, MATCH($A21, 'Project Assignment Check'!$A:$A, 0), ), 0 ) ), "" ) | J21: =IFERROR( INDEX('Project Assignment Check'!$G$1:$ZX$1, MATCH( LARGE( INDEX('Project Assignment Check'!$G:$ZX, MATCH($A21, 'Project Assignment Check'!$A:$A, 0), ), COLUMN()-4 ), INDEX('Project Assignment Check'!$G:$ZX, MATCH($A21, 'Project Assignment Check'!$A:$A, 0), ), 0 ) ), "" )
A22: SRP8-021 | B22: Charging | C22: Energy Systems | D22: Chassis & Bodywork | E22: =IF(IFERROR( INDEX('Project Assignment Check'!$G$1:$ZX$1, MATCH( LARGE( INDEX('Project Assignment Check'!$G:$ZX, MATCH($A22, 'Project Assignment Check'!$A:$A, 0), ), COLUMN()-4 ), INDEX('Project Assignment Check'!$G:$ZX, MATCH($A22, 'Project Assignment Check'!$A:$A, 0), ), 0 ) ), "" ) = 0,"", IFERROR( INDEX('Project Assignment Check'!$G$1:$ZX$1, MATCH( LARGE( INDEX('Project Assignment Check'!$G:$ZX, MATCH($A22, 'Project Assignment Check'!$A:$A, 0), ), COLUMN()-4 ), INDEX('Project Assignment Check'!$G:$ZX, MATCH($A22, 'Project Assignment Check'!$A:$A, 0), ), 0 ) ), "" )) -> ADR-109 | F22: =IFERROR( INDEX('Project Assignment Check'!$G$1:$ZX$1, MATCH( LARGE( INDEX('Project Assignment Check'!$G:$ZX, MATCH($A22, 'Project Assignment Check'!$A:$A, 0), ), COLUMN()-4 ), INDEX('Project Assignment Check'!$G:$ZX, MATCH($A22, 'Project Assignment Check'!$A:$A, 0), ), 0 ) ), "" ) | G22: =IFERROR( INDEX('Project Assignment Check'!$G$1:$ZX$1, MATCH( LARGE( INDEX('Project Assignment Check'!$G:$ZX, MATCH($A22, 'Project Assignment Check'!$A:$A, 0), ), COLUMN()-4 ), INDEX('Project Assignment Check'!$G:$ZX, MATCH($A22, 'Project Assignment Check'!$A:$A, 0), ), 0 ) ), "" ) | H22: =IFERROR( INDEX('Project Assignment Check'!$G$1:$ZX$1, MATCH( LARGE( INDEX('Project Assignment Check'!$G:$ZX, MATCH($A22, 'Project Assignment Check'!$A:$A, 0), ), COLUMN()-4 ), INDEX('Project Assignment Check'!$G:$ZX, MATCH($A22, 'Project Assignment Check'!$A:$A, 0), ), 0 ) ), "" ) | I22: =IFERROR( INDEX('Project Assignment Check'!$G$1:$ZX$1, MATCH( LARGE( INDEX('Project Assignment Check'!$G:$ZX, MATCH($A22, 'Project Assignment Check'!$A:$A, 0), ), COLUMN()-4 ), INDEX('Project Assignment Check'!$G:$ZX, MATCH($A22, 'Project Assignment Check'!$A:$A, 0), ), 0 ) ), "" ) | J22: =IFERROR( INDEX('Project Assignment Check'!$G$1:$ZX$1, MATCH( LARGE( INDEX('Project Assignment Check'!$G:$ZX, MATCH($A22, 'Project Assignment Check'!$A:$A, 0), ), COLUMN()-4 ), INDEX('Project Assignment Check'!$G:$ZX, MATCH($A22, 'Project Assignment Check'!$A:$A, 0), ), 0 ) ), "" )
A23: SRP8-022 | B23: Steering Wheel | C23: Interior | D23: Embedded Systems | E23: =IF(IFERROR( INDEX('Project Assignment Check'!$G$1:$ZX$1, MATCH( LARGE( INDEX('Project Assignment Check'!$G:$ZX, MATCH($A23, 'Project Assignment Check'!$A:$A, 0), ), COLUMN()-4 ), INDEX('Project Assignment Check'!$G:$ZX, MATCH($A23, 'Project Assignment Check'!$A:$A, 0), ), 0 ) ), "" ) = 0,"", IFERROR( INDEX('Project Assignment Check'!$G$1:$ZX$1, MATCH( LARGE( INDEX('Project Assignment Check'!$G:$ZX, MATCH($A23, 'Project Assignment Check'!$A:$A, 0), ), COLUMN()-4 ), INDEX('Project Assignment Check'!$G:$ZX, MATCH($A23, 'Project Assignment Check'!$A:$A, 0), ), 0 ) ), "" )) -> ADR-42 | F23: =IFERROR( INDEX('Project Assignment Check'!$G$1:$ZX$1, MATCH( LARGE( INDEX('Project Assignment Check'!$G:$ZX, MATCH($A23, 'Project Assignment Check'!$A:$A, 0), ), COLUMN()-4 ), INDEX('Project Assignment Check'!$G:$ZX, MATCH($A23, 'Project Assignment Check'!$A:$A, 0), ), 0 ) ), "" ) -> ADR-10 | G23: =IFERROR( INDEX('Project Assignment Check'!$G$1:$ZX$1, MATCH( LARGE( INDEX('Project Assignment Check'!$G:$ZX, MATCH($A23, 'Project Assignment Check'!$A:$A, 0), ), COLUMN()-4 ), INDEX('Project Assignment Check'!$G:$ZX, MATCH($A23, 'Project Assignment Check'!$A:$A, 0), ), 0 ) ), "" ) -> ADR-10 | H23: =IFERROR( INDEX('Project Assignment Check'!$G$1:$ZX$1, MATCH( LARGE( INDEX('Project Assignment Check'!$G:$ZX, MATCH($A23, 'Project Assignment Check'!$A:$A, 0), ), COLUMN()-4 ), INDEX('Project Assignment Check'!$G:$ZX, MATCH($A23, 'Project Assignment Check'!$A:$A, 0), ), 0 ) ), "" ) | I23: =IFERROR( INDEX('Project Assignment Check'!$G$1:$ZX$1, MATCH( LARGE( INDEX('Project Assignment Check'!$G:$ZX, MATCH($A23, 'Project Assignment Check'!$A:$A, 0), ), COLUMN()-4 ), INDEX('Project Assignment Check'!$G:$ZX, MATCH($A23, 'Project Assignment Check'!$A:$A, 0), ), 0 ) ), "" ) | J23: =IFERROR( INDEX('Project Assignment Check'!$G$1:$ZX$1, MATCH( LARGE( INDEX('Project Assignment Check'!$G:$ZX, MATCH($A23, 'Project Assignment Check'!$A:$A, 0), ), COLUMN()-4 ), INDEX('Project Assignment Check'!$G:$ZX, MATCH($A23, 'Project Assignment Check'!$A:$A, 0), ), 0 ) ), "" )
A24: SRP8-023 | B24: Interior Lights | C24: Interior | D24: Embedded Systems | E24: =IF(IFERROR( INDEX('Project Assignment Check'!$G$1:$ZX$1, MATCH( LARGE( INDEX('Project Assignment Check'!$G:$ZX, MATCH($A24, 'Project Assignment Check'!$A:$A, 0), ), COLUMN()-4 ), INDEX('Project Assignment Check'!$G:$ZX, MATCH($A24, 'Project Assignment Check'!$A:$A, 0), ), 0 ) ), "" ) = 0,"", IFERROR( INDEX('Project Assignment Check'!$G$1:$ZX$1, MATCH( LARGE( INDEX('Project Assignment Check'!$G:$ZX, MATCH($A24, 'Project Assignment Check'!$A:$A, 0), ), COLUMN()-4 ), INDEX('Project Assignment Check'!$G:$ZX, MATCH($A24, 'Project Assignment Check'!$A:$A, 0), ), 0 ) ), "" )) | F24: =IFERROR( INDEX('Project Assignment Check'!$G$1:$ZX$1, MATCH( LARGE( INDEX('Project Assignment Check'!$G:$ZX, MATCH($A24, 'Project Assignment Check'!$A:$A, 0), ), COLUMN()-4 ), INDEX('Project Assignment Check'!$G:$ZX, MATCH($A24, 'Project Assignment Check'!$A:$A, 0), ), 0 ) ), "" ) | G24: =IFERROR( INDEX('Project Assignment Check'!$G$1:$ZX$1, MATCH( LARGE( INDEX('Project Assignment Check'!$G:$ZX, MATCH($A24, 'Project Assignment Check'!$A:$A, 0), ), COLUMN()-4 ), INDEX('Project Assignment Check'!$G:$ZX, MATCH($A24, 'Project Assignment Check'!$A:$A, 0), ), 0 ) ), "" ) | H24: =IFERROR( INDEX('Project Assignment Check'!$G$1:$ZX$1, MATCH( LARGE( INDEX('Project Assignment Check'!$G:$ZX, MATCH($A24, 'Project Assignment Check'!$A:$A, 0), ), COLUMN()-4 ), INDEX('Project Assignment Check'!$G:$ZX, MATCH($A24, 'Project Assignment Check'!$A:$A, 0), ), 0 ) ), "" ) | I24: =IFERROR( INDEX('Project Assignment Check'!$G$1:$ZX$1, MATCH( LARGE( INDEX('Project Assignment Check'!$G:$ZX, MATCH($A24, 'Project Assignment Check'!$A:$A, 0), ), COLUMN()-4 ), INDEX('Project Assignment Check'!$G:$ZX, MATCH($A24, 'Project Assignment Check'!$A:$A, 0), ), 0 ) ), "" ) | J24: =IFERROR( INDEX('Project Assignment Check'!$G$1:$ZX$1, MATCH( LARGE( INDEX('Project Assignment Check'!$G:$ZX, MATCH($A24, 'Project Assignment Check'!$A:$A, 0), ), COLUMN()-4 ), INDEX('Project Assignment Check'!$G:$ZX, MATCH($A24, 'Project Assignment Check'!$A:$A, 0), ), 0 ) ), "" )
A25: SRP8-024 | B25: Rear Vision System | C25: Interior | D25: Chassis & Bodywork | E25: =IF(IFERROR( INDEX('Project Assignment Check'!$G$1:$ZX$1, MATCH( LARGE( INDEX('Project Assignment Check'!$G:$ZX, MATCH($A25, 'Project Assignment Check'!$A:$A, 0), ), COLUMN()-4 ), INDEX('Project Assignment Check'!$G:$ZX, MATCH($A25, 'Project Assignment Check'!$A:$A, 0), ), 0 ) ), "" ) = 0,"", IFERROR( INDEX('Project Assignment Check'!$G$1:$ZX$1, MATCH( LARGE( INDEX('Project Assignment Check'!$G:$ZX, MATCH($A25, 'Project Assignment Check'!$A:$A, 0), ), COLUMN()-4 ), INDEX('Project Assignment Check'!$G:$ZX, MATCH($A25, 'Project Assignment Check'!$A:$A, 0), ), 0 ) ), "" )) -> ADR-14 | F25: =IFERROR( INDEX('Project Assignment Check'!$G$1:$ZX$1, MATCH( LARGE( INDEX('Project Assignment Check'!$G:$ZX, MATCH($A25, 'Project Assignment Check'!$A:$A, 0), ), COLUMN()-4 ), INDEX('Project Assignment Check'!$G:$ZX, MATCH($A25, 'Project Assignment Check'!$A:$A, 0), ), 0 ) ), "" ) | G25: =IFERROR( INDEX('Project Assignment Check'!$G$1:$ZX$1, MATCH( LARGE( INDEX('Project Assignment Check'!$G:$ZX, MATCH($A25, 'Project Assignment Check'!$A:$A, 0), ), COLUMN()-4 ), INDEX('Project Assignment Check'!$G:$ZX, MATCH($A25, 'Project Assignment Check'!$A:$A, 0), ), 0 ) ), "" ) | H25: =IFERROR( INDEX('Project Assignment Check'!$G$1:$ZX$1, MATCH( LARGE( INDEX('Project Assignment Check'!$G:$ZX, MATCH($A25, 'Project Assignment Check'!$A:$A, 0), ), COLUMN()-4 ), INDEX('Project Assignment Check'!$G:$ZX, MATCH($A25, 'Project Assignment Check'!$A:$A, 0), ), 0 ) ), "" ) | I25: =IFERROR( INDEX('Project Assignment Check'!$G$1:$ZX$1, MATCH( LARGE( INDEX('Project Assignment Check'!$G:$ZX, MATCH($A25, 'Project Assignment Check'!$A:$A, 0), ), COLUMN()-4 ), INDEX('Project Assignment Check'!$G:$ZX, MATCH($A25, 'Project Assignment Check'!$A:$A, 0), ), 0 ) ), "" ) | J25: =IFERROR( INDEX('Project Assignment Check'!$G$1:$ZX$1, MATCH( LARGE( INDEX('Project Assignment Check'!$G:$ZX, MATCH($A25, 'Project Assignment Check'!$A:$A, 0), ), COLUMN()-4 ), INDEX('Project Assignment Check'!$G:$ZX, MATCH($A25, 'Project Assignment Check'!$A:$A, 0), ), 0 ) ), "" )
A26: SRP8-025 | B26: Side Vision System | C26: Interior | D26: Chassis & Bodywork | E26: =IF(IFERROR( INDEX('Project Assignment Check'!$G$1:$ZX$1, MATCH( LARGE( INDEX('Project Assignment Check'!$G:$ZX, MATCH($A26, 'Project Assignment Check'!$A:$A, 0), ), COLUMN()-4 ), INDEX('Project Assignment Check'!$G:$ZX, MATCH($A26, 'Project Assignment Check'!$A:$A, 0), ), 0 ) ), "" ) = 0,"", IFERROR( INDEX('Project Assignment Check'!$G$1:$ZX$1, MATCH( LARGE( INDEX('Project Assignment Check'!$G:$ZX, MATCH($A26, 'Project Assignment Check'!$A:$A, 0), ), COLUMN()-4 ), INDEX('Project Assignment Check'!$G:$ZX, MATCH($A26, 'Project Assignment Check'!$A:$A, 0), ), 0 ) ), "" )) | F26: =IFERROR( INDEX('Project Assignment Check'!$G$1:$ZX$1, MATCH( LARGE( INDEX('Project Assignment Check'!$G:$ZX, MATCH($A26, 'Project Assignment Check'!$A:$A, 0), ), COLUMN()-4 ), INDEX('Project Assignment Check'!$G:$ZX, MATCH($A26, 'Project Assignment Check'!$A:$A, 0), ), 0 ) ), "" ) | G26: =IFERROR( INDEX('Project Assignment Check'!$G$1:$ZX$1, MATCH( LARGE( INDEX('Project Assignment Check'!$G:$ZX, MATCH($A26, 'Project Assignment Check'!$A:$A, 0), ), COLUMN()-4 ), INDEX('Project Assignment Check'!$G:$ZX, MATCH($A26, 'Project Assignment Check'!$A:$A, 0), ), 0 ) ), "" ) | H26: =IFERROR( INDEX('Project Assignment Check'!$G$1:$ZX$1, MATCH( LARGE( INDEX('Project Assignment Check'!$G:$ZX, MATCH($A26, 'Project Assignment Check'!$A:$A, 0), ), COLUMN()-4 ), INDEX('Project Assignment Check'!$G:$ZX, MATCH($A26, 'Project Assignment Check'!$A:$A, 0), ), 0 ) ), "" ) | I26: =IFERROR( INDEX('Project Assignment Check'!$G$1:$ZX$1, MATCH( LARGE( INDEX('Project Assignment Check'!$G:$ZX, MATCH($A26, 'Project Assignment Check'!$A:$A, 0), ), COLUMN()-4 ), INDEX('Project Assignment Check'!$G:$ZX, MATCH($A26, 'Project Assignment Check'!$A:$A, 0), ), 0 ) ), "" ) | J26: =IFERROR( INDEX('Project Assignment Check'!$G$1:$ZX$1, MATCH( LARGE( INDEX('Project Assignment Check'!$G:$ZX, MATCH($A26, 'Project Assignment Check'!$A:$A, 0), ), COLUMN()-4 ), INDEX('Project Assignment Check'!$G:$ZX, MATCH($A26, 'Project Assignment Check'!$A:$A, 0), ), 0 ) ), "" )
A27: SRP8-026 | B27: Pedals | C27: Interior | E27: =IF(IFERROR( INDEX('Project Assignment Check'!$G$1:$ZX$1, MATCH( LARGE( INDEX('Project Assignment Check'!$G:$ZX, MATCH($A27, 'Project Assignment Check'!$A:$A, 0), ), COLUMN()-4 ), INDEX('Project Assignment Check'!$G:$ZX, MATCH($A27, 'Project Assignment Check'!$A:$A, 0), ), 0 ) ), "" ) = 0,"", IFERROR( INDEX('Project Assignment Check'!$G$1:$ZX$1, MATCH( LARGE( INDEX('Project Assignment Check'!$G:$ZX, MATCH($A27, 'Project Assignment Check'!$A:$A, 0), ), COLUMN()-4 ), INDEX('Project Assignment Check'!$G:$ZX, MATCH($A27, 'Project Assignment Check'!$A:$A, 0), ), 0 ) ), "" )) -> ADR-31 | F27: =IFERROR( INDEX('Project Assignment Check'!$G$1:$ZX$1, MATCH( LARGE( INDEX('Project Assignment Check'!$G:$ZX, MATCH($A27, 'Project Assignment Check'!$A:$A, 0), ), COLUMN()-4 ), INDEX('Project Assignment Check'!$G:$ZX, MATCH($A27, 'Project Assignment Check'!$A:$A, 0), ), 0 ) ), "" ) | G27: =IFERROR( INDEX('Project Assignment Check'!$G$1:$ZX$1, MATCH( LARGE( INDEX('Project Assignment Check'!$G:$ZX, MATCH($A27, 'Project Assignment Check'!$A:$A, 0), ), COLUMN()-4 ), INDEX('Project Assignment Check'!$G:$ZX, MATCH($A27, 'Project Assignment Check'!$A:$A, 0), ), 0 ) ), "" ) | H27: =IFERROR( INDEX('Project Assignment Check'!$G$1:$ZX$1, MATCH( LARGE( INDEX('Project Assignment Check'!$G:$ZX, MATCH($A27, 'Project Assignment Check'!$A:$A, 0), ), COLUMN()-4 ), INDEX('Project Assignment Check'!$G:$ZX, MATCH($A27, 'Project Assignment Check'!$A:$A, 0), ), 0 ) ), "" ) | I27: =IFERROR( INDEX('Project Assignment Check'!$G$1:$ZX$1, MATCH( LARGE( INDEX('Project Assignment Check'!$G:$ZX, MATCH($A27, 'Project Assignment Check'!$A:$A, 0), ), COLUMN()-4 ), INDEX('Project Assignment Check'!$G:$ZX, MATCH($A27, 'Project Assignment Check'!$A:$A, 0), ), 0 ) ), "" ) | J27: =IFERROR( INDEX('Project Assignment Check'!$G$1:$ZX$1, MATCH( LARGE( INDEX('Project Assignment Check'!$G:$ZX, MATCH($A27, 'Project Assignment Check'!$A:$A, 0), ), COLUMN()-4 ), INDEX('Project Assignment Check'!$G:$ZX, MATCH($A27, 'Project Assignment Check'!$A:$A, 0), ), 0 ) ), "" )
A28: SRP8-027 | B28: Ceiling | C28: Interior | D28: Chassis & Bodywork | E28: =IF(IFERROR( INDEX('Project Assignment Check'!$G$1:$ZX$1, MATCH( LARGE( INDEX('Project Assignment Check'!$G:$ZX, MATCH($A28, 'Project Assignment Check'!$A:$A, 0), ), COLUMN()-4 ), INDEX('Project Assignment Check'!$G:$ZX, MATCH($A28, 'Project Assignment Check'!$A:$A, 0), ), 0 ) ), "" ) = 0,"", IFERROR( INDEX('Project Assignment Check'!$G$1:$ZX$1, MATCH( LARGE( INDEX('Project Assignment Check'!$G:$ZX, MATCH($A28, 'Project Assignment Check'!$A:$A, 0), ), COLUMN()-4 ), INDEX('Project Assignment Check'!$G:$ZX, MATCH($A28, 'Project Assignment Check'!$A:$A, 0), ), 0 ) ), "" )) -> ADR-11 | F28: =IFERROR( INDEX('Project Assignment Check'!$G$1:$ZX$1, MATCH( LARGE( INDEX('Project Assignment Check'!$G:$ZX, MATCH($A28, 'Project Assignment Check'!$A:$A, 0), ), COLUMN()-4 ), INDEX('Project Assignment Check'!$G:$ZX, MATCH($A28, 'Project Assignment Check'!$A:$A, 0), ), 0 ) ), "" ) -> ADR-11 | G28: =IFERROR( INDEX('Project Assignment Check'!$G$1:$ZX$1, MATCH( LARGE( INDEX('Project Assignment Check'!$G:$ZX, MATCH($A28, 'Project Assignment Check'!$A:$A, 0), ), COLUMN()-4 ), INDEX('Project Assignment Check'!$G:$ZX, MATCH($A28, 'Project Assignment Check'!$A:$A, 0), ), 0 ) ), "" ) -> ADR-11 | H28: =IFERROR( INDEX('Project Assignment Check'!$G$1:$ZX$1, MATCH( LARGE( INDEX('Project Assignment Check'!$G:$ZX, MATCH($A28, 'Project Assignment Check'!$A:$A, 0), ), COLUMN()-4 ), INDEX('Project Assignment Check'!$G:$ZX, MATCH($A28, 'Project Assignment Check'!$A:$A, 0), ), 0 ) ), "" ) | I28: =IFERROR( INDEX('Project Assignment Check'!$G$1:$ZX$1, MATCH( LARGE( INDEX('Project Assignment Check'!$G:$ZX, MATCH($A28, 'Project Assignment Check'!$A:$A, 0), ), COLUMN()-4 ), INDEX('Project Assignment Check'!$G:$ZX, MATCH($A28, 'Project Assignment Check'!$A:$A, 0), ), 0 ) ), "" ) | J28: =IFERROR( INDEX('Project Assignment Check'!$G$1:$ZX$1, MATCH( LARGE( INDEX('Project Assignment Check'!$G:$ZX, MATCH($A28, 'Project Assignment Check'!$A:$A, 0), ), COLUMN()-4 ), INDEX('Project Assignment Check'!$G:$ZX, MATCH($A28, 'Project Assignment Check'!$A:$A, 0), ), 0 ) ), "" )
A29: SRP8-028 | B29: Central Display | C29: Interior | D29: Chassis & Bodywork | E29: =IF(IFERROR( INDEX('Project Assignment Check'!$G$1:$ZX$1, MATCH( LARGE( INDEX('Project Assignment Check'!$G:$ZX, MATCH($A29, 'Project Assignment Check'!$A:$A, 0), ), COLUMN()-4 ), INDEX('Project Assignment Check'!$G:$ZX, MATCH($A29, 'Project Assignment Check'!$A:$A, 0), ), 0 ) ), "" ) = 0,"", IFERROR( INDEX('Project Assignment Check'!$G$1:$ZX$1, MATCH( LARGE( INDEX('Project Assignment Check'!$G:$ZX, MATCH($A29, 'Project Assignment Check'!$A:$A, 0), ), COLUMN()-4 ), INDEX('Project Assignment Check'!$G:$ZX, MATCH($A29, 'Project Assignment Check'!$A:$A, 0), ), 0 ) ), "" )) -> ADR-21 | F29: =IFERROR( INDEX('Project Assignment Check'!$G$1:$ZX$1, MATCH( LARGE( INDEX('Project Assignment Check'!$G:$ZX, MATCH($A29, 'Project Assignment Check'!$A:$A, 0), ), COLUMN()-4 ), INDEX('Project Assignment Check'!$G:$ZX, MATCH($A29, 'Project Assignment Check'!$A:$A, 0), ), 0 ) ), "" ) -> ADR-21 | G29: =IFERROR( INDEX('Project Assignment Check'!$G$1:$ZX$1, MATCH( LARGE( INDEX('Project Assignment Check'!$G:$ZX, MATCH($A29, 'Project Assignment Check'!$A:$A, 0), ), COLUMN()-4 ), INDEX('Project Assignment Check'!$G:$ZX, MATCH($A29, 'Project Assignment Check'!$A:$A, 0), ), 0 ) ), "" ) | H29: =IFERROR( INDEX('Project Assignment Check'!$G$1:$ZX$1, MATCH( LARGE( INDEX('Project Assignment Check'!$G:$ZX, MATCH($A29, 'Project Assignment Check'!$A:$A, 0), ), COLUMN()-4 ), INDEX('Project Assignment Check'!$G:$ZX, MATCH($A29, 'Project Assignment Check'!$A:$A, 0), ), 0 ) ), "" ) | I29: =IFERROR( INDEX('Project Assignment Check'!$G$1:$ZX$1, MATCH( LARGE( INDEX('Project Assignment Check'!$G:$ZX, MATCH($A29, 'Project Assignment Check'!$A:$A, 0), ), COLUMN()-4 ), INDEX('Project Assignment Check'!$G:$ZX, MATCH($A29, 'Project Assignment Check'!$A:$A, 0), ), 0 ) ), "" ) | J29: =IFERROR( INDEX('Project Assignment Check'!$G$1:$ZX$1, MATCH( LARGE( INDEX('Project Assignment Check'!$G:$ZX, MATCH($A29, 'Project Assignment Check'!$A:$A, 0), ), COLUMN()-4 ), INDEX('Project Assignment Check'!$G:$ZX, MATCH($A29, 'Project Assignment Check'!$A:$A, 0), ), 0 ) ), "" )
A30: SRP8-029 | B30: Driver Display | C30: Interior | D30: Embedded Systems | E30: =IF(IFERROR( INDEX('Project Assignment Check'!$G$1:$ZX$1, MATCH( LARGE( INDEX('Project Assignment Check'!$G:$ZX, MATCH($A30, 'Project Assignment Check'!$A:$A, 0), ), COLUMN()-4 ), INDEX('Project Assignment Check'!$G:$ZX, MATCH($A30, 'Project Assignment Check'!$A:$A, 0), ), 0 ) ), "" ) = 0,"", IFERROR( INDEX('Project Assignment Check'!$G$1:$ZX$1, MATCH( LARGE( INDEX('Project Assignment Check'!$G:$ZX, MATCH($A30, 'Project Assignment Check'!$A:$A, 0), ), COLUMN()-4 ), INDEX('Project Assignment Check'!$G:$ZX, MATCH($A30, 'Project Assignment Check'!$A:$A, 0), ), 0 ) ), "" )) -> ADR-18 | F30: =IFERROR( INDEX('Project Assignment Check'!$G$1:$ZX$1, MATCH( LARGE( INDEX('Project Assignment Check'!$G:$ZX, MATCH($A30, 'Project Assignment Check'!$A:$A, 0), ), COLUMN()-4 ), INDEX('Project Assignment Check'!$G:$ZX, MATCH($A30, 'Project Assignment Check'!$A:$A, 0), ), 0 ) ), "" ) -> ADR-18 | G30: =IFERROR( INDEX('Project Assignment Check'!$G$1:$ZX$1, MATCH( LARGE( INDEX('Project Assignment Check'!$G:$ZX, MATCH($A30, 'Project Assignment Check'!$A:$A, 0), ), COLUMN()-4 ), INDEX('Project Assignment Check'!$G:$ZX, MATCH($A30, 'Project Assignment Check'!$A:$A, 0), ), 0 ) ), "" ) -> ADR-18 | H30: =IFERROR( INDEX('Project Assignment Check'!$G$1:$ZX$1, MATCH( LARGE( INDEX('Project Assignment Check'!$G:$ZX, MATCH($A30, 'Project Assignment Check'!$A:$A, 0), ), COLUMN()-4 ), INDEX('Project Assignment Check'!$G:$ZX, MATCH($A30, 'Project Assignment Check'!$A:$A, 0), ), 0 ) ), "" ) -> ADR-18 | I30: =IFERROR( INDEX('Project Assignment Check'!$G$1:$ZX$1, MATCH( LARGE( INDEX('Project Assignment Check'!$G:$ZX, MATCH($A30, 'Project Assignment Check'!$A:$A, 0), ), COLUMN()-4 ), INDEX('Project Assignment Check'!$G:$ZX, MATCH($A30, 'Project Assignment Check'!$A:$A, 0), ), 0 ) ), "" ) -> ADR-18 | J30: =IFERROR( INDEX('Project Assignment Check'!$G$1:$ZX$1, MATCH( LARGE( INDEX('Project Assignment Check'!$G:$ZX, MATCH($A30, 'Project Assignment Check'!$A:$A, 0), ), COLUMN()-4 ), INDEX('Project Assignment Check'!$G:$ZX, MATCH($A30, 'Project Assignment Check'!$A:$A, 0), ), 0 ) ), "" ) -> ADR-18
